Workbook

Sheet 2025年12月收支财务报表
C1: 2025年12月收支财务报表
C4: 财务统计 STATISTICS | G4: 12月收支明细 DETAIL | S4: =SUMIF(M:M,"广告配套",N:N) -> 5179.6729 | T4: U支出的广告配套（不含RMB支出）
G5: 序号 | H5: 日期 | I5: 收入 | M5: 支出
C6: 月份查询 | I6: 项目 | J6: 金额 | K6: 备注 | L6: 时间 | M6: 项目 | N6: 金额 | O6: 备注 | P6: 时间 | S6: =SUMIF(M:M,"后勤支出",N:N) -> 25910.27 | T6: 后勤支出
C7: 12月 | D7: ▼ | G7: 1 | H7: 45992 | I7: 11月结余 | J7: ='2025年11月收支财务报表'!C25 -> 26016.496 | S7: =SUMIF(M:M,"fb三不限10➕1Nancy",N:N) -> 2780.13 | T7: fb三不限10➕1Nancy | V7: =SUMIF(M:M,"wade shen 美金谷歌户25+5%",N:N) -> 0 | W7: wade shen 美金谷歌户
C8: 收入 | G8: 2 | H8: 45992 | M8: 广告配套 | N8: 50 | O8: BM*10 | P8: 0.44097222 | S8: =SUMIF(M:M,"B哥&谷歌充值9➕1Nancy",N:N) -> 320 | T8: B哥&谷歌充值9➕1Nancy
C9: =C21 -> 220076.63 | G9: 3 | H9: 45992 | M9: 广告配套 | N9: 14.24 | O9: 谷歌邮箱*8 | P9: 0.47013889 | S9: =SUMIF(M:M,"SZ_TK下户Chris Ryan",N:N) -> 474.28 | T9: SZ_TK下户Chris Ryan
C10: 支出 | G10: 4 | H10: 45992 | I10: 海总-新加坡、加拿大 | J10: 4000 | L10: 0.67569444 | M10: 广告配套 | N10: 288.86 | O10: IP: 40个 | P10: 0.45694444 | S10: =SUMIF(M:M,"印度企业户 欧洲美金户下户",N:N) -> 1140 | T10: 印度企业户 欧洲美金户下户 | V10: =SUMIF(M:M,"GT&SHEN 欧洲户新",N:N) -> 0 | W10: GT&SHEN 欧洲户新
C11: =C23 -> 198049.19 | G11: 5 | H11: 45992 | M11: 印度企业户 欧洲美金户下户 | N11: 1140 | O11: 1000*1.14=1140 | P11: 0.46111111 | S11: =SUMIF(M:M,"Y-5208 FB欧/美户",N:N) -> 4382.82 | T11: Y-5208 FB欧/美户 | V11: =SUMIF(M:M,"GT&papa 二不限",N:N) -> 0 | W11: GT&papa 二不限新
C12: 结余 | G12: 6 | H12: 45992 | M12: fb三不限10➕1Nancy | N12: 669.75 | O12: 1000*1.111-441.25=669.75 | P12: 5.0604167 | S12: =SUMIF(M:M,"谷歌共享户/老户",N:N) -> 1200 | T12: 谷歌共享户/老户
C13: =C9-C11 -> 22027.436 | G13: 7 | H13: 45993 | M13: SZ_TK下户Chris Ryan | N13: 474.28 | O13: (700-290.3)*1.06开户费+20*2=474.28 | P13: 0.94375 | S13: =SUMIF(M:M,"路人互动",N:N) -> 221.12 | T13: 路人互动 | V13: =SUMIF(M:M,"GT&SHEN 谷歌原生账单户",N:N) -> 0 | W13: GT&SHEN 谷歌原生账单户
G14: 8 | H14: 45994 | M14: 广告配套 | N14: 54.3 | O14: ADS续费 | P14: 0.48055556 | S14: =SUMIF(M:M,"志诚三不限",N:N) -> 3679.96 | T14: 志诚三不限
C15: 任意时段查询 | G15: 9 | H15: 45994 | M15: 后勤支出 | N15: 580.6 | O15: 580.6，ZZY的周结算11/22-11/30 | P15: 0.59375 | S15: =SUMIF(M:M,"路人互动系统",N:N) -> 643.86 | T15: 路人互动系统 | V15: =SUMIF(M:M,"启航",N:N) -> 0 | W15: 启航
C16: 起始日期： | G16: 10 | H16: 45994 | M16: 广告配套 | N16: 225 | O16: 防护续费 | P16: 0.59513889 | S16: =SUMIF(M:M,"GT&papa欧",N:N) -> 552.84 | T16: GT&papa欧 | V16: =SUMIF(M:M,"印度户印尼企业户",N:N) -> 0 | W16: 印度户印尼企业户
C17: 45292 | G17: 11 | H17: 45994 | M17: Y-5208 FB欧/美户 | N17: 320.04 | O17: ZZ 2900.38+309.0418-3,444.38=-234.9582；SZ 500*1.11=555 | P17: 0.61666667 | S17: =SUMIF(M:M,"星链-AdNova",N:N) -> 5629.83 | T17: 星链-AdNova | V17: =SUMIF(M:M,"海总新渠道",N:N) -> 0 | W17: 海总新渠道
C18: 结束日期： | G18: 12 | H18: 45994 | M18: 谷歌共享户/老户 | N18: 100 | O18: 开户费50*2=100 | P18: 0.68263889 | S18: =SUMIF(M:M,"大鱼速汇",N:N) -> 1010 | T18: 大鱼速汇 | V18: =SUMIF(M:M,"GT&海总 欧洲金融户",N:N) -> 0 | W18: GT&海总 欧洲金融户
C19: 72805 | G19: 13 | H19: 45994 | M19: Y-5208 FB欧/美户 | N19: 2775 | O19: 500*5*1.11=2775 | P19: 0.75694444 | S19: =SUMIF(M:M,"VCC-新系统",N:N) -> 4444 | T19: VCC-新系统 | V19: =SUMIF(M:M,"海总-黑泽",N:N) -> 0 | W19: 海总-黑泽
C20: 收入 | G20: 14 | H20: 45994 | M20: 路人互动系统 | N20: 107.68 | O20: 开户费50*2+随机金额0.68+6.55*1.07=107.68 | P20: 0.92013889 | S20: =SUMIF(M:M,"谷歌-饭团",N:N) -> 2260.2375 | T20: 谷歌-饭团
C21: =SUMIFS(J:J,H:H,">="&$C$17,H:H,"<="&$C$19) -> 220076.63 | G21: 15 | H21: 45995 | M21: 广告配套 | N21: 50 | O21: 工单 | P21: 0.68611111 | S21: =SUMIF(M:M,"风口猪充值广告费",N:N) -> 4687.84 | T21: 风口猪11月充值广告费
C22: 支出 | G22: 16 | H22: 45995 | M22: 志诚三不限 | N22: 1279.57 | O22: 182.1+1248.7+19*50+1690+1061.9-3853.13=1,279.57 | P22: 0.79166667 | S22: =SUMIF(M:M,"Anthony - FKZ - 6,5%",N:N) -> 213 | T22: Anthony - FKZ - 6,5% | V22: =SUMIF(M:M,"TK下户hailey",N:N) -> 0 | W22: TK下户hailey
C23: =SUMIFS(N:N,H:H,">="&$C$17,H:H,"<="&$C$19) -> 198049.19 | G23: 17 | H23: 45995 | M23: 谷歌共享户/老户 | N23: 1100 | O23: 500*2*1.10=1100 | P23: 21：02 | S23: =SUMIF(M:M,"Lolo - FKZ (~5% | dating)",N:N) -> 105 | T23: Lolo - FKZ (~5% | dating)
C24: 结余 | G24: 18 | H24: 45995 | M24: 路人互动 | N24: 221.12 | O24: （500-433.53）*1.07+开户费50*3=221.12 | P24: 0.87986111 | S24: =SUMIF(M:M,"十月二不限——（泰华）",N:N) -> 396 | T24: 十月二不限——（泰华） | V24: =SUMIF(M:M,"SZ-2_TK广告户-村长",N:N) -> 0 | W24: SZ-2_TK广告户-村长
C25: =C21-C23 -> 22027.436 | G25: 19 | H25: 45996 | I25: F2新加坡 | J25: 2400 | L25: 0.95694444 | M25: 广告配套 | N25: 255.1329 | O25: VPN续费 | P25: 0.43194444 | S25: =SUMIF(M:M,"二不限企业户",N:N) -> 483 | T25: 二不限企业户Makie
G26: 20 | H26: 45996 | M26: fb三不限10➕1Nancy | N26: 599.95 | O26: （500-4.99）*1.1*1.01+开户费50=599.95 | P26: 0.46875 | S26: =SUMIF(M:M,"凤凰渠道-泰华",N:N) -> 8226.19 | T26: 凤凰渠道-泰华
G27: 21 | H27: 45996 | M27: fb三不限10➕1Nancy | N27: 630.25 | O27: 500*1.05*1.01+开户费50*2=630.25 | P27: 0.57708333 | S27: =SUMIF(M:M,"风口猪12月充值广告费",N:N) -> 2167.81 | T27: 风口猪12月充值广告费
G28: 22 | H28: 45996 | M28: 广告配套 | N28: 14 | O28: 认证主页+普通主页 | P28: 0.75972222 | S28: =SUMIF(M:M,"流苏",N:N) -> 54600 | T28: 流苏
G29: 23 | H29: 45996 | M29: 广告配套 | N29: 2277.23 | O29: 明细：个号：60；中文认证主页：12；认证主页：109；主页：2；复审主页：6；复审BM：10 | P29: 0.76319444 | S29: =SUMIF(M:M,"岳总",N:N) -> 23250 | T29: 岳总
G30: 24 | H30: 45997 | M30: GT&papa欧 | N30: 140 | O30: 开户费20*7=140 | P30: 0.60277778 | S30: =SUMIF(M:M,"渠道106-本土fb🇯🇵",N:N) -> 29160 | T30: 渠道106-本土fb🇯🇵
G31: 25 | H31: 45997 | M31: Y-5208 FB欧/美户 | N31: 737.78 | O31: 其中SZ 500*1.11=555；DUNG备用金：500；Mad-shahe备用金：500；RED待付：（425.42-500）*1.11=82.78；ne待付：500*1.11=555；SP待付 ：1100；总待付：82.78+555+1100-500-500=737.78 | P31: 0.63055556 | S31: =SUMIF(M:M,"华侨粉测试 ",N:N) -> 2200 | T31: 华侨粉测试
G32: 26 | H32: 45997 | M32: 星链-AdNova | N32: 2166.93 | O32: SZ 开户费5*60+(1200-少算100-804.69)*1.08+上面的1,548.01=2,166.94 | P32: 0.69652778 | S32: =SUMIF(M:M,"印度资金测试",N:N) -> 12405 | T32: 印度资金测试
G33: 27 | H33: 45998 | I33: 海总-新加坡、加拿大 | J33: 4000 | L33: 0.82430556 | S33: =SUMIF(M:M,"官方授权户-15",N:N) -> 326.33 | T33: 官方授权户-15
G34: 28 | H34: 45999 | M34: 大鱼速汇 | N34: 101 | O34: 100*1.01=101 | P34: 0.44236111
G35: 29 | H35: 45999 | I35: 印度资金测试 | J35: 20000 | L35: 0.64722222 | M35: 谷歌-饭团 | N35: 373.2375 | O35: (500-163.75)*1.11=373.2375 | P35: 0.66319444
G36: 30 | H36: 45999 | M36: 大鱼速汇 | N36: 101 | O36: 100*1.01=101 | P36: 0.68194444
G37: 31 | H37: 45999 | M37: Y-5208 FB欧/美户 | N37: 550 | O37: 500*1.1=550 | P37: 0.70625
G38: 32 | H38: 45999 | M38: B哥&谷歌充值9➕1Nancy | N38: 320 | O38: 200*1.1+开户费100=320 | P38: 0.72569444
G39: 33 | H39: 45999 | I39: 华侨老头粉 | J39: 2200 | L39: 0.87916667 | M39: 华侨粉测试 | N39: 1100 | P39: 0.88958333
G40: 34 | H40: 46000 | M40: 路人互动系统 | N40: 107.17 | O40: 100*1.07+随机金额0.17=107.17 | P40: 0.44513889 | S40: =SUM(S4:S39) -> 198049.19 | T40: =C23-S40 -> 0
G41: 35 | H41: 46000 | M41: 大鱼速汇 | N41: 202 | O41: 200*1.01=202 | P41: 0.67222222
G42: 36 | H42: 46000 | M42: GT&papa欧 | N42: 283.84 | O42: SZ (50-29.6)*1.09=22.24；ZZ 240*1.09=261.6 | P42: 0.68888889 | S42: 往上支出-------------------分割线-------------------往下收入
G43: 37 | H43: 46000 | I43: 海总-新加坡、加拿大 | J43: 10000 | L43: 0.7125 | M43: 广告配套 | N43: 25 | O43: BM*5 | P43: 0.8375
G44: 38 | H44: 46001 | M44: GT&papa欧 | N44: 109 | O44: 100*1.09=109 | P44: 0.44166667 | S44: =SUMIF(I:I,"海总-新加坡、加拿大",J:J) -> 48000 | T44: 海总-新加坡、加拿大
G45: 39 | H45: 46001 | M45: 广告配套 | N45: 25 | O45: BM*5 | P45: 0.45486111 | S45: =SUMIF(I:I,"F2新加坡",J:J) -> 20900 | T45: F2新加坡
G46: 40 | H46: 46001 | M46: Anthony - FKZ - 6,5% | N46: 213 | O46: 200*1.065=213 | P46: 0.64166667 | S46: =SUMIF(I:I,"印度资金测试",J:J) -> 20000 | T46: 印度资金测试
G47: 41 | H47: 46001 | M47: 华侨粉测试 | N47: 1100 | P47: 0.64513889 | S47: =SUMIF(I:I,"华侨老头粉",J:J) -> 2200 | T47: 华侨老头粉
G48: 42 | H48: 46001 | M48: Lolo - FKZ (~5% | dating) | N48: 105 | O48: 100*1.05=105U | P48: 0.66736111 | S48: =SUMIF(I:I,"渠道106-不土FB🇯🇵",J:J) -> 90000 | T48: 渠道106-不土FB🇯🇵
G49: 43 | H49: 46001 | M49: 风口猪充值广告费 | N49: 4687.84 | O49: 10-11月支出的广告费：共计：4687.84 | P49: 0.72777778 | S49: =SUMIF(I:I,"F2加拿大TK",J:J) -> 3900 | T49: F2加拿大TK
G50: 44 | H50: 46001 | M50: 十月二不限——（泰华） | N50: 396 | O50: 300*1.02+30*3开户费=396 | P50: 0.74166667 | S50: =SUMIF(I:I,"巴西1期",J:J) -> 3200 | T50: 巴西1期
G51: 45 | H51: 46001 | M51: 大鱼速汇 | N51: 202 | O51: 200*1.01=202 | P51: 0.79583333
G52: 46 | H52: 46001 | M52: 广告配套 | N52: 288.86 | O52: IP: 40个 | P52: 0.85416667
G53: 47 | H53: 46001 | M53: 谷歌-饭团 | N53: 666 | O53: 600*1.11=666 | P53: 0.86041667
G54: 48 | H54: 46002 | M54: 路人互动系统 | N54: 107.25 | O54: 100*1.07+随机金额0.25=107.25 | P54: 0.65277778
G55: 49 | H55: 46002 | M55: 广告配套 | N55: 25 | O55: BM*5 | P55: 0.66875
G56: 50 | H56: 46002 | I56: 海总-新加坡、加拿大 | J56: 10000 | L56: 0.67916667 | M56: 渠道106-本土fb🇯🇵 | N56: 29160 | O56: 10-11月的退款 | P56: 0.76458333 | S56: =SUMIF(I:I,"路人互动",J:J) -> 1448.89 | T56: 路人互动
G57: 51 | H57: 46002 | M57: 二不限企业户 | N57: 483 | O57: 471.23 *1.025=483 | P57: 0.80138889 | S57: =SUMIF(I:I,"谷歌共享户/老户",J:J) -> 998 | T57: 谷歌共享户/老户
G58: 52 | H58: 46002 | I58: 渠道106-不土FB🇯🇵 | J58: 18000 | L58: 0.81388889 | M58: 岳总 | N58: 7500 | P58: 0.82430556 | S58: =SUMIF(I:I,"启航",J:J) -> 2067.02 | T58: 启航
G59: 53 | H59: 46003 | I59: F2新加坡 | J59: 6000 | L59: 0.013194444 | M59: 谷歌-饭团 | N59: 1221 | O59: 1100*1.11=1221 | P59: 0.81805556 | S59: =SUMIF(I:I,"华侨粉测试 ",J:J) -> 355.971 | T59: 华侨粉测试
G60: 54 | H60: 46004 | I60: 印度企业户 欧洲美金户下户 | J60: 990.25 | L60: 0.86736111 | M60: 广告配套 | N60: 25 | O60: BM*5 | P60: 0.4625 | S60: =SUMIF(I:I,"印度企业户 欧洲美金户下户",J:J) -> 990.25 | T60: 印度企业户 欧洲美金户下户
G61: 55 | H61: 46004 | M61: 广告配套 | N61: 12.05 | O61: 谷歌邮箱*8 | P61: 0.47430556 | S61: =J7 -> 26016.496 | T61: 11月结余
G62: 56 | H62: 46004 | I62: F2新加坡 | J62: 6000 | L62: 0.89652778 | S62: =SUM(S44:S61) -> 220076.63
G63: 57 | H63: 46004 | I63: 渠道106-不土FB🇯🇵 | J63: 18000 | L63: 0.92083333 | M63: 流苏 | N63: 7500 | P63: 0.97916667 | T63: =S62-C21 -> 0
G64: 58 | H64: 46005 | M64: 岳总 | N64: 8550 | P64: 0.58333333
G65: 59 | H65: 46005 | M65: 凤凰渠道-泰华 | N65: 3107.96 | O65: 3700+706-1298.04=3107.96 | P65: 0.68472222
G66: 60 | H66: 46005 | I66: 渠道106-不土FB🇯🇵 | J66: 18000 | L66: 0.83125
G67: 61 | H67: 46006 | M67: 星链-AdNova | N67: 3462.9 | O67: (4100-893.62)*1.08+0.01=3,462.9 | P67: 0.43194444
G68: 62 | H68: 46006 | M68: 流苏 | N68: 7500 | P68: 0.44444444
G69: 63 | H69: 46006 | M69: 广告配套 | N69: 25 | O69: BM*5 | P69: 0.46736111
G70: 64 | H70: 46006 | M70: 广告配套 | N70: 1450 | O70: 明细：个号：40；认证主页：68；复审主页：1；BM：1；中文认证主页：5；TK白号：3；复审BM：15 | P70: 0.47361111
G71: 65 | H71: 46006 | M71: 后勤支出 | N71: 10 | O71: 发工资 | P71: 0.64791667
G72: 66 | H72: 46006 | M72: 后勤支出 | N72: 1126.76 | O72: 发工资 | P72: 0.65138889
G73: 67 | H73: 46006 | M73: 后勤支出 | N73: 720.23 | O73: 发工资 | P73: 0.65277778
G74: 68 | H74: 46006 | M74: 后勤支出 | N74: 1126.76 | O74: 发工资 | P74: 0.65555556
G75: 69 | H75: 46006 | M75: 后勤支出 | N75: 10 | O75: 发工资 | P75: 0.65625
G76: 70 | H76: 46006 | M76: 后勤支出 | N76: 10 | O76: 发工资 | P76: 0.65763889
G77: 71 | H77: 46006 | M77: 后勤支出 | N77: 263.38 | O77: 发工资 | P77: 0.66180556
G78: 72 | H78: 46006 | M78: 后勤支出 | N78: 566.5 | O78: 发工资 | P78: 0.66319444
G79: 73 | H79: 46006 | M79: 后勤支出 | N79: 950.62 | O79: 发工资 | P79: 0.66527778
G80: 74 | H80: 46006 | M80: 后勤支出 | N80: 1524.08 | O80: 发工资 | P80: 0.66666667
... G87: 81 | H87: 46006 | M87: 后勤支出 | N87: 703.62 | O87: 发工资 | P87: 0.67777778
G88: 82 | H88: 46006 | I88: 华侨粉测试 | J88: 355.971 | L88: 0.71319444 | M88: 后勤支出 | N88: 144.93 | O88: 发工资 | P88: 0.71458333
G89: 83 | H89: 46006 | M89: GT&papa欧 | N89: 20 | O89: 开户费20 | P89: 0.72291667
G90: 84 | H90: 46006 | I90: 海总-新加坡、加拿大 | J90: 10000 | L90: 17：21 | M90: 后勤支出 | N90: 1221.55 | O90: 发工资 | P90: 0.75
G91: 85 | H91: 46006 | M91: 大鱼速汇 | N91: 101 | O91: 100*1.01=101 | P91: 0.79861111
G92: 86 | H92: 46006 | M92: 后勤支出 | N92: 617.89 | O92: 发工资 | P92: 0.80138889
G93: 87 | H93: 46006 | M93: 后勤支出 | N93: 6000 | O93: 换汇RMB | P93: 0.80694444
G94: 88 | H94: 46006 | M94: VCC-新系统 | N94: 101 | O94: 100*1.01=101 | P94: 0.84236111
G95: 89 | H95: 46006 | M95: 后勤支出 | N95: 610.54 | O95: SZ2-ZZY 周结算12.1-12.14支出 $610.54 | P95: 0.88263889
G96: 90 | H96: 46006 | I96: 启航 | J96: 2067.02 | L96: 0.90763889
G97: 91 | H97: 46006 | I97: 渠道106-不土FB🇯🇵 | J97: 18000 | L97: 0.93680556 | M97: 流苏 | N97: 5550 | P97: 0.99166667
G98: 92 | H98: 46006 | M98: 岳总 | N98: 7200 | P98: 0.99444444
G99: 93 | H99: 46007 | M99: 广告配套 | N99: 25 | O99: BM*5 | P99: 0.62083333
G100: 94 | H100: 46007 | M100: 志诚三不限 | N100: 917.15 | O100: 开户费760+2190+194.1+SZ117.56-2344.51=917.15 | P100: 0.67083333
G101: 95 | H101: 46007 | M101: 流苏 | N101: 7500 | P101: 16：11
G102: 96 | H102: 46007 | I102: 海总-新加坡、加拿大 | J102: 10000 | L102: 0.71111111 | M102: VCC-新系统 | N102: 101 | O102: 100*1.01=101 | P102: 0.78541667
G103: 97 | H103: 46007 | M103: 大鱼速汇 | N103: 101 | O103: 合并付款 | P103: 0.83888889
G104: 98 | H104: 46007 | M104: VCC-新系统 | N104: 202 | O104: 合并付款 | P104: 0.83888889
G105: 99 | H105: 46007 | M105: fb三不限10➕1Nancy | N105: 703.39 | O105: 600*1.05*1.01+67.09=703.39 | P105: 0.89513889
G106: 100 | H106: 46007 | I106: F2加拿大TK | J106: 3900 | L106: 0.97361111 | M106: 流苏 | N106: 5850 | P106: 0.97430556
G107: 101 | H107: 46008 | M107: 路人互动系统 | N107: 107.49 | O107: 随机金额0.49+100*1.07=107.49 | P107: 0.49027778
G108: 102 | H108: 46008 | M108: VCC-新系统 | N108: 505 | O108: 500*1.01=505 | P108: 0.57916667
...

Sheet 2025年11月收支财务报表
C1: 2025年11月收支财务报表
C4: 财务统计 STATISTICS | G4: 11月收支明细 DETAIL | S4: =SUMIF(M:M,"广告配套",N:N) -> 8873.59 | T4: U支出的广告配套（不含RMB支出）
G5: 序号 | H5: 日期 | I5: 收入 | M5: 支出
C6: 月份查询 | I6: 项目 | J6: 金额 | K6: 备注 | L6: 时间 | M6: 项目 | N6: 金额 | O6: 备注 | P6: 时间 | S6: =SUMIF(M:M,"后勤支出",N:N) -> 190060.25 | T6: 后勤支出
C7: 11月 | D7: ▼ | G7: 1 | H7: 45962 | I7: 10月结余 | J7: ='2025年10月收支财务报表'!C25 -> 221029.65 | M7: fb三不限10➕1Nancy | N7: 1150 | O7: 1000*1.11=1110+40=1150 | P7: 0.46805556 | S7: =SUMIF(M:M,"凤凰渠道-泰华",N:N) -> 2220 | T7: 凤凰渠道-泰华
C8: 收入 | G8: 2 | H8: 45962 | M8: GT&SHEN 欧洲户新 | N8: 218 | O8: ZZ 100*1.09=109：SZ 100*1.09=109 | P8: 0.62916667 | S8: =SUMIF(M:M,"wade shen 美金谷歌户25+5%",N:N) -> 633.93 | T8: wade shen 美金谷歌户 | U8: 已退
C9: =C21 -> 357273.99 | G9: 3 | H9: 45962 | I9: 渠道106-本土fb🇯🇵 | J9: 18000 | L9: 0.65694444 | M9: 岳总 | N9: 7500 | P9: 0.65972222 | S9: =SUMIF(M:M,"二不限企业户",N:N) -> 1414.78 | T9: 二不限企业户Makie | U9: 11/14 管控
C10: 支出 | G10: 4 | H10: 45962 | M10: GT&papa 二不限 | N10: 104 | O10: ZZ 100*1.04=104 | P10: 0.70069444 | S10: =SUMIF(M:M,"星链-AdNova",N:N) -> 25845.872 | T10: 星链-AdNova
C11: =C23 -> 331257.5 | G11: 5 | H11: 45962 | M11: GT&papa 二不限 | N11: 208 | O11: SZ 200*1.04=208 | P11: 0.86875 | S11: =SUMIF(M:M,"GT&SHEN 欧洲户新",N:N) -> 218 | T11: GT&SHEN 欧洲户新 | U11: 余额转谷歌了
C12: 结余 | G12: 6 | H12: 45962 | M12: 岳总 | N12: 9150 | P12: 0.94722222 | S12: =SUMIF(M:M,"fb三不限10➕1Nancy",N:N) -> 5394.88 | T12: fb三不限10➕1Nancy
C13: =C9-C11 -> 26016.496 | G13: 7 | H13: 45963 | I13: 渠道106-本土fb🇯🇵 | J13: 36000 | L13: 0.55763889 | M13: 广告配套 | N13: 14.15 | O13: 谷歌邮箱*5 | P13: 0.58888889 | S13: =SUMIF(M:M,"GT&papa 二不限",N:N) -> 312 | T13: GT&papa 二不限新 | U13: 11/17 封控
G14: 8 | H14: 45963 | M14: 二不限企业户 | N14: 1414.78 | O14: -1380.27*1.025=-1414.78 | P14: 0.59652778 | S14: =SUMIF(M:M,"岳总",N:N) -> 31650 | T14: 岳总
C15: 任意时段查询 | G15: 9 | H15: 45963 | M15: 岳总 | N15: 15000 | P15: 0.6625 | S15: =SUMIF(M:M,"GT&SHEN 谷歌原生账单户",N:N) -> 50 | T15: GT&SHEN 谷歌原生账单户 | U15: 余额转谷歌了
C16: 起始日期： | G16: 10 | H16: 45963 | M16: 广告配套 | N16: 240 | O16: 20端口 | P16: 0.67291667 | S16: =SUMIF(M:M,"路人互动",N:N) -> 5809.98 | T16: 路人互动
C17: 45292 | G17: 11 | H17: 45964 | I17: 华飞-Alex（三不限）8+千分6 | J17: 200 | K17: 退款 | L17: 0.44583333 | M17: 广告配套 | N17: 66 | O17: BM：10 | P17: 0.47222222 | S17: =SUMIF(M:M,"启航",N:N) -> 4633.29 | T17: 启航
C18: 结束日期： | G18: 12 | H18: 45964 | M18: wade shen 美金谷歌户25+5% | N18: 633.93 | O18: SZ 1000-368.44*1.075-30=633.93 | P18: 0.48958333 | S18: =SUMIF(M:M,"印度户印尼企业户",N:N) -> 5779.89 | T18: 印度户印尼企业户
C19: 72805 | G19: 13 | H19: 45964 | M19: 广告配套 | N19: 14.15 | O19: 谷歌邮箱*5 | P19: 0.50902778 | S19: =SUMIF(M:M,"海总新渠道",N:N) -> 1665 | T19: 海总新渠道
C20: 收入 | G20: 14 | H20: 45964 | M20: GT&SHEN 谷歌原生账单户 | N20: 50 | O20: 开户费50 | P20: 0.54722222 | S20: =SUMIF(M:M,"GT&海总 欧洲金融户",N:N) -> 387.63 | T20: GT&海总 欧洲金融户
C21: =SUMIFS(J:J,H:H,">="&$C$17,H:H,"<="&$C$19) -> 357273.99 | G21: 15 | H21: 45964 | M21: 后勤支出 | N21: 15000 | O21: 换汇 | P21: 0.64375 | S21: =SUMIF(M:M,"海总-黑泽",N:N) -> 3720.1875 | T21: 海总-黑泽
C22: 支出 | G22: 16 | H22: 45964 | I22: bc 的广告费 | J22: 10000 | L22: 0.70416667 | M22: 广告配套 | N22: 288.86 | O22: IP: 40个 | P22: 0.82569444 | S22: =SUMIF(M:M,"Y-5208 FB欧/美户",N:N) -> 4335.69 | T22: Y-5208 FB欧/美户
C23: =SUMIFS(N:N,H:H,">="&$C$17,H:H,"<="&$C$19) -> 331257.5 | G23: 17 | H23: 45964 | M23: 凤凰渠道-泰华 | N23: 2220 | O23: ZZ 2000*1.11=2220 | P23: 0.99027778 | S23: =SUMIF(M:M,"志诚三不限",N:N) -> 4652.83 | T23: 志诚三不限
C24: 结余 | G24: 18 | H24: 45964 | I24: Alex & Doris_谷歌户 | J24: 941.2 | K24: 退款 | L24: 0.99097222 | M24: 广告配套 | N24: 14.14 | O24: 谷歌邮箱*5 | P24: 0.44861111 | S24: =SUMIF(M:M,"SZ_TK下户Chris Ryan",N:N) -> 6107.85 | T24: SZ_TK下户Chris Ryan
C25: =C21-C23 -> 26016.496 | G25: 19 | H25: 45965 | M25: fb三不限10➕1Nancy | N25: 1110 | O25: ZZ 1000*1.11=1110 | P25: 0.49652778 | S25: =SUMIF(M:M,"TK下户hailey",N:N) -> 255 | T25: TK下户hailey
G26: 20 | H26: 45965 | M26: 后勤支出 | N26: 12056.74 | O26: B哥半年房租 | P26: 0.45416667 | S26: =SUMIF(M:M,"大鱼速汇",N:N) -> 808 | T26: 大鱼速汇
G27: 21 | H27: 45966 | M27: 后勤支出 | N27: 2270.9003 | O27: 发工资 | P27: 0.62569444 | S27: =SUMIF(M:M,"SZ-2_TK广告户-村长",N:N) -> 160 | T27: SZ-2_TK广告户-村长
G28: 22 | H28: 45966 | M28: 后勤支出 | N28: 4867.4742 | O28: 发工资 | P28: 0.62777778 | S28: =SUMIF(M:M,"谷歌-饭团",N:N) -> 1247.752 | T28: 谷歌-饭团
G29: 23 | H29: 45966 | M29: 后勤支出 | N29: 3434.0034 | O29: 发工资 | P29: 0.62916667 | S29: =SUMIF(M:M,"bc 的广告费",N:N) -> 4231.1 | T29: bc 的广告费退款
G30: 24 | H30: 45966 | M30: 后勤支出 | N30: 5425.2755 | O30: 发工资 | P30: 0.63125 | S30: =SUMIF(M:M,"德国单粉—summer FB180",N:N) -> 16470 | T30: 德国单粉—summer FB180
G31: 25 | H31: 45966 | M31: 后勤支出 | N31: 2487.7651 | O31: 发工资 | P31: 0.63333333 | S31: =SUMIF(M:M,"渠道BF 德国F",N:N) -> 4320 | T31: 渠道BF 德国F
G32: 26 | H32: 45966 | M32: 后勤支出 | N32: 1646.5457 | O32: 发工资 | P32: 0.63402778
G33: 27 | H33: 45966 | M33: 后勤支出 | N33: 5000 | O33: 发工资 | P33: 0.63611111 | S33: =SUM(S4:S31) -> 331257.5
G34: 28 | H34: 45966 | M34: 后勤支出 | N34: 10 | O34: 发工资 | P34: 0.6375
G35: 29 | H35: 45966 | M35: 后勤支出 | N35: 10 | O35: 发工资 | P35: 0.63819444 | S35: 往上支出-------------------分割线-------------------往下收入
G36: 30 | H36: 45966 | M36: 后勤支出 | N36: 10 | O36: 发工资 | P36: 0.63958333
G37: 31 | H37: 45966 | M37: 后勤支出 | N37: 10 | O37: 发工资 | P37: 0.64027778 | S37: =SUMIF(I:I,"渠道106-本土fb🇯🇵",J:J) -> 54000 | T37: 渠道106-本土fb🇯🇵 | U37: =S37+'2025年10月收支财务报表'!S46 -> 95760
G38: 32 | H38: 45966 | M38: 后勤支出 | N38: 10 | O38: 发工资 | P38: 0.64097222 | S38: =SUMIF(I:I,"bc 的广告费",J:J) -> 10000 | T38: bc 的广告费
G39: 33 | H39: 45966 | M39: 后勤支出 | N39: 10 | O39: 发工资 | P39: 0.64166667 | S39: =SUMIF(I:I,"新K4",J:J) -> 1173.97 | T39: 新K4
G40: 34 | H40: 45966 | M40: 后勤支出 | N40: 10 | O40: 发工资 | P40: 0.64305556 | S40: =SUMIF(I:I,"瑞典1梯队（蟑螂哥）结算群",J:J) -> 3420 | T40: 瑞典1梯队（蟑螂哥）结算群
G41: 35 | H41: 45966 | M41: 后勤支出 | N41: 10 | O41: 发工资 | P41: 0.64375 | S41: =SUMIF(I:I,"海总-新加坡、加拿大",J:J) -> 6300 | T41: 海总-新加坡、加拿大
G42: 36 | H42: 45966 | M42: 后勤支出 | N42: 10 | O42: 发工资 | P42: 0.64444444 | S42: =SUMIF(I:I,"德国单粉—summer FB180",J:J) -> 38000 | T42: 德国单粉—summer FB180
G43: 37 | H43: 45966 | M43: 后勤支出 | N43: 2372.56 | O43: 发工资 | P43: 0.64722222 | S43: =SUMIF(I:I,"印尼二期",J:J) -> 7000 | T43: 印尼二期
G44: 38 | H44: 45966 | M44: 后勤支出 | N44: 1406.34 | O44: 发工资 | P44: 0.64861111
G45: 39 | H45: 45966 | M45: 后勤支出 | N45: 3605.09 | O45: 发工资 | P45: 0.65
G46: 40 | H46: 45966 | M46: 后勤支出 | N46: 1383.94 | O46: 发工资 | P46: 0.65208333
G47: 41 | H47: 45966 | M47: 后勤支出 | N47: 975.92 | O47: 发工资 | P47: 0.65416667
G48: 42 | H48: 45966 | M48: 后勤支出 | N48: 1116.76 | O48: 发工资 | P48: 0.65486111
G49: 43 | H49: 45966 | M49: 后勤支出 | N49: 804.23 | O49: 发工资 | P49: 0.65625
G50: 44 | H50: 45966 | M50: 后勤支出 | N50: 1116.76 | O50: 发工资 | P50: 0.65694444
G51: 45 | H51: 45966 | M51: 后勤支出 | N51: 376.19 | O51: 发工资 | P51: 0.65972222 | S51: =SUMIF(I:I,"海总新渠道",J:J) -> 1488.1 | T51: 海总新渠道
G52: 46 | H52: 45966 | I52: 岳总 | J52: 8400 | L52: 0.68680556 | M52: 后勤支出 | N52: 60083.847 | O52: B哥10月分红：133,519.66*0.45=60,083.847 | P52: 0.7 | S52: =SUMIF(I:I,"十月二不限",J:J) -> 225.12 | T52: 十月二不限
G53: 47 | H53: 45966 | M53: 广告配套 | N53: 66 | O53: BM：10 | P53: 0.74166667 | S53: =SUMIF(I:I,"星链-AdNova",J:J) -> 890.09 | T53: 星链-AdNova
G54: 48 | H54: 45966 | I54: 新K4 | J54: 1173.97 | K54: 总消耗：$1020.84 服务费15%: $153.13 金额：1020.84+153.13=$1173.97 | L54: 0.88541667 | S54: =SUMIF(I:I,"wade shen 美金谷歌户25+5%",J:J) -> 1200.73 | T54: wade shen 美金谷歌户25+5%
G55: 49 | H55: 45967 | M55: 广告配套 | N55: 225 | O55: 防护续费 | P55: 0.44097222 | S55: =SUMIF(I:I,"Alex_1011——谷歌原生户",J:J) -> 828 | T55: Alex_1011——谷歌原生户
G56: 50 | H56: 45967 | M56: 后勤支出 | N56: 1260.52 | O56: SZ公司支出报销 | P56: 0.56805556 | S56: =SUMIF(I:I,"泰华 & Bigad 谷歌老户 8+1",J:J) -> 1877.13 | T56: 泰华 & Bigad 谷歌老户 8+1
G57: 51 | H57: 45967 | I57: 瑞典1梯队（蟑螂哥）结算群 | J57: 360 | K57: 日期：11.05 用途：瑞典1梯队蟑螂哥渠道 单价：90 有效：4个 金额：90*4=360 | L57: 0.60486111 | M57: 渠道BF 德国F | N57: 4320 | O57: 退款 | P57: 0.675 | S57: =SUMIF(I:I,"谷歌-饭团",J:J) -> 300 | T57: 谷歌-饭团
G58: 52 | H58: 45967 | M58: 星链-AdNova | N58: 472 | O58: 400*1.08+开户费20*2=472 | P58: 0.79930556 | S58: =SUMIF(I:I,"岳总",J:J) -> 8400 | T58: 岳总
G59: 53 | H59: 45968 | M59: 广告配套 | N59: 66 | O59: BM：10 | P59: 0.68194444 | S59: =SUMIF(I:I,"Alex & Doris_谷歌户",J:J) -> 941.2 | T59: Alex & Doris_谷歌户
G60: 54 | H60: 45968 | M60: 广告配套 | N60: 792 | O60: 明细：老主页：1; 复审老主页：56； 认证主页：7；个号：41；二解号：1 | P60: 0.81388889 | S60: =SUMIF(I:I,"华飞-Alex（三不限）8+千分6",J:J) -> 200 | T60: 华飞-Alex（三不限）8+千分6
G61: 55 | H61: 45969 | M61: 星链-AdNova | N61: 1004 | O61: 开户费-4*20-BC2*30-800*1.08=-1004 | P61: 0.64027778 | S61: =J7 -> 221029.65 | T61: 10月结余
G62: 56 | H62: 45970 | M62: 路人互动 | N62: 200 | O62: 开户费200 | P62: 11；28 | S62: =SUM(S37:S61) -> 357273.99
G63: 57 | H63: 45970 | M63: fb三不限10➕1Nancy | N63: 1112.7 | O63: ZZ （1500-497.56）*1.11=1112.70 | P63: 0.51805556
G64: 58 | H64: 45971 | I64: 瑞典1梯队（蟑螂哥）结算群 | J64: 1620 | K64: 日期：11.08 用途：瑞典1梯队蟑螂哥渠道 单价：90 有效：18个 金额：90*18=1620 | L64: 0.12222222 | M64: 路人互动 | N64: 535 | O64: -500*1.07=-535 | P64: 0.45416667
G65: 59 | H65: 45971 | M65: 启航 | N65: 2961.23 | O65: ZZ 1500* 1.1/0.99=1,666.67；SZ 2000* 1.1/0.99-927.66=1,294.56 | P65: 0.47152778
G66: 60 | H66: 45971 | M66: 广告配套 | N66: 288.86 | O66: IP: 40个 | P66: 0.50347222
G67: 61 | H67: 45971 | I67: 谷歌-饭团 | J67: 300 | K67: 退款 | L67: 0.64305556 | M67: 广告配套 | N67: 66 | O67: BM：10 | P67: 0.72083333
G68: 62 | H68: 45971 | M68: 路人互动 | N68: 535 | O68: -500*1.07=-535 | P68: 0.775
G69: 63 | H69: 45971 | I69: 瑞典1梯队（蟑螂哥）结算群 | J69: 180 | K69: 日期：11.09 用途：瑞典1梯队蟑螂哥渠道 单价：90 有效：2个 金额：90*2=180 | L69: 0.78125 | M69: 印度户印尼企业户 | N69: 5779.89 | O69: 8720.22+707.62-3647.95=5779.89 | P69: 0.81666667
G70: 64 | H70: 45971 | M70: 后勤支出 | N70: 60083.847 | O70: 张总10月分红：133,519.66*0.45=60,083.847 | P70: 0.91875
G71: 65 | H71: 45972 | I71: 泰华 & Bigad 谷歌老户 8+1 | J71: 1877.13 | K71: 退款 | L71: 0.47013889 | M71: 路人互动 | N71: 535 | O71: -500*1.07=-535 | P71: 0.51527778
G72: 66 | H72: 45972 | M72: 星链-AdNova | N72: 718 | O72: 开户费-2*20-BC30-600*1.08=-718 | P72: 0.72777778
G73: 67 | H73: 45972 | M73: 路人互动 | N73: 535 | O73: -500*1.07=-535 | P73: 0.73333333
G74: 68 | H74: 45972 | M74: fb三不限10➕1Nancy | N74: 650.29 | O74: ZZ(1000-414.15)*1.11= 650.29 | P74: 0.73611111
G75: 69 | H75: 45972 | M75: 路人互动 | N75: 100 | O75: 开户费50*2 | P75: 0.81875
G76: 70 | H76: 45973 | M76: 广告配套 | N76: 28.31 | O76: 明细：谷歌邮箱*10 | P76: 0.36041667
G77: 71 | H77: 45973 | M77: 星链-AdNova | N77: 261.07 | O77: 开户费-2*20-(195.31-400)*1.08=-261.07 | P77: 0.53611111
G78: 72 | H78: 45973 | M78: GT&海总 欧洲金融户 | N78: 387.63 | O78: 500-147.61=352.39*1.1=387.63 | P78: 0.55763889
G79: 73 | H79: 45973 | M79: 海总新渠道 | N79: 1665 | O79: 500*1.11*3=1665 | P79: 0.65972222
G80: 74 | H80: 45973 | I80: 海总-新加坡、加拿大 | J80: 2000 | L80: 0.66805556
G81: 75 | H81: 45974 | M81: 海总-黑泽 | N81: 409.16 | O81: 3500+(3500-949.78)*0.0908+开户费30*13-3712.4=409.16 | P81: 0.43888889
G82: 76 | H82: 45974 | I82: Alex_1011——谷歌原生户 | J82: 828 | K82: 退款 | L82: 0.64375 | M82: 海总-黑泽 | N82: 545.4 | O82: 500*1.0908=545.4 | P82: 0.65416667
G83: 77 | H83: 45974 | I83: wade shen 美金谷歌户25+5% | J83: 1200.73 | L83: 0.68819444 | M83: 海总-黑泽 | N83: 545.4 | O83: 500*1.0908=545.4 | P83: 0.7
G84: 78 | H84: 45974 | M84: Y-5208 FB欧/美户 | N84: 452.87 | O84: 1000*1.1-647.12=452.87 | P84: 0.79722222
G85: 79 | H85: 45975 | M85: 路人互动 | N85: 535 | O85: -500*1.07=-535 | P85: 0.45138889
G86: 80 | H86: 45975 | M86: 星链-AdNova | N86: 1598.06 | O86: (1500-130.93)*1.08+开户费20*6=1,598.60 | P86: 0.53055556
G87: 81 | H87: 45975 | M87: 星链-AdNova | N87: 216.54 | O87: 200*1.08=216.00 | P87: 0.69166667
G88: 82 | H88: 45975 | I88: 瑞典1梯队（蟑螂哥）结算群 | J88: 900 | L88: 0.71111111 | M88: 志诚三不限 | N88: 573.14 | O88: (清零5.85+5.59-150)*1.07-开户费50*5+(7.38-130)*1.1-开户费40=573.14 | P88: 0.85694444
G89: 83 | H89: 45975 | M89: 广告配套 | N89: 1092 | O89: 明细：主页：3；认证主页：11；老主页：65 ；个号：55 | P89: 0.86041667
G90: 84 | H90: 45975 | M90: SZ_TK下户Chris Ryan | N90: 252 | O90: 开户费20*2+200*1.06=252 | P90: 0.98125
G91: 85 | H91: 45976 | M91: 广告配套 | N91: 18.46 | O91: 谷歌邮箱*7 | P91: 0.43958333
G92: 86 | H92: 45976 | M92: SZ_TK下户Chris Ryan | N92: 252 | O92: 开户费20*2+200*1.06=252 | P92: 0.71319444
G93: 87 | H93: 45976 | M93: 广告配套 | N93: 110 | O93: TK德国中介费 | P93: 0.84375
G94: 88 | H94: 45977 | M94: SZ_TK下户Chris Ryan | N94: 126 | O94: 开户费20+100*1.06=126 | P94: 0.77569444
G95: 89 | H95: 45977 | M95: 星链-AdNova | N95: 343.83 | O95: （398.4+368.42-900）*1.08-开户费200=-343.83 | P95: 0.79097222
G96: 90 | H96: 45977 | M96: 星链-AdNova | N96: 1404 | O96: 1300*1.08=1404 | P96: 0.91458333
G97: 91 | H97: 45978 | M97: 广告配套 | N97: 14.18 | O97: 谷歌邮箱*5 | P97: 0.43541667
G98: 92 | H98: 45978 | M98: 广告配套 | N98: 500 | O98: 矿工费 | P98: 0.44027778
G99: 93 | H99: 45978 | M99: Y-5208 FB欧/美户 | N99: 1100 | O99: 500*2*1.1=1100 | P99: 0.45069444
G100: 94 | H100: 45978 | M100: 路人互动 | N100: 50 | O100: 开户费50 | P100: 0.45763889
... G103: 97 | H103: 45978 | M103: TK下户hailey | N103: 255 | O103: 开户费105+150=255 | P103: 0.64166667
G104: 98 | H104: 45978 | M104: 启航 | N104: 1672.06 | O104: 3500+244.21-2072.15=1672.06 | P104: 15：58
...

Sheet 2025年10月收支财务报表
C1: 2025年10月收支财务报表
C4: 财务统计 STATISTICS | G4: 10月收支明细 DETAIL | S4: =SUMIF(M:M,"广告配套",N:N) -> 9175.395 | T4: U支出的广告配套（不含RMB支出）
G5: 序号 | H5: 日期 | I5: 收入 | M5: 支出
C6: 月份查询 | I6: 项目 | J6: 金额 | K6: 备注 | L6: 时间 | M6: 项目 | N6: 金额 | O6: 备注 | P6: 时间 | S6: =SUMIF(M:M,"后勤支出",N:N) -> 31523.68 | T6: 后勤支出
C7: 10月 | D7: ▼ | G7: 1 | H7: 45931 | I7: 9月结余 | J7: ='2025年9月收支财务报表'!C25 -> 19233.42 | S7: =SUMIF(M:M,"印度户印尼企业户",N:N) -> 213183.14 | T7: 印度户印尼企业户
C8: 收入 | G8: 2 | H8: 45931 | I8: 白马4期 | J8: 30000 | L8: 0.64166667 | S8: =SUMIF(M:M,"Vcc-102524 服务费1（泰华）",N:N) -> 404 | T8: Vcc-102524 服务费1（泰华）
C9: =C21 -> 772527.52 | G9: 3 | H9: 45932 | M9: 印度户印尼企业户 | N9: 14780.99 | O9: 充值金额13649.06263+手续费1131.925011=14,780.99 | P9: 0.73055556 | S9: =SUMIF(M:M,"凤凰渠道-泰华",N:N) -> 182993.43 | T9: 凤凰渠道-泰华
C10: 支出 | G10: 4 | H10: 45932 | M10: 广告配套 | N10: 78.57 | O10: 个号*10 | P10: 0.83541667 | S10: =SUMIF(M:M,"wade shen 美金谷歌户25+5%",N:N) -> 195.5 | T10: wade shen 美金谷歌户25+5%
C11: =C23 -> 551497.86 | G11: 5 | H11: 45933 | M11: 广告配套 | N11: 25.45 | O11: 谷歌邮箱*5 | P11: 0.42430556 | S11: =SUMIF(M:M,"二不限企业户",N:N) -> 7612.44 | T11: 二不限企业户
C12: 结余 | G12: 6 | H12: 45933 | M12: 广告配套 | N12: 33 | O12: 个号*5 | P12: 0.72847222 | S12: =SUMIF(M:M,"Y-5208 FB欧/美户",N:N) -> 1374.31 | T12: Y-5208 FB欧/美户
C13: =C9-C11 -> 221029.65 | G13: 7 | H13: 45933 | M13: 三不限美国户-8%小鱼 | N13: 540 | O13: 500*1.08=540 | P13: 0.59166667 | S13: =SUMIF(M:M,"三不限美国户-8%小鱼",N:N) -> 540 | T13: 三不限美国户-8%小鱼
G14: 8 | H14: 45933 | M14: 后勤支出 | N14: 10000 | O14: 换汇 | P14: 0.74097222 | S14: =SUMIF(M:M,"十月二不限",N:N) -> 5255.56 | T14: 十月二不限
C15: 任意时段查询 | G15: 9 | H15: 45934 | I15: 白马4期 | J15: 30000 | L15: 14：18 | M15: 印度户印尼企业户 | N15: 6455.82 | O15: 充值金额5940.570042+手续费515.2456034=6,455.82 | P15: 12：08 | S15: =SUMIF(M:M,"Alex_1011——谷歌原生户",N:N) -> 4783 | T15: Alex_1011——谷歌原生户
C16: 起始日期： | G16: 10 | H16: 45935 | M16: 广告配套 | N16: 288.86 | O16: IP*40个 | P16: 20：22 | S16: =SUMIF(M:M,"启航",N:N) -> 2189.82 | T16: 启航
C17: 45292 | G17: 11 | H17: 45936 | M17: 广告配套 | N17: 210.55 | O17: 耐用号*5 | P17: 11：13 | S17: =SUMIF(M:M,"HC ADS Agency 2 2026",N:N) -> 53.5 | T17: HC ADS Agency 2 2026
C18: 结束日期： | G18: 12 | H18: 45936 | M18: 印度户印尼企业户 | N18: 18063.14 | O18: 充值金额16678.84+手续费1384.31=18,063.14 | P18: 0.47291667 | S18: =SUMIF(M:M,"泰华 & Bigad 谷歌老户 8+1",N:N) -> 3461.4 | T18: 泰华 & Bigad 谷歌老户 8+1
C19: 72805 | G19: 13 | H19: 45936 | M19: 十月二不限 | N19: 516.36 | O19: ZZ (100*3-295)*1.02+开户费30=35.1，SZ (100*5*-87)1.02+开户费30*2=481.26，合计516.36 | P19: 0.64652778 | S19: =SUMIF(M:M,"wade 谷歌户（阿水）",N:N) -> 686 | T19: wade 谷歌户（阿水）
C20: 收入 | G20: 14 | H20: 45936 | M20: 广告配套 | N20: 225 | O20: 防护续费 | P20: 15：41 | S20: =SUMIF(M:M,"海总-黑泽",N:N) -> 3967.8 | T20: 海总-黑泽
C21: =SUMIFS(J:J,H:H,">="&$C$17,H:H,"<="&$C$19) -> 772527.52 | G21: 15 | H21: 45936 | I21: K26/印度股票 | J21: 30000 | L21: 0.65555556 | M21: Vcc-102524 服务费1（泰华） | N21: 404 | O21: 400*1.01=404 | P21: 0.6625 | S21: =SUMIF(M:M,"谷歌-otto",N:N) -> 333.3 | T21: 谷歌-otto
C22: 支出 | G22: 16 | H22: 45937 | M22: 印度户印尼企业户 | N22: 13884.26 | O22: 充值金额12800.24+手续费1084.02=13,884.26 | P22: 12：51 | S22: =SUMIF(M:M,"星链-AdNova",N:N) -> 1140 | T22: 星链-AdNova
C23: =SUMIFS(N:N,H:H,">="&$C$17,H:H,"<="&$C$19) -> 551497.86 | G23: 17 | H23: 45937 | I23: K26/印度股票 | J23: 20000 | L23: 22：37 | S23: =SUMIF(M:M,"志诚三不限",N:N) -> 278.89 | T23: 志诚三不限
C24: 结余 | G24: 18 | H24: 45938 | I24: 路人互动 | J24: 2480.7 | L24: 13：44 | M24: 印度户印尼企业户 | N24: 8403.65 | O24: 充值金额7781.16+手续费622.49=8,403.65 | P24: 0.67777778 | S24: =SUMIF(M:M,"SHEN@FLZ 2 群",N:N) -> 14241.7 | T24: SHEN@FLZ 2 群
C25: =C21-C23 -> 221029.65 | G25: 19 | H25: 45938 | M25: 二不限企业户 | N25: 420.36 | O25: (800-381.08)*1.025=429.39，实转420.36，少转9.03 | P25: 22：28 | S25: =SUMIF(M:M,"GT&SHEN 欧洲户新",N:N) -> 218 | T25: GT&SHEN 欧洲户新
G26: 20 | H26: 45939 | M26: wade shen 美金谷歌户25+5% | N26: 140.03 | O26: (清零1133.54-充值1087.06)*1.075-开户费190= -140.03 | P26: 11：43 | S26: =SUMIF(M:M,"GT二不限新",N:N) -> 60 | T26: GT二不限新
G27: 21 | H27: 45939 | M27: 广告配套 | N27: 16.11 | O27: 谷歌邮箱4个 | P27: 11：49 | S27: =SUMIF(M:M,"印度20期",N:N) -> 1371 | T27: 印度20期
G28: 22 | H28: 45939 | M28: 广告配套 | N28: 20 | O28: GPT订阅19.8*1.01=20 | P28: 11：58 | S28: =SUMIF(M:M,"岳总",N:N) -> 32100 | T28: 岳总
G29: 23 | H29: 45939 | M29: 广告配套 | N29: 50.5 | O29: GPT订阅50*1.01=50.5 | P29: 12：11 | S29: =SUMIF(M:M,"海总-比利时单导测试",N:N) -> 2800 | T29: 海总-比利时单导测试
G30: 24 | H30: 45939 | M30: 后勤支出 | N30: 805.33 | O30: 发工资 | P30: 15：19 | S30: =SUMIF(M:M,"赵总",N:N) -> 25050 | T30: 赵总
G31: 25 | H31: 45939 | M31: 后勤支出 | N31: 1800 | O31: 发工资 | P31: 15：23 | S31: =SUMIF(M:M,"新K1/B哥",N:N) -> 6506 | T31: 新K1/B哥
G32: 26 | H32: 45939 | M32: 后勤支出 | N32: 1157.56 | O32: 发工资 | P32: 0.64305556
G33: 27 | H33: 45939 | M33: 后勤支出 | N33: 1269.56 | O33: 发工资 | P33: 0.64444444 | S33: =SUM(S4:S31) -> 551497.86
G34: 28 | H34: 45939 | M34: 后勤支出 | N34: 1326.41 | O34: 发工资 | P34: 0.64722222
G35: 29 | H35: 45939 | M35: 后勤支出 | N35: 2607.56 | O35: 发工资 | P35: 0.64861111 | S35: 往上支出-------------------分割线-------------------往下收入
G36: 30 | H36: 45939 | M36: 后勤支出 | N36: 845.07 | O36: 发工资 | P36: 15：37
G37: 31 | H37: 45939 | M37: 后勤支出 | N37: 1185.56 | O37: 发工资 | P37: 15：40 | S37: =SUMIF(I:I,"白马4期",J:J) -> 60000 | T37: 白马4期 | U37: =S37+'2025年9月收支财务报表'!S40 -> 120000
G38: 32 | H38: 45939 | M38: 后勤支出 | N38: 5000 | O38: 发工资 | P38: 15：42 | S38: =SUMIF(I:I,"K26/印度股票",J:J) -> 144212 | T38: K26/印度股票
G39: 33 | H39: 45939 | M39: 后勤支出 | N39: 280 | O39: 发工资 | P39: 15：44 | S39: =SUMIF(I:I,"B哥/马来英语粉",J:J) -> 40000 | T39: B哥/马来英语粉 | U39: =S39+'2025年9月收支财务报表'!S46 -> 60000
G40: 34 | H40: 45939 | M40: Y-5208 FB欧/美户 | N40: 1374.31 | O40: 1110+1120-855.69=1374.31 | P40: 16：23 | S40: =SUMIF(I:I,"新K1/B哥",J:J) -> 170000 | T40: 新K1/B哥
G41: 35 | H41: 45939 | M41: 广告配套 | N41: 14 | O41: 飞机会员 | P41: 18：20 | S41: =SUMIF(I:I,"新K4/B哥",J:J) -> 135067 | T41: 新K4/B哥
G42: 36 | H42: 45939 | I42: K26/印度股票 | J42: 20000 | L42: 18：54 | M42: 二不限企业户 | N42: 615 | O42: 600*1.025=615 | P42: 0.95486111 | S42: =SUMIF(I:I,"海总-比利时单导测试",J:J) -> 2800 | T42: 海总-比利时单导测试
G43: 37 | H43: 45940 | M43: 广告配套 | N43: 288.86 | O43: IP*40个 | P43: 10：20 | S43: =SUMIF(I:I,"韩国维权粉测试",J:J) -> 2200 | T43: 韩国维权粉测试
G44: 38 | H44: 45940 | M44: 广告配套 | N44: 24.86 | O44: 谷歌邮箱*6 | P44: 10：36 | S44: =SUMIF(I:I,"印度20期",J:J) -> 90000 | T44: 印度20期
G45: 39 | H45: 45940 | M45: 后勤支出 | N45: 4746.63 | O45: SZ报销 | P45: 12：06 | S45: =SUMIF(I:I,"德国单粉—summer FB180",J:J) -> 45000 | T45: 德国单粉—summer FB180
G46: 40 | H46: 45940 | M46: 印度户印尼企业户 | N46: 15877.47 | O46: 充值金额14664.33+手续费1213.15=15,877.47 | P46: 12：11 | S46: =SUMIF(I:I,"渠道106-本土fb🇯🇵",J:J) -> 41760 | T46: 渠道106-本土fb🇯🇵
G47: 41 | H47: 45940 | M47: 广告配套 | N47: 500 | O47: 个号充值预存 | P47: 0.66875 | S47: =SUMIF(I:I,"赵总",J:J) -> 7050 | T47: 赵总
G48: 42 | H48: 45940 | M48: 二不限企业户 | N48: 1435 | O48: SZ 1200*1.025=1,230，ZZ 200*1.025=205 | P48: 16：53 | S48: =SUMIF(I:I,"6% 海外户",J:J) -> 377 | T48: 6% 海外户
G49: 43 | H49: 45940 | I49: K26/印度股票 | J49: 20000 | L49: 17：08 | M49: 广告配套 | N49: 2.86 | O49: 谷歌邮箱*2 | P49: 0.73333333 | S49: =SUMIF(I:I,"wade 谷歌户（阿水）",J:J) -> 386.48 | T49: wade 谷歌户（阿水）
G50: 44 | H50: 45940 | M50: 广告配套 | N50: 10.0769 | O50: 飞机号 | P50: 20：10 | S50: =SUMIF(I:I,"志诚三不限",J:J) -> 1859.25 | T50: 志诚三不限
G51: 45 | H51: 45940 | M51: 十月二不限 | N51: 670 | O51: 600*1.02+开户费30*2=672，少转2U | P51: 20：26 | S51: =SUMIF(I:I,"GT&SHEN 欧洲户8+1",J:J) -> 4384 | T51: GT&SHEN 欧洲户8+1
G52: 46 | H52: 45940 | M52: 广告配套 | N52: 1500 | O52: 明细：谷歌邮箱：1；主页：4；老主页：52；BM：30；个号：60 | P52: 0.85625 | S52: =SUMIF(I:I,"印度企业户 欧洲美金户",J:J) -> 734.07 | T52: 印度企业户 欧洲美金户
G53: 47 | H53: 45941 | M53: 广告配套 | N53: 14.12 | O53: 谷歌邮箱*5 | P53: 0.42916667 | S53: =SUMIF(I:I,"岳总",J:J) -> 4205 | T53: 岳总
G54: 48 | H54: 45941 | M54: 印度户印尼企业户 | N54: 15965.45 | O54: 14727.27+1238.18=15,965.45 | P54: 0.62708333 | S54: =SUMIF(I:I,"海总-黑泽",J:J) -> 601.6 | T54: 海总-黑泽
G55: 49 | H55: 45941 | M55: 十月二不限 | N55: 612 | O55: SZ 400*1.02=408；ZZ 200*1.02=204 | P55: 0.63888889 | S55: =SUMIF(I:I,"潘安户",J:J) -> 177 | T55: 潘安户
G56: 50 | H56: 45941 | I56: K26/印度股票 | J56: 20000 | L56: 19：10 | M56: 广告配套 | N56: 200 | O56: 印度WhatsApp*5 | P56: 0.8 | S56: =SUMIF(I:I,"路人互动",J:J) -> 2480.7 | T56: 路人互动
G57: 51 | H57: 45941 | M57: Alex_1011——谷歌原生户 | N57: 1832 | O57: 开户费(600+800)+400*1.08=1832 | P57: 0.91805556 | S57: =J7 -> 19233.42 | T57: 9月结余
G58: 52 | H58: 45942 | M58: 十月二不限 | N58: 816 | O58: 800*1.02=816 | P58: 0.81875 | S58: =SUM(S37:S57) -> 772527.52
G59: 53 | H59: 45943 | M59: 启航 | N59: 1078.7 | P59: 0.50069444
G60: 54 | H60: 45943 | M60: 印度户印尼企业户 | N60: 19142.53 | O60: 17641.23+1501.30=19,142.53 | P60: 0.50347222
G61: 55 | H61: 45943 | M61: Alex_1011——谷歌原生户 | N61: 540 | O61: 500*1.08=540 | P61: 0.52152778
G62: 56 | H62: 45943 | I62: 潘安户 | J62: 177 | L62: 12：40 | M62: 凤凰渠道-泰华 | N62: 11100 | O62: ZZ 8000*1.11=8880，SZ 2000*1.11=2220 | P62: 15：04
G63: 57 | H63: 45943 | M63: 十月二不限 | N63: 642 | O63: ZZ 开户费30+200*1.02=234 ，SZ 400*1.02=408 | P63: 15：34
G64: 58 | H64: 45943 | M64: 广告配套 | N64: 14.11 | O64: 谷歌邮箱*5 | P64: 0.69097222
G65: 59 | H65: 45943 | I65: 海总-黑泽 | J65: 601.6 | L65: 18：03 | M65: 十月二不限 | N65: 918 | O65: ZZ 400*1.02=408；SZ 500*1.02=510 | P65: 20：09
G66: 60 | H66: 45943 | M66: 广告配套 | N66: 500 | O66: 矿工费TRX | P66: 20：15
G67: 61 | H67: 45943 | M67: 二不限企业户 | N67: 778.39 | O67: -759.4*1.025=-778.39 | P67: 0.88402778
G68: 62 | H68: 45943 | M68: Alex_1011——谷歌原生户 | N68: 167 | O68: 100*1.07+开户费60=167 | P68: 21：31
G69: 63 | H69: 45943 | I69: K26/印度股票 | J69: 20000 | L69: 21：48
G70: 64 | H70: 45944 | M70: 凤凰渠道-泰华 | N70: 5550 | O70: ZZ 5000*1.11=5550 | P70: 10：16
G71: 65 | H71: 45944 | M71: 广告配套 | N71: 78.57 | O71: 个号*10 | P71: 10：46
G72: 66 | H72: 45944 | M72: 印度户印尼企业户 | N72: 9515.78 | O72: 8783.13+732.65=9,515.78 | P72: 12：17
G73: 67 | H73: 45944 | M73: HC ADS Agency 2 2026 | N73: 53.5 | O73: 50*1.07=53.5 | P73: 16：21
G74: 68 | H74: 45944 | M74: 泰华 & Bigad 谷歌老户 8+1 | N74: 3461.4 | O74: 500*4*1.0807+开户费650*2=3461.4 | P74: 17：12
G75: 69 | H75: 45944 | I75: 岳总 | J75: 4205 | L75: 18：01 | M75: 十月二不限 | N75: 714 | O75: SZ 600*1.02=612；ZZ 100*1.02=102 | P75: 19：00
G76: 70 | H76: 45944 | M76: 二不限企业户 | N76: 924.82 | O76: ZZ (1000-97.74)*1.025=924.82 | P76: 0.88194444
G77: 71 | H77: 45945 | M77: 凤凰渠道-泰华 | N77: 4440 | O77: SZ 1000*1.11=1110；ZZ 3000*1.11=3330 | P77: 10：14
G78: 72 | H78: 45945 | M78: 广告配套 | N78: 16.95 | O78: 谷歌邮箱*9 | P78: 10：18
G79: 73 | H79: 45945 | M79: 广告配套 | N79: 42.38 | O79: 谷歌邮箱*12 | P79: 0.67986111
G80: 74 | H80: 45945 | M80: 广告配套 | N80: 14.37806 | O80: vpn | P80: 0.9625
G81: 75 | H81: 45946 | M81: 凤凰渠道-泰华 | N81: 3330 | O81: ZZ 3000*1.11=3330 | P81: 0.425
G82: 76 | H82: 45946 | M82: 广告配套 | N82: 500 | O82: 个号预存 | P82: 0.55902778
G83: 77 | H83: 45946 | M83: 印度户印尼企业户 | N83: 7397.39 | O83: 6830.92+566.47=7,397.39 | P83: 0.62916667
G84: 78 | H84: 45946 | I84: 海总-比利时单导测试 | J84: 2800 | L84: 0.64375 | M84: 广告配套 | N84: 50 | O84: 域名*2 | P84: 0.64930556
G85: 79 | H85: 45946 | M85: Alex_1011——谷歌原生户 | N85: 300 | O85: 业务验证300 | P85: 0.65138889
G86: 80 | H86: 45946 | I86: 印度企业户 欧洲美金户 | J86: 734.07 | L86: 0.67638889 | M86: wade 谷歌户（阿水） | N86: 359 | O86: 开户费250+100*1.09=359 | P86: 0.73819444
G87: 81 | H87: 45946 | M87: Alex_1011——谷歌原生户 | N87: 540 | O87: 500*1.08=540 | P87: 0.75069444
G88: 82 | H88: 45946 | M88: Alex_1011——谷歌原生户 | N88: 535 | O88: 500*1.07=535 | P88: 0.96944444
G89: 83 | H89: 45947 | M89: 凤凰渠道-泰华 | N89: 6660 | O89: ZZ 6000*1.11=6660 | P89: 0.42638889
G90: 84 | H90: 45947 | M90: 启航 | N90: =555.56*2 -> 1111.12 | O90: SZ 500*1.11112=555.56；ZZ 500*1.11112=555.56 | P90: 0.61111111
G91: 85 | H91: 45947 | M91: 广告配套 | N91: 288.22 | O91: IP*40个 | P91: 0.64166667
G92: 86 | H92: 45947 | I92: B哥/马来英语粉 | J92: 20000 | L92: 0.67291667 | M92: 印度户印尼企业户 | N92: 8459.83 | O92: 7814.66+645.17=8,459.83 | P92: 0.67291667
G93: 87 | H93: 45947 | I93: 新K1/B哥 | J93: 30000 | L93: 0.7125
G94: 88 | H94: 45947 | I94: 新K1/B哥 | J94: 30000 | L94: 0.71875 | M94: Alex_1011——谷歌原生户 | N94: 334 | O94: 100*2*0.07+开户费60*2=334 | P94: 0.74305556
G95: 89 | H95: 45947 | M95: Alex_1011——谷歌原生户 | N95: 535 | O95: 500*1.07=535 | P95: 0.78125
G96: 90 | H96: 45947 | M96: 凤凰渠道-泰华 | N96: 16645.68 | O96: ZZ 14996.1*1.11+0.01=16,645.68 | P96: 0.92291667
G97: 91 | H97: 45948 | M97: 广告配套 | N97: 1233 | O97: 主页：43；老主页：4；个号：50；老BM：20；申诉分享BM：1 | P97: 0.42638889
G98: 92 | H98: 45948 | M98: wade 谷歌户（阿水） | N98: 327 | O98: 300*1.09=327 | P98: 0.55555556
G99: 93 | H99: 45948 | M99: 印度户印尼企业户 | N99: 9542.23 | O99: 8807.62+734.61=9,542.23 | P99: 0.62222222
G100: 94 | H100: 45948 | I100: 新K1/B哥 | J100: 30000 | L100: 0.64236111
G101: 95 | H101: 45949 | M101: 凤凰渠道-泰华 | N101: 9990 | O101: ZZ 9000*1.11=9990 | P101: 0.58055556
G102: 96 | H102: 45949 | M102: 广告配套 | N102: 14 | O102: 飞机会员3个月 | P102: 0.58472222
...

Sheet 2025年9月收支财务报表
C1: 2025年9月收支财务报表
C4: 财务统计 STATISTICS | G4: 9月收支明细 DETAIL | S4: =SUMIF(M:M,"广告配套",N:N) -> 10833.788 | T4: U支出的广告配套（不含RMB支出）
G5: 序号 | H5: 日期 | I5: 收入 | M5: 支出
C6: 月份查询 | I6: 项目 | J6: 金额 | K6: 备注 | L6: 时间 | M6: 项目 | N6: 金额 | O6: 备注 | P6: 时间 | S6: =SUMIF(M:M,"后勤支出",N:N) -> 47962.486 | T6: 后勤支出
C7: 9月 | D7: ▼ | G7: 1 | H7: 45901 | I7: 8月结余 | J7: ='2025年8月收支财务报表'!C25 -> 112330.75 | M7: 广告配套 | N7: 210.36 | O7: 耐用号*5 | P7: 0.61458333 | S7: =SUMIF(M:M,"GT&SHEN 欧洲户８＋１ 港60+5+1",N:N) -> 77971.79 | T7: GT&SHEN 欧洲户８＋１ 港60+5+1
C8: 收入 | G8: 2 | H8: 45901 | M8: 广告配套 | N8: 24.57 | O8: IP | P8: 17：01 | S8: =SUMIF(M:M,"志诚三不限",N:N) -> 35281.28 | T8: 志诚三不限
C9: =C21 -> 413986.89 | G9: 3 | H9: 45901 | M9: 广告配套 | N9: 26.25 | O9: IP2 | P9: 0.71388889 | S9: =SUMIF(M:M,"海总新渠道",N:N) -> 1110 | T9: 海总新渠道
C10: 支出 | G10: 4 | H10: 45901 | I10: 马来英_阿稳 | J10: 840 | K10: 退款 | L10: 0.82013889 | M10: GT&SHEN 欧洲户８＋１ 港60+5+1 | N10: 540 | O10: 500*1.08=540 | P10: 0.86319444 | S10: =SUMIF(M:M,"印度户印尼企业户",N:N) -> 90763.63 | T10: 印度户印尼企业户
C11: =C23 -> 394753.47 | G11: 5 | H11: 45901 | M11: 志诚三不限 | N11: 2058.46 | O11: 500*2*1.11=1110 | P11: 0.95763889 | S11: =SUMIF(M:M,"路人互动",N:N) -> 15002.96 | T11: 路人互动
C12: 结余 | G12: 6 | H12: 45902 | M12: 海总新渠道 | N12: 1110 | P12: 0.49722222 | S12: =SUMIF(M:M,"Vcc-102524 服务费1（泰华）",N:N) -> 404 | T12: Vcc-102524 服务费1（泰华）
C13: =C9-C11 -> 19233.42 | G13: 7 | H13: 45902 | M13: 广告配套 | N13: 59 | O13: 个号 10个 | P13: 0.54375 | S13: =SUMIF(M:M,"印度企业户 欧洲美金户",N:N) -> 1056.3 | T13: 印度企业户 欧洲美金户
G14: 8 | H14: 45902 | M14: 广告配套 | N14: 288.86 | O14: IP | P14: 0.67638889 | S14: =SUMIF(M:M,"凤凰渠道-泰华",N:N) -> 14511.09 | T14: 凤凰渠道-泰华
C15: 任意时段查询 | G15: 9 | H15: 45902 | M15: 后勤支出 | N15: 60 | O15: 营业执照 | P15: 0.68472222 | S15: =SUMIF(M:M,"海总-黑泽",N:N) -> 4423.2 | T15: 海总-黑泽
C16: 起始日期： | G16: 10 | H16: 45902 | M16: 广告配套 | N16: 500 | O16: 个号预存 | P16: 0.69791667 | S16: =SUMIF(M:M,"Alex & Doris_谷歌户",N:N) -> 1110 | T16: Alex & Doris_谷歌户
C17: 45292 | G17: 11 | H17: 45902 | M17: 广告配套 | N17: 34.285 | O17: 个号 3个 | P17: 0.72777778 | S17: =SUMIF(M:M,"wade shen 美金谷歌户25+5%",N:N) -> 1247.5 | T17: wade shen 美金谷歌户25+5%
C18: 结束日期： | G18: 12 | H18: 45902 | M18: 广告配套 | N18: 20 | O18: 老主页2个 | P18: 0.73333333 | S18: =SUMIF(M:M,"GT二不限",N:N) -> 1765.12 | T18: GT二不限
C19: 72805 | G19: 13 | H19: 45902 | M19: 渠道L 英文L 马来 | N19: 3960 | O19: 退款 | P19: 19：22 | S19: =SUMIF(M:M,"谷歌户（阿水）",N:N) -> 300 | T19: 谷歌户（阿水）
C20: 收入 | G20: 14 | H20: 45902 | M20: 志诚三不限 | N20: 3062.1 | O20: 2640+422.1=3062.1 | P20: 0.99930556 | S20: =SUMIF(M:M,"6% 海外户",N:N) -> 455.84 | T20: 6% 海外户
C21: =SUMIFS(J:J,H:H,">="&$C$17,H:H,"<="&$C$19) -> 413986.89 | G21: 15 | H21: 45903 | M21: 广告配套 | N21: 59 | O21: BM：10个 | P21: 0.53194444 | S21: =SUMIF(M:M,"深圳芳林子",N:N) -> 3454.2 | T21: 深圳芳林子
C22: 支出 | G22: 16 | H22: 45903 | M22: 印度户印尼企业户 | N22: 8499.15 | O22: 7841.81+657.34=8499.15 | P22: 0.53402778 | S22: =SUMIF(M:M,"二不限企业户",N:N) -> 820 | T22: 二不限企业户
C23: =SUMIFS(N:N,H:H,">="&$C$17,H:H,"<="&$C$19) -> 394753.47 | G23: 17 | H23: 45903 | M23: 广告配套 | N23: 10.0369 | O23: 飞机号预存 | P23: 0.55625 | S23: =SUMIF(M:M,"华飞-Alex（三不限）8+千分6",N:N) -> 334.596 | T23: 华飞-Alex（三不限）8+千分6
C24: 结余 | G24: 18 | H24: 45903 | M24: 后勤支出 | N24: 10000 | O24: 换汇RMB | P24: 0.56111111 | S24: =SUMIF(M:M,"Y-5208 FB欧/美户",N:N) -> 2260 | T24: Y-5208 FB欧/美户
C25: =C21-C23 -> 19233.42 | G25: 19 | H25: 45903 | M25: 后勤支出 | N25: 10000 | O25: 换汇RMB2 | P25: 14：30 | S25: =SUMIF(M:M,"三不限美国户-8%小鱼",N:N) -> 1080 | T25: 三不限美国户-8%小鱼
G26: 20 | H26: 45903 | M26: 广告配套 | N26: 9.98 | O26: fbspider单月套餐A | P26: 0.65 | S26: =SUMIF(M:M,"潘安户",N:N) -> 218.16 | T26: 潘安户
G27: 21 | H27: 45903 | I27: 十月二不限 | J27: 55.7 | K27: 退款 | L27: 0.92847222 | S27: =SUMIF(M:M,"企业户",N:N) -> 152.53 | T27: 企业户
G28: 22 | H28: 45904 | I28: 西班牙大区1组资源-张小强 | J28: 3960 | K28: 9月1-2日 西班牙大区1组资源-张小强 9/1 F50 有效 11 9/2 F50 有效25 合计: (11+25)*110=3960 | L28: 0.033333333 | M28: 广告配套 | N28: 118 | O28: BM：10个，个号：10个 | P28: 0.49305556 | S28: =SUMIF(M:M,"Jay",N:N) -> 9600 | T28: Jay
G29: 23 | H29: 45904 | I29: 欧洲户10➕1-Nancy | J29: 481.56 | K29: 退款 | L29: 0.57708333 | M29: 广告配套 | N29: $0.48 | O29: 谷歌邮箱1个 | P29: 0.63055556 | S29: =SUMIF(M:M,"岳总",N:N) -> 42920 | T29: 岳总
G30: 24 | H30: 45904 | M30: GT&SHEN 欧洲户８＋１ 港60+5+1 | N30: 218 | O30: 200*1.09=218 | P30: 0.67916667 | S30: =SUMIF(M:M,"晨",N:N) -> 5250 | T30: 晨
G31: 25 | H31: 45904 | I31: 客户服务群-L0816 | J31: 695.49 | K31: 退款 | L31: 18：01 | S31: =SUMIF(M:M,"意大利3期",N:N) -> 20505 | T31: 意大利3期
G32: 26 | H32: 45904 | I32: 西班牙大区1组资源-张小强 | J32: 2090 | K32: 9月3日 西班牙大区1组资源-张小强 9/3 T5 有效 19 合计: 19*110=2090 | L32: 18：11 | M32: 志诚三不限 | N32: 3352.29 | O32: (1020-9.45)*1.07+开户费60+500-500+2010*1.1=3,352.29 | P32: 23：08 | S32: =SUMIF(M:M,"渠道L 英文L 马来",N:N) -> 3960 | T32: 渠道L 英文L 马来
G33: 27 | H33: 45905 | I33: 西班牙大区1组资源-张小强 | J33: 2200 | K33: 9月5日 西班牙大区1组资源-张小强 9/5 C68有效20 合计: 20*110=2200 | L33: 0.51319444 | M33: 后勤支出 | N33: 3511.8189 | O33: 发工资 | P33: 0.63263889
G34: 28 | H34: 45905 | I34: 拉总（印度） | J34: 576 | L34: 0.63333333 | M34: 后勤支出 | N34: 1800 | O34: 发工资 | P34: 0.63611111 | S34: =SUM(S4:S32) -> 394753.47
G35: 29 | H35: 45905 | M35: 后勤支出 | N35: 1263.9556 | O35: 发工资 | P35: 0.63888889
G36: 30 | H36: 45905 | M36: 后勤支出 | N36: 2002.0444 | O36: 发工资 | P36: 0.64166667 | S36: 往上支出-------------------分割线-------------------往下收入
G37: 31 | H37: 45905 | M37: 后勤支出 | N37: 555.55556 | O37: 发工资 | P37: 0.64305556
G38: 32 | H38: 45905 | M38: 后勤支出 | N38: 695.55556 | O38: 发工资 | P38: 0.64513889 | S38: =SUMIF(I:I,"西班牙大区1组资源-张小强",J:J) -> 9680 | T38: 西班牙大区1组资源-张小强
G39: 33 | H39: 45905 | M39: 后勤支出 | N39: 555.55556 | O39: 发工资 | P39: 0.64583333 | S39: =SUMIF(I:I,"拉总（印度）",J:J) -> 576 | T39: 拉总（印度）
G40: 34 | H40: 45905 | M40: 后勤支出 | N40: 5000 | O40: 发工资 | P40: 0.64722222 | S40: =SUMIF(I:I,"白马4期",J:J) -> 60000 | T40: 白马4期
G41: 35 | H41: 45905 | M41: 意大利3期 | N41: 20505 | O41: 退款 | P41: 0.65625 | S41: =SUMIF(I:I,"渠道BF 新加坡L",J:J) -> 2700 | T41: 渠道BF 新加坡L
G42: 36 | H42: 45905 | M42: 广告配套 | N42: 89 | O42: 个号：15个 | P42: 15：57 | S42: =SUMIF(I:I,"印度18期",J:J) -> 123944 | T42: 印度18期
G43: 37 | H43: 45905 | I43: 海总-德国；意大利 | J43: 5535 | L43: 0.68819444 | S43: =SUMIF(I:I,"2009意大利",J:J) -> 2260 | T43: 2009意大利
G44: 38 | H44: 45905 | I44: 2009意大利 | J44: 2260 | K44: 2009意大利总转款0，总有效17.5，0-1.5*120-16*130=-2260 | L44: 0.80555556 | S44: =SUMIF(I:I,"意大利3期",J:J) -> 4485 | T44: 意大利3期
G45: 39 | H45: 45906 | M45: 印度户印尼企业户 | N45: 4221.41 | O45: 3917.97*1.08-10=4221.41 | P45: 0.56041667 | S45: =SUMIF(I:I,"2011意大利",J:J) -> 2145 | T45: 2011意大利
G46: 40 | H46: 45906 | M46: 路人互动 | N46: 575 | O46: 500*1.09+30开户费=575 | P46: 0.63402778 | S46: =SUMIF(I:I,"马来英语粉",J:J) -> 20000 | T46: 马来英语粉
G47: 41 | H47: 45907 | I47: 白马4期 | J47: 30000 | L47: 0.65069444 | S47: =SUMIF(I:I,"日本 FB人设",J:J) -> 59000 | T47: 日本 FB人设
G48: 42 | H48: 45907 | M48: 广告配套 | N48: 225 | O48: 防护续费 | P48: 20：26 | S48: =SUMIF(I:I,"尼日利亚",J:J) -> 200 | T48: 尼日利亚
G49: 43 | H49: 45908 | M49: 广告配套 | N49: 500 | O49: 个号预存 | P49: 0.59791667
G50: 44 | H50: 45908 | M50: 广告配套 | N50: 59 | O50: 个号 10个 | P50: 0.60486111
G51: 45 | H51: 45908 | M51: 路人互动 | N51: 545 | O51: -500*1.09=-545 | P51: 15 | S51: =SUMIF(I:I,"R|泰华&云峰合作群美金企业户",J:J) -> 1884.89 | T51: R|泰华&云峰合作群美金企业户
G52: 46 | H52: 45908 | I52: 西班牙大区1组资源-张小强 | J52: 1430 | K52: 9月5日 西班牙大区1组资源-张小强 9/5 A17 有效13 合计:13*110=1430 | L52: 15：49 | M52: Vcc-102524 服务费1（泰华） | N52: 101 | O52: 100*1.01=101 | P52: 16：52 | S52: =SUMIF(I:I,"晨",J:J) -> 4375 | T52: 晨
G53: 47 | H53: 45908 | M53: GT&SHEN 欧洲户８＋１ 港60+5+1 | N53: 683.02 | O53: 626.62*1.09=683.02 | P53: 1924 | S53: =SUMIF(I:I,"Y-5208 FB欧/美户",J:J) -> 1763.33 | T53: Y-5208 FB欧/美户
G54: 48 | H54: 45908 | M54: 广告配套 | N54: 59 | O54: 个号 10个 | P54: 0.85833333 | S54: =SUMIF(I:I,"海总新渠道",J:J) -> 535.17 | T54: 海总新渠道
G55: 49 | H55: 45908 | M55: GT&SHEN 欧洲户８＋１ 港60+5+1 | N55: 1090 | O55: 1000*1.09=1090 | P55: 22：32 | S55: =SUMIF(I:I,"后勤支出",J:J) -> 500 | T55: 后勤支出：预支工资退回
G56: 50 | H56: 45909 | M56: GT&SHEN 欧洲户８＋１ 港60+5+1 | N56: 1090 | O56: 1000*1.09=1090 | P56: 12：03 | S56: =SUMIF(I:I,"海总-德国；意大利",J:J) -> 5535 | T56: 海总-德国；意大利
G57: 51 | H57: 45909 | M57: GT&SHEN 欧洲户８＋１ 港60+5+1 | N57: 545 | O57: 500*1.09=545 | P57: 12：17 | S57: =SUMIF(I:I,"客户服务群-L0816",J:J) -> 695.49 | T57: 客户服务群-L0816
G58: 52 | H58: 45909 | M58: GT&SHEN 欧洲户８＋１ 港60+5+1 | N58: 545 | O58: 500*1.09=545 | P58: 0.65416667 | S58: =SUMIF(I:I,"欧洲户10➕1-Nancy",J:J) -> 481.56 | T58: 欧洲户10➕1-Nancy
G59: 53 | H59: 45909 | M59: 后勤支出 | N59: 500 | O59: 工资预支 | P59: 0.68125 | S59: =SUMIF(I:I,"十月二不限",J:J) -> 55.7 | T59: 十月二不限
G60: 54 | H60: 45909 | I60: 渠道BF 新加坡L | J60: 2700 | L60: 17：15 | M60: 印度企业户 欧洲美金户 | N60: 330 | O60: 300*1.1=330U | P60: 0.75138889 | S60: =SUMIF(I:I,"马来英_阿稳",J:J) -> 840 | T60: 马来英_阿稳
G61: 55 | H61: 45909 | M61: GT&SHEN 欧洲户８＋１ 港60+5+1 | N61: 902.08 | O61: (500*2-187.92/1.09)*1.09=902.08 | P61: 0.94166667 | S61: =J7 -> 112330.75 | T61: 8月结余
G62: 56 | H62: 45910 | M62: GT&SHEN 欧洲户８＋１ 港60+5+1 | N62: 1090 | O62: 1000*1.09=1090 | P62: 11：27 | S62: =SUM(S38:S61) -> 413986.89
G63: 57 | H63: 45910 | M63: 后勤支出 | N63: 10000 | O63: 换汇 | P63: 0.51319444
G64: 58 | H64: 45910 | M64: GT&SHEN 欧洲户８＋１ 港60+5+1 | N64: 1090 | O64: 1000*1.09=1090 | P64: 0.54097222
G65: 59 | H65: 45910 | M65: 广告配套 | N65: 127 | O65: BM：10个，个号：10个 | P65: 0.54444444
G66: 60 | H66: 45910 | M66: GT&SHEN 欧洲户８＋１ 港60+5+1 | N66: 1635 | O66: 1500*1.09=1635 | P66: 0.61388889
G67: 61 | H67: 45910 | I67: 后勤支出 | J67: 500 | K67: 预支工资退回 | L67: 0.74375 | M67: 志诚三不限 | N67: 2410.48 | O67: 5320+526.33+60*3开户费-3615.85=2410.48 | P67: 0.75138889
G68: 62 | H68: 45910 | M68: GT&SHEN 欧洲户８＋１ 港60+5+1 | N68: 2180 | O68: 2000*1.09=2180 | P68: 0.81319444
G69: 63 | H69: 45910 | M69: 凤凰渠道-泰华 | N69: 4214.44 | O69: 3623.4*1.13+30*4开户费=4,214.44 | P69: 0.84027778
G70: 64 | H70: 45910 | M70: GT&SHEN 欧洲户８＋１ 港60+5+1 | N70: 2180 | O70: 2000*1.09=2180 | P70: 22：06
G71: 65 | H71: 45911 | M71: GT&SHEN 欧洲户８＋１ 港60+5+1 | N71: 2725 | O71: 2500*1.09=2725 | P71: 11：04
G72: 66 | H72: 45911 | M72: 印度户印尼企业户 | N72: 4793.91 | O72: 4434.08+359.82=4793.91 | P72: 11：44
G73: 67 | H73: 45911 | M73: 后勤支出 | N73: 1778 | O73: 金海商务签973+床160+四件套35+洗衣机110+现金500预支工资 | P73: 0.54791667
G74: 68 | H74: 45911 | M74: 广告配套 | N74: 255.1797 | O74: VPN1季度9.11-12.11 | P74: 0.55069444
G75: 69 | H75: 45911 | M75: 广告配套 | N75: 500 | O75: 个号预存 | P75: 0.51666667
G76: 70 | H76: 45911 | M76: GT&SHEN 欧洲户８＋１ 港60+5+1 | N76: 2289 | O76: 2100*1.09=2,289 | P76: 0.68611111
G77: 71 | H77: 45911 | M77: 广告配套 | N77: 1.92 | O77: 谷歌邮箱4个 | P77: 0.71597222
G78: 72 | H78: 45911 | M78: 路人互动 | N78: 545 | O78: -500*1.09=-545 | P78: 20：26
G79: 73 | H79: 45912 | M79: 广告配套 | N79: 1.02 | O79: 谷歌邮箱1个 | P79: 0.48680556
G80: 74 | H80: 45912 | M80: GT&SHEN 欧洲户８＋１ 港60+5+1 | N80: 4905 | O80: 4500*1.09=4905 | P80: 0.51111111
G81: 75 | H81: 45912 | M81: wade shen 美金谷歌户25+5% | N81: 60 | O81: 开户费15*4=60 | P81: 0.60277778
G82: 76 | H82: 45912 | M82: 广告配套 | N82: 66 | O82: BM：10个 | P82: 0.6125
G83: 77 | H83: 45912 | I83: 海总新渠道 | J83: 535.17 | K83: 退款 | L83: 0.69791667 | M83: 路人互动 | N83: 545 | O83: -500*1.09=-545 | P83: 0.6125
G84: 78 | H84: 45912 | M84: 广告配套 | N84: 0.89 | O84: 谷歌邮箱1个 | P84: 0.75347222
G85: 79 | H85: 45912 | M85: 海总-黑泽 | N85: 575.4 | O85: 500*1.0908+30开户费=575.4 | P85: 0.775
G86: 80 | H86: 45912 | M86: 广告配套 | N86: 14.14 | O86: 谷歌邮箱3个 | P86: 0.84236111
G87: 81 | H87: 45912 | M87: 广告配套 | N87: 1059.89 | O87: 千粉主页：1；复审老主页：7；认证主页：47；个号：40 | P87: 0.84861111
G88: 82 | H88: 45912 | I88: 印度18期 | J88: 30000 | L88: 0.85416667 | M88: GT&SHEN 欧洲户８＋１ 港60+5+1 | N88: 2651.29 | O88: (3000-567.62)*1.09=2651.29 | P88: 0.88263889
G89: 83 | H89: 45913 | M89: 晨 | N89: 5250 | P89: 0.57986111
G90: 84 | H90: 45913 | M90: GT&SHEN 欧洲户８＋１ 港60+5+1 | N90: 2725 | O90: 2500*1.09=2,725 | P90: 0.59583333
G91: 85 | H91: 45913 | M91: 广告配套 | N91: 18.65 | O91: 谷歌邮箱4个 | P91: 16：07
G92: 86 | H92: 45913 | M92: 广告配套 | N92: 500 | O92: 个号预存 | P92: 16：52
G93: 87 | H93: 45913 | M93: 志诚三不限 | N93: 1987.53 | O93: B1710*1.07+开户费60-G清零105.6*1.1+E(300-100)*1.07=1987.54 | P93: 0.71736111
G94: 88 | H94: 45913 | M94: 海总-黑泽 | N94: 1120.8 | O94: 500*1.0908*2+30开户费=1120.8 | P94: 0.79930556
G95: 89 | H95: 45913 | M95: 广告配套 | N95: 14.74601 | O95: 梯子 | P95: 0.80902778
G96: 90 | H96: 45913 | M96: wade shen 美金谷歌户25+5% | N96: 430 | O96: 400*1.075=430 | P96: 0.91388889
G97: 91 | H97: 45913 | M97: Alex & Doris_谷歌户 | N97: 1110 | O97: 1000*1.11=1110 | P97: 0.92847222
G98: 92 | H98: 45913 | M98: GT&SHEN 欧洲户８＋１ 港60+5+1 | N98: 4797.25 | O98: (4500-98.85)*1.09=4,797.25 | P98: 0.94166667
G99: 93 | H99: 45914 | M99: 路人互动 | N99: 1167.96 | O99: (1500-456)*1.09+30开户费=1167.96 | P99: 0.41875
G100: 94 | H100: 45914 | M100: GT&SHEN 欧洲户８＋１ 港60+5+1 | N100: 2289 | O100: 2100*1.09=2289 | P100: 11：49
G101: 95 | H101: 45914 | M101: GT&SHEN 欧洲户８＋１ 港60+5+1 | N101: 2180 | O101: 2000*1.09=2180 | P101: 14：54
G102: 96 | H102: 45914 | M102: 海总-黑泽 | N102: 545.4 | O102: 500*1.0908=545.4 | P102: 14：57
...

Sheet 2025年8月收支财务报表
C1: 2025年8月收支财务报表
C4: 财务统计 STATISTICS | G4: 8月收支明细 DETAIL | S4: =SUMIF(M:M,"广告配套",N:N) -> 7033.375 | T4: U支出的广告配套（不含RMB支出）
G5: 序号 | H5: 日期 | I5: 收入 | M5: 支出
C6: 月份查询 | I6: 项目 | J6: 金额 | K6: 备注 | L6: 时间 | M6: 项目 | N6: 金额 | O6: 备注 | P6: 时间 | S6: =SUMIF(M:M,"后勤支出",N:N) -> 417091.94 | T6: 后勤支出
C7: 8月 | D7: ▼ | G7: 1 | H7: 45870 | I7: 7月结余 | J7: ='2025年7月收支财务报表'!C25 -> 368534.27 | M7: 广告配套 | N7: 40 | O7: WS技术号3个 | P7: 0.56666667 | S7: =SUMIF(M:M,"深圳芳林子",N:N) -> 570.65 | T7: 深圳芳林子
C8: 收入 | G8: 2 | H8: 45870 | I8: 德国股票粉（1）组【张小强】 | J8: 7520 | K8: 7月31日 德国股票粉（1）组【张小强】 7/31 F17群 有效12 7/31 Q3 有效8 7/31 A3 有效27 合计: （12+8+27）*160=7520 | L8: 0.61458333 | M8: 凤凰渠道-泰华 | N8: 6601.28 | O8: (7115.57-1427.5)*1.15+30*2=6601.28 | P8: 0.67916667 | S8: =SUMIF(M:M,"印度企业户 欧洲美金户",N:N) -> 10544.56 | T8: 印度企业户 欧洲美金户
C9: =C21 -> 888102.54 | G9: 3 | H9: 45870 | M9: 凤凰渠道-泰华 | N9: 8424.59 | O9: (8441.3-1115.57)*1.15=8,424.59 | P9: 0.89930556 | S9: =SUMIF(M:M,"凤凰渠道-泰华",N:N) -> 48872.05 | T9: 凤凰渠道-泰华
C10: 支出 | G10: 4 | H10: 45871 | M10: 广告配套 | N10: 500 | O10: 矿工费 | P10: 0.43611111 | S10: =SUMIF(M:M,"Vcc-102524 服务费1（泰华）",N:N) -> 202 | T10: Vcc-102524 服务费1（泰华）
C11: =C23 -> 775771.79 | G11: 5 | H11: 45871 | I11: 德国股票粉（1）组【张小强】 | J11: 3040 | K11: 7月31日 德国股票粉（1）组【张小强】 7/31 J3 有效8 7/31 A1有效9 S5有效2 共计有效11 合计: （8+9+2）*160=3040 | L11: 0.69722222 | M11: 凤凰渠道-泰华 | N11: 12075 | O11: 0500*1.15=12075 | P11: 17：26 | S11: =SUMIF(M:M,"🌹R|泰华&云峰合作群美金企业户12+1",N:N) -> 2262.4 | T11: 🌹R|泰华&云峰合作群美金企业户12+1
C12: 结余 | G12: 6 | H12: 45871 | M12: 凤凰渠道-泰华 | N12: 4600 | O12: 4000*1.15=4600 | P12: 0.92638889 | S12: =SUMIF(M:M,"GT&SHEN 欧洲户８＋１ 港60+5+1",N:N) -> 13287.51 | T12: GT&SHEN 欧洲户８＋１ 港60+5+1
C13: =C9-C11 -> 112330.75 | G13: 7 | H13: 45871 | M13: 广告配套 | N13: 101.5 | O13: 账单户2 | P13: 0.97569444 | S13: =SUMIF(M:M,"印度户印尼企业户",N:N) -> 29569.46 | T13: 印度户印尼企业户
G14: 8 | H14: 45871 | M14: Vcc-102524 服务费1（泰华） | N14: 202 | O14: 200*1.01=202 | P14: 0.99375 | S14: =SUMIF(M:M,"Y-5208 FB欧/美户",N:N) -> 5075 | T14: Y-5208 FB欧/美户
C15: 任意时段查询 | G15: 9 | H15: 45872 | M15: 凤凰渠道-泰华 | N15: 4600 | O15: 4000*1.15=4600 | P15: 0.99861111 | S15: =SUMIF(M:M,"印尼企业户",N:N) -> 1150 | T15: 印尼企业户
C16: 起始日期： | G16: 10 | H16: 45872 | M16: 后勤支出 | N16: 37375.427 | O16: 7月分红-LH，373754.27*10%=37375.427 | P16: 0.57291667 | S16: =SUMIF(M:M,"客户服务群-L0816",N:N) -> 3129 | T16: 客户服务群-L0816
C17: 45292 | G17: 11 | H17: 45872 | M17: 后勤支出 | N17: 168189.42 | O17: 7月分红- B哥 373754.27*0.45=168189.4215 | P17: 0.59097222 | S17: =SUMIF(M:M,"志诚三不限",N:N) -> 11710.95 | T17: 志诚三不限
C18: 结束日期： | G18: 12 | H18: 45872 | M18: 广告配套 | N18: 18 | O18: 老主页：5 | P18: 0.64305556 | S18: =SUMIF(M:M,"黑泽",N:N) -> 60 | T18: 黑泽
C19: 72805 | G19: 13 | H19: 45872 | M19: 凤凰渠道-泰华 | N19: 7475 | O19: 6500*1.15=7475 | P19: 0.75486111 | S19: =SUMIF(M:M,"欧洲户10➕1-Nancy",N:N) -> 1665 | T19: 欧洲户10➕1-Nancy
C20: 收入 | G20: 14 | H20: 45873 | M20: 后勤支出 | N20: 10000 | O20: 换汇RMB | P20: 0.81388889 | S20: =SUMIF(M:M,"海总新渠道",N:N) -> 1080 | T20: 海总新渠道
C21: =SUMIFS(J:J,H:H,">="&$C$17,H:H,"<="&$C$19) -> 888102.54 | G21: 15 | H21: 45873 | M21: 广告配套 | N21: 1010 | O21: 主页：15 ；老主页：36；千粉主页：50；个号：45；三解：10；BM15 | P21: 0.62291667 | S21: =SUMIF(M:M,"路人互动",N:N) -> 779.89 | T21: 路人互动
C22: 支出 | G22: 16 | H22: 45873 | M22: 凤凰渠道-泰华 | N22: 5096.18 | O22: (7000-2568.54)*1.15=5096.18 | P22: 22：31 | S22: =SUMIF(M:M,"马来英_阿稳",N:N) -> 11440 | T22: 马来英_阿稳
C23: =SUMIFS(N:N,H:H,">="&$C$17,H:H,"<="&$C$19) -> 775771.79 | G23: 17 | H23: 45874 | M23: 🌹R|泰华&云峰合作群美金企业户12+1 | N23: 1131.2 | O23: 1000*1.12*1.01= 1,131.2 | P23: 0.9625 | S23: =SUMIF(M:M,"德国德语-阿稳",N:N) -> 2600 | T23: 德国德语-阿稳
C24: 结余 | G24: 18 | H24: 45874 | M24: 后勤支出 | N24: 15024.343 | O24: 发工资 | P24: 0.6375 | S24: =SUMIF(M:M,"海总-小日子，意大利🇮🇹",N:N) -> 5000 | T24: 海总-小日子，意大利🇮🇹
C25: =C21-C23 -> 112330.75 | G25: 19 | H25: 45874 | M25: 后勤支出 | N25: 10434.579 | O25: 发工资 | P25: 0.64166667 | S25: =SUMIF(M:M,"阿稳-IN",N:N) -> 17280 | T25: 阿稳-IN
G26: 20 | H26: 45874 | M26: 后勤支出 | N26: 13790.168 | O26: 发工资 | P26: 0.63888889 | S26: =SUMIF(M:M,"印度23期",N:N) -> 12060 | T26: 印度23期 | U26: 退款
G27: 21 | H27: 45874 | M27: 后勤支出 | N27: 697.64789 | O27: 发工资 | P27: 0.64236111 | S27: =SUMIF(M:M,"B1印度",N:N) -> 24064 | T27: B1印度 | U27: 退款
G28: 22 | H28: 45874 | M28: 后勤支出 | N28: 7775.2256 | O28: 发工资 | P28: 0.64027778 | S28: =SUMIF(M:M,"海总-德国；意大利",N:N) -> 105935 | T28: 海总-德国；意大利
G29: 23 | H29: 45874 | M29: 后勤支出 | N29: 7738.063 | O29: 发工资 | P29: 0.64375 | S29: =SUMIF(M:M,"印度驻场-lala(郑总）",N:N) -> 43309 | T29: 印度驻场-lala(郑总）
G30: 24 | H30: 45874 | M30: 后勤支出 | N30: 6175.9153 | O30: 发工资 | P30: 0.64513889 | S30: =SUM(S4:S29) -> 775771.79
G31: 25 | H31: 45874 | M31: 后勤支出 | N31: 6701.7337 | O31: 发工资 | P31: 0.64652778
G32: 26 | H32: 45874 | M32: 后勤支出 | N32: 5000 | O32: 发工资 | P32: 0.64722222 | S32: 往上支出-------------------分割线-------------------往下收入
G33: 27 | H33: 45874 | I33: 阿水 印度mom 11+1 | J33: 4222.37 | K33: 退款 | L33: 0.72222222
G34: 28 | H34: 45874 | I34: 印度15期 | J34: 16772 | K34: 14期补粉 | L34: 0.79444444 | S34: =SUMIF(I:I,"德国股票粉（1）组【张小强】",J:J) -> 133280 | T34: 德国股票粉（1）组【张小强】
G35: 29 | H35: 45874 | I35: 印度15期 | J35: 22372 | K35: 15期补粉 | L35: 0.79861111 | M35: 印度企业户 欧洲美金户 | N35: 70.9 | O35: 60+10*1.09=70.9U | P35: 21：35 | S35: =SUMIF(I:I,"印度15期",J:J) -> 39144 | T35: 印度15期
G36: 30 | H36: 45875 | I36: 德国股票粉（1）组【张小强】 | J36: 800 | K36: 8月4日 德国股票粉（1）组【张小强】 8/4 X2有效2 8/4 M6有效1 8/4 J4有效2 合计: （2+1+2）*160=800 | L36: 0.56527778 | M36: GT&SHEN 欧洲户８＋１ 港60+5+1 | N36: 110 | O36: 100*1.1=110 | P36: 17：39 | S36: =SUMIF(I:I,"印度25期",J:J) -> 1928 | T36: 印度25期
G37: 31 | H37: 45875 | M37: GT&SHEN 欧洲户８＋１ 港60+5+1 | N37: 211.8 | O37: 60*3开户费+10*3*1.06=211.8 | P37: 0.76736111 | S37: =SUMIF(I:I,"波贝6期",J:J) -> 36232 | T37: 波贝6期
G38: 32 | H38: 45875 | M38: 广告配套 | N38: 243.62 | O38: 住宅Ip 120G | P38: 0.76944444 | S38: =SUMIF(I:I,"B1印度",J:J) -> 50000 | T38: B1印度
G39: 33 | H39: 45875 | M39: 深圳芳林子 | N39: 570.65 | O39: 500*1.13*1.01=570.65 | P39: 0.91805556 | S39: =SUMIF(I:I,"意大利第5梯队610",J:J) -> 7620 | T39: 意大利第5梯队610
G40: 34 | H40: 45875 | M40: 印度驻场-lala(郑总） | N40: 483 | P40: 22：04 | S40: =SUMIF(I:I,"印度16期",J:J) -> 30408 | T40: 印度16期
G41: 35 | H41: 45875 | I41: 印度25期 | J41: 1928 | L41: 11：37 | S41: =SUMIF(I:I,"渠道BF 德国F",J:J) -> 8000 | T41: 渠道BF 德国F
G42: 36 | H42: 45876 | I42: 钱包差值 | J42: 35.437 | S42: =SUMIF(I:I,"渠道L 英文L 马来",J:J) -> 18000 | T42: 渠道L 英文L 马来
G43: 37 | H43: 45876 | M43: 印度户印尼企业户 | N43: 5352.58 | O43: 4937.58+415.01=5352.58 | P43: 0.56388889 | S43: =SUMIF(I:I,"印度23期",J:J) -> 50000 | T43: 印度23期
G44: 38 | H44: 45876 | M44: 广告配套 | N44: 225 | O44: 防护续费 | P44: 13：33 | S44: =SUMIF(I:I,"拉总（印度）",J:J) -> 3816 | T44: 拉总（印度）
G45: 39 | H45: 45876 | M45: Y-5208 FB欧/美户 | N45: 105 | O45: 500*1.1-445=105 | P45: 15：16 | S45: =SUMIF(I:I,"印度17期",J:J) -> 30000 | T45: 印度17期
G46: 40 | H46: 45876 | I46: 波贝6期 | J46: 30000 | L46: 15：20 | M46: 海总-德国；意大利 | N46: 6500 | P46: 0.67777778 | S46: =SUMIF(I:I,"西班牙大区1组资源-张小强",J:J) -> 220 | T46: 西班牙大区1组资源-张小强
G47: 41 | H47: 45876 | M47: 印尼企业户 | N47: 1150 | O47: 1000*1.15=1150 | P47: 17：42 | S47: =SUMIF(I:I,"深圳芳林子",J:J) -> 19982.64 | T47: 深圳芳林子 | U47: 退款
G48: 42 | H48: 45876 | M48: GT&SHEN 欧洲户８＋１ 港60+5+1 | N48: 530 | O48: 500*1.06=530 | P48: 0.53611111 | S48: =SUMIF(I:I,"海总新渠道",J:J) -> 1080 | T48: 海总新渠道 | U48: 退款
G49: 43 | H49: 45877 | I49: 德国股票粉（1）组【张小强】 | J49: 8480 | K49: 8月7日 德国股票粉（1）组【张小强】 8/7 F16 有效17 X2 有效：17 J4 有效：19 共计53 合计: 53*160=8480 | L49: 0.62083333 | M49: 🌹R|泰华&云峰合作群美金企业户12+1 | N49: 1131.2 | O49: 1000*1.12*1.01= 1,131.2 | P49: 0.62361111 | S49: =SUMIF(I:I,"德国德语-阿稳",J:J) -> 1820 | T49: 德国德语-阿稳 | U49: 退款
G50: 44 | H50: 45877 | M50: Y-5208 FB欧/美户 | N50: 550 | O50: 500×1.1=550 | P50: 0.63194444 | S50: =SUMIF(I:I,"海总-德国；意大利",J:J) -> 7670 | T50: 海总-德国；意大利 | U50: 退款
G51: 45 | H51: 45877 | M51: 印度驻场-lala(郑总） | N51: 28244 | P51: 0.64583333 | S51: =SUMIF(I:I,"凤凰渠道-泰华",J:J) -> 16135.85 | T51: 凤凰渠道-泰华 | U51: 退款
G52: 46 | H52: 45877 | I52: B1印度 | J52: 50000 | L52: 0.70069444 | S52: =SUMIF(I:I,"海总-小日子，意大利🇮🇹",J:J) -> 2150 | T52: 海总-小日子，意大利🇮🇹 | U52: 退款
G53: 47 | H53: 45877 | I53: 海总新渠道 10+1 | J53: 39337.47 | L53: 0.70555556 | M53: GT&SHEN 欧洲户８＋１ 港60+5+1 | N53: 530 | O53: 500*1.06=530 | P53: 17：17 | S53: =SUMIF(I:I,"济宁韦宁&香港有意思 二不限 3%",J:J) -> 1411.75 | T53: 济宁韦宁&香港有意思 二不限 3% | U53: 退款
G54: 48 | H54: 45877 | I54: 印度企业户 欧洲美金户 | J54: 9409 | L54: 0.73541667 | M54: GT&SHEN 欧洲户８＋１ 港60+5+1 | N54: 812.4 | O54: (500+4*10)*1.06+60*4=812.4 | P54: 18：25 | S54: =SUMIF(I:I,"海总-MC开户对接群",J:J) -> 2522 | T54: 海总-MC开户对接群 | U54: 退款
G55: 49 | H55: 45877 | M55: 海总-德国；意大利 | N55: 9620 | P55: 0.82569444 | S55: =SUMIF(I:I,"Vcc-102524 服务费1（泰华）",J:J) -> 192.95 | T55: Vcc-102524 服务费1（泰华） | U55: 退款
G56: 50 | H56: 45877 | I56: 印尼企业户 | J56: 1150 | L56: 0.94444444 | S56: =SUMIF(I:I,"路人互动-海总（50-7）山",J:J) -> 1116.98 | T56: 路人互动-海总（50-7）山 | U56: 退款
G57: 51 | H57: 45878 | I57: 意大利第5梯队610 | J57: 960 | L57: 0.20555556 | M57: 广告配套 | N57: 29 | O57: 个号*5 | P57: 0.5375 | S57: =SUMIF(I:I,"海总新渠道 10+1",J:J) -> 39337.47 | T57: 海总新渠道 10+1 | U57: 退款
G58: 52 | H58: 45878 | I58: 德国股票粉（1）组【张小强】 | J58: 11200 | K58: 8月8日 德国股票粉（1）组【张小强】 8/8 T19 有效20 T22有效18 Q3 有效17 S6 有效15 合计: (20+18+17+15)*160=11200 | L58: 0.60555556 | M58: GT&SHEN 欧洲户８＋１ 港60+5+1 | N58: 1060 | O58: 1000*1.06=1060 | P58: 0.73402778 | S58: =SUMIF(I:I,"印尼企业户",J:J) -> 1150 | T58: 印尼企业户 | U58: 退款
G59: 53 | H59: 45878 | M59: 印度驻场-lala(郑总） | N59: 4991 | P59: 0.83819444 | S59: =SUMIF(I:I,"印度企业户 欧洲美金户",J:J) -> 12092.82 | T59: 印度企业户 欧洲美金户 | U59: 退款
G60: 54 | H60: 45878 | M60: GT&SHEN 欧洲户８＋１ 港60+5+1 | N60: 1060 | O60: 1000*1.06=1060 | P60: 0.94305556 | S60: =SUMIF(I:I,"阿水 印度mom 11+1",J:J) -> 4222.37 | T60: 阿水 印度mom 11+1 | U60: 退款
G61: 55 | H61: 45878 | M61: Y-5208 FB欧/美户 | N61: 550 | O61: 500×1.1=550 | P61: 0.94930556 | S61: =SUMIF(I:I,"钱包差值",J:J) -> 35.437 | T61: 钱包差值
G62: 56 | H62: 45878 | M62: GT&SHEN 欧洲户８＋１ 港60+5+1 | N62: 2120 | O62: 2000*1.06=2120 | P62: 0.95277778 | S62: =J7 -> 368534.27 | T62: 7月结余
G63: 57 | H63: 45879 | M63: GT&SHEN 欧洲户８＋１ 港60+5+1 | N63: 1731.2 | O63: 60*2开户+(1500+10*2)*1.06=1731.2 | P63: 0.58888889 | S63: =SUM(S34:S62) -> 888102.54
G64: 58 | H64: 45879 | I64: 德国股票粉（1）组【张小强】 | J64: 2880 | K64: 8月9日 德国股票粉（1）组【张小强】 8/9 A1 有效15 8/9 S7 有效3 合计: (15+3)*160=2880 | L64: 0.67430556 | M64: 印度企业户 欧洲美金户 | N64: 550 | O64: 500*1.1=550U | P64: 17：45
G65: 59 | H65: 45879 | M65: 海总-德国；意大利 | N65: 9230 | P65: 0.87430556
G66: 60 | H66: 45879 | M66: GT&SHEN 欧洲户８＋１ 港60+5+1 | N66: 872 | O66: (500+100*3)*1.09=872 | P66: 0.93125
G67: 61 | H67: 45880 | I67: 德国股票粉（1）组【张小强】 | J67: 9920 | K67: 8月10日 德国股票粉（1）组【张小强】 8/10 F18有效1 8/10 S3有效3 8/10 C5有效22 8/10 T20有效19 8/10 有效17 合计: (1+3+22+19+17)*160=9920 | L67: 0.50277778 | M67: 广告配套 | N67: 58 | O67: 个号*10 | P67: 0.55902778
G68: 62 | H68: 45880 | I68: 意大利第5梯队610 | J68: 960 | K68: 8月8日 有效1已结算 8月9日 有效3 8月10日 有效5 合计：8*120=960 | M68: GT&SHEN 欧洲户８＋１ 港60+5+1 | N68: 1060 | O68: 1000*1.06=1060 | P68: 0.69027778
G69: 63 | H69: 45880 | M69: 广告配套 | N69: 29 | O69: BM45*5 | P69: 0.75416667
G70: 64 | H70: 45880 | M70: 广告配套 | N70: 754 | O70: 明细：账单户：2；30主页：1；老主页：8；老主页：65；千粉主页：2；主页：6；BM：15；个号：35；耐用号：5 | P70: 0.76736111
G71: 65 | H71: 45880 | M71: 海总-德国；意大利 | N71: 6500 | P71: 0.78402778
G72: 66 | H72: 45880 | M72: 印度企业户 欧洲美金户 | N72: 540.44 | O72: （500-8.69）*1.1=540.44U | P72: 0.89236111
G73: 67 | H73: 45880 | I73: 波贝6期 | J73: 6232 | L73: 0.92152778
G74: 68 | H74: 45881 | M74: GT&SHEN 欧洲户８＋１ 港60+5+1 | N74: 180 | O74: 开户费60*3，备用金510-充值30=480 | P74: 0.58194444
G75: 69 | H75: 45881 | M75: 海总-德国；意大利 | N75: 9100 | P75: 0.59513889
G76: 70 | H76: 45881 | I76: 德国股票粉（1）组【张小强】 | J76: 14240 | K76: 8月11日 德国股票粉（1）组【张小强】 8/11 A3 有效21 8/11 J7 有效24 8/11 M13 有效21 8/11 F18有效7 8/11 J5有效16 合计: (21+24+21+7+16)*160=14240 | L76: 0.73472222 | M76: B1印度 | N76: 24064 | O76: 退款 | P76: 0.70972222
G77: 71 | H77: 45881 | M77: Y-5208 FB欧/美户 | N77: 550 | O77: 500×1.1=550 | P77: 20：12
G78: 72 | H78: 45881 | M78: 印度企业户 欧洲美金户 | N78: 550 | O78: 500×1.1=550 | P78: 0.85
G79: 73 | H79: 45881 | I79: 路人互动-海总（50-7）山 | J79: 1116.98 | L79: 20：51
G80: 74 | H80: 45882 | M80: GT&SHEN 欧洲户８＋１ 港60+5+1 | N80: 120 | O80: 开户费60*2，备用金480+9.61-充值20=469.61 | P80: 0.58055556
G81: 75 | H81: 45882 | M81: 海总-德国；意大利 | N81: 9200 | P81: 0.60208333
G82: 76 | H82: 45882 | M82: 广告配套 | N82: 58 | O82: BM45*5; 个号40*5 | P82: 14：29
G83: 77 | H83: 45882 | I83: 德国股票粉（1）组【张小强】 | J83: 11520 | K83: 8月12日 德国股票粉（1）组【张小强】 8/12 F18 有效23 8/12 M13有效21 8/12 M13有效22 8/12 J4有效6 合计: (23+21+22+6)*160=11520 | L83: 15：40 | M83: Y-5208 FB欧/美户 | N83: 1100 | O83: 1000×1.1=1100 | P83: 15：48
G84: 78 | H84: 45882 | M84: 海总-德国；意大利 | N84: 6500 | P84: 0.90972222
G85: 79 | H85: 45882 | M85: 印度企业户 欧洲美金户 | N85: 11.5 | O85: 10*1.5=11.5 | P85: 22：24
G86: 80 | H86: 45882 | M86: 印度企业户 欧洲美金户 | N86: 563.5 | O86: 490*1.5=563.5 | P86: 23：02
G87: 81 | H87: 45883 | I87: 意大利第5梯队610 | J87: 600 | K87: 8月11日 有效1 8月13日有效4 合计：5*120=600 | L87: 07：23
G88: 82 | H88: 45883 | I88: 德国股票粉（1）组【张小强】 | J88: 17120 | K88: 8月13日 德国股票粉（1）组【张小强】 8/13 C5有效24 8/13 A1有效18 8/13 S6 有效20 8/13 X2有效5 8/13 A41 有效19 8/13 Q5 有效20 8/13 J4有效1 合计: (24+18+20+5+19+20+1)*160=17120 | L88: 0.6 | M88: 海总-德国；意大利 | N88: 6630 | P88: 0.62291667
G89: 83 | H89: 45883 | M89: 广告配套 | N89: 88 | O89: BM45*10; 个号40*5 | P89: 0.65625
G90: 84 | H90: 45883 | M90: Y-5208 FB欧/美户 | N90: 1120 | O90: 1000×1.12=1120 | P90: 15：58
G91: 85 | H91: 45883 | M91: Y-5208 FB欧/美户 | N91: 1100 | O91: 1000×1.1=1100 | P91: 0.79722222
G92: 86 | H92: 45883 | M92: 印度企业户 欧洲美金户 | N92: 550 | O92: 500*1.1=550U | P92: 0.80277778
G93: 87 | H93: 45883 | I93: 印度企业户 欧洲美金户 | J93: 2683.82 | K93: 退款 | L93: 0.91111111
G94: 88 | H94: 45884 | I94: Vcc-102524 服务费1（泰华） | J94: 192.95 | K94: 退款 | L94: 0.48819444 | M94: 海总-德国；意大利 | N94: 18590 | P94: 0.62638889
G95: 89 | H95: 45884 | I95: 德国股票粉（1）组【张小强】 | J95: 15520 | K95: 8月14日 德国股票粉（1）组【张小强】 8/14 B101有效21 8/14 A24有效22 8/14 B93有效33 8/14 A41有效21 合计: (21+22+33+21)*160=15520 | L95: 17：32 | M95: 印度企业户 欧洲美金户 | N95: 565 | O95: 500*1.13=565U | P95: 18：07
G96: 90 | H96: 45884 | M96: GT&SHEN 欧洲户８＋１ 港60+5+1 | N96: 523.47 | O96: (500-6.16)*1.06=523.47 | P96: 19：54
G97: 91 | H97: 45885 | I97: 意大利第5梯队610 | J97: 1560 | K97: 8月14日 有效1 8月15日 885群有效6 8月15日 336群 有效6 合计：13*120=1560 | L97: 0.24583333 | M97: 客户服务群-L0816 | N97: 60 | O97: 个号10U*5=50U (110U合并付款，60U是开户费) | P97: 0.51527778
G98: 92 | H98: 45885 | M98: 广告配套 | N98: 50 | O98: 个号10U*5=50U (110U合并付款，60U是开户费) 客户服务群-L0816 | P98: 0.51527778
G99: 93 | H99: 45885 | M99: 印度企业户 欧洲美金户 | N99: 575 | O99: 500*1.15=575U | P99: 0.61319444
G100: 94 | H100: 45885 | I100: 海总-MC开户对接群 | J100: 2522 | K100: 退款 | L100: 0.62222222
G101: 95 | H101: 45885 | I101: 德国股票粉（1）组【张小强】 | J101: 13600 | K101: 8月15日 德国股票粉（1）组【张小强】 8/15 A51 有效32 8/15 B111 有效6 8/15 A12 有效30 8/15 A31 有效17 合计: (32+6+30+17)*160=13600 | L101: 0.67638889
G102: 96 | H102: 45885 | I102: 印度16期 | J102: 30000 | K102: 退款 | L102: 19：33
...

Sheet 2025年7月收支财务报表
C1: 2025年7月收支财务报表
C4: 财务统计 STATISTICS | G4: 7月收支明细 DETAIL | S4: =SUMIF(M:M,"广告配套",N:N) -> 3174.84 | T4: U支出的广告配套（不含RMB支出）
G5: 序号 | H5: 日期 | I5: 收入 | M5: 支出
C6: 月份查询 | I6: 项目 | J6: 金额 | K6: 备注 | L6: 时间 | M6: 项目 | N6: 金额 | O6: 备注 | P6: 时间 | S6: =SUMIF(M:M,"后勤支出",N:N) -> 176614.67 | T6: 后勤支出
C7: 7月 | D7: ▼ | G7: 1 | H7: 45839 | I7: 6月结余 | J7: ='2025年6月收支财务报表'!C25 -> 138682.47 | S7: =SUMIF(M:M,"深圳芳林子",N:N) -> 339022.42 | T7: 深圳芳林子
C8: 收入 | G8: 2 | H8: 45839 | I8: 拉总（印度）24 | J8: 4656 | L8: 0.022222222 | M8: 深圳芳林子 | N8: 16915.53 | O8: 14193.26*1.18*1.01=16915.53 | P8: 0.60486111 | S8: =SUMIF(M:M,"印度企业户 欧洲美金户",N:N) -> 40671.09 | T8: 印度企业户 欧洲美金户
C9: =C21 -> 1512556.2 | G9: 3 | H9: 45839 | I9: 德国股票粉（2）组【张小强】 | J9: 2185.6 | K9: 6月29-6/30日 德国股票粉（2）组【张小强】 6/29 C2确认有效3.33个 6/30 C2确认有效4个 M1确认有效6.33个 合计: （3.33+10.33）*160=2185.6 | L9: 0.66458333 | S9: =SUMIF(M:M,"Nancy-印度户15➕1",N:N) -> 9511.52 | T9: Nancy-印度户15➕1
C10: 支出 | G10: 4 | H10: 45839 | I10: 印度12期 | J10: 50000 | L10: 0.66527778 | M10: 深圳芳林子 | N10: 1394.76 | O10: 1190.48*1.16*1.01=1394.76 | P10: 0.74583333 | S10: =SUMIF(M:M,"海总新渠道 10+1",N:N) -> 175152.61 | T10: 海总新渠道 10+1
C11: =C23 -> 1144021.9 | G11: 5 | H11: 45839 | M11: 印度企业户 欧洲美金户 | N11: 594.18 | O11: （1000-487.78）*1.16=594.18U | P11: 0.75486111 | S11: =SUMIF(M:M,"启航广告费",N:N) -> 18417.42 | T11: 启航广告费
C12: 结余 | G12: 6 | H12: 45839 | I12: 印度汤总 | J12: 28000 | L12: 0.87013889 | S12: =SUMIF(M:M,"十月二不限——（泰华）",N:N) -> 3034 | T12: 十月二不限——（泰华）
C13: =C9-C11 -> 368534.27 | G13: 7 | H13: 45839 | I13: 拉总（印度）24 | J13: 6240 | L13: 0.99166667 | S13: =SUMIF(M:M,"凤凰渠道-泰华",N:N) -> 168932.69 | T13: 凤凰渠道-泰华
G14: 8 | H14: 45840 | M14: 深圳芳林子 | N14: 2789.52 | O14: 200000/84*1.16*1.01=2789.52 | P14: 0.49722222 | S14: =SUMIF(M:M,"济宁韦宁&香港有意思 二不限 3%",N:N) -> 28902.08 | T14: 济宁韦宁&香港有意思 二不限 3%
C15: 任意时段查询 | G15: 9 | H15: 45840 | I15: 波贝3期 | J15: 50000 | L15: 0.56944444 | M15: 印度企业户 欧洲美金户 | N15: 1740 | O15: 1500*1.16=1740U | P15: 0.57847222 | S15: =SUMIF(M:M,"海总/户合作mom",N:N) -> 5750 | T15: 海总/户合作mom
C16: 起始日期： | G16: 10 | H16: 45840 | M16: 深圳芳林子 | N16: 47672 | O16: 40000*1.18*1.01=47672 | P16: 0.58055556 | S16: =SUMIF(M:M,"路人互动-海总（50-7）山",N:N) -> 5600 | T16: 路人互动-海总（50-7）山
C17: 45292 | G17: 11 | H17: 45840 | M17: Nancy-印度户15➕1 | N17: 9511.52 | O17: 8189*1.15*1.01=9511.52 | P17: 0.58402778 | S17: =SUMIF(M:M,"印度户印尼企业户",N:N) -> 62567.59 | T17: 印度户印尼企业户
C18: 结束日期： | G18: 12 | H18: 45840 | M18: 后勤支出 | N18: 62407.111 | O18: 6月分红- B哥138,682.47*0.45=62407.1115 | P18: 0.58611111 | S18: =SUMIF(M:M,"Y-5208 FB欧/美户",N:N) -> 1645 | T18: Y-5208 FB欧/美户
C19: 72805 | G19: 13 | H19: 45840 | I19: 德国蟑螂哥渠道 | J19: 480 | K19: 6/30 有效1，7/1 有效2 | L19: 15：09 | M19: 印度企业户 欧洲美金户 | N19: 3480 | O19: 3000*1.16=3480U | P19: 0.77916667 | S19: =SUMIF(M:M,"阿水 印度mom 11+1",N:N) -> 5600 | T19: 阿水 印度mom 11+1
C20: 收入 | G20: 14 | H20: 45840 | I20: 印度汤总 | J20: 28000 | L20: 0.89513889 | S20: =SUMIF(M:M,"波贝5期",N:N) -> 6116 | T20: 波贝5期
C21: =SUMIFS(J:J,H:H,">="&$C$17,H:H,"<="&$C$19) -> 1512556.2 | G21: 15 | H21: 45841 | M21: 深圳芳林子 | N21: 35422.58 | O21: 29721.92*1.18*1.01=35422.58 | P21: 0.57986111 | S21: =SUMIF(M:M,"波贝4期",N:N) -> 9328 | T21: 波贝4期
C22: 支出 | G22: 16 | H22: 45841 | I22: 拉总（印度）24 | J22: 1560 | L22: 0.61458333 | S22: =SUMIF(M:M,"预支",N:N) -> 50000 | T22: 预支
C23: =SUMIFS(N:N,H:H,">="&$C$17,H:H,"<="&$C$19) -> 1144021.9 | G23: 17 | H23: 45841 | I23: 印度12期 | J23: 50000 | L23: 0.63541667 | M23: 印度企业户 欧洲美金户 | N23: 11141.72 | O23: (10000-395.07)*1.16=11141.72 | P23: 0.6375 | S23: =SUMIF(M:M,"印度20期",N:N) -> 15540 | T23: 印度20期
C24: 结余 | G24: 18 | H24: 45841 | M24: 深圳芳林子 | N24: 11918 | O24: 10000*1.18*1.01=11918 | P24: 0.64513889 | S24: =SUMIF(M:M,"渠道BF 德国B",N:N) -> 4290 | T24: 渠道BF 德国B
C25: =C21-C23 -> 368534.27 | G25: 19 | H25: 45841 | I25: 德国股票粉（2）组【张小强】 | J25: 2025.6 | K25: 7月1-2日 德国股票粉（2）组【张小强】 7/1 T3确认有效7.66个 K4确认有效1个 7/2 F6确认有效4 合计: （8.66+4）*160=2025.6 | L25: 0.64861111 | S25: =SUMIF(M:M,"波贝3期",N:N) -> 14152 | T25: 波贝3期
G26: 20 | H26: 45841 | I26: 印度汤总 | J26: 42000 | L26: 0.88958333 | S26: =SUM(S4:S25) -> 1144021.9
G27: 21 | H27: 45842 | I27: 拉总（印度）24 | J27: 4800 | L27: 0.0069444444 | M27: 印度企业户 欧洲美金户 | N27: 8050 | O27: 7000*1.15=8050U | P27: 0.57569444
G28: 22 | H28: 45842 | M28: 深圳芳林子 | N28: 7251.8 | O28: (1000*1.13+150+5000*1.18)*1.01=7251.8 | P28: 0.58611111 | S28: 往上支出-------------------分割线-------------------往下收入
G29: 23 | H29: 45842 | M29: 印度企业户 欧洲美金户 | N29: 1150 | O29: 1000*1.15=1150U | P29: 0.63194444
G30: 24 | H30: 45842 | M30: 海总新渠道 10+1 | N30: 2260 | O30: 2000*1.13=2260 | P30: 0.66805556 | S30: =SUMIF(I:I,"拉总（印度）24",J:J) -> 41040 | T30: 拉总（印度）24
G31: 25 | H31: 45842 | I31: Nancy-印度户15➕1 | J31: 11323.12 | L31: 0.68125 | M31: 启航广告费 | N31: 2087.72 | O31: 6/7-7/4 : 4100+544.45-2556.73=2087.72 | P31: 0.7375 | S31: =SUMIF(I:I,"德国股票粉（2）组【张小强】",J:J) -> 4371.2 | T31: 德国股票粉（2）组【张小强】
G32: 26 | H32: 45842 | M32: 海总新渠道 10+1 | N32: 1130 | O32: 1000*1.13=1130 | P32: 0.78402778 | S32: =SUMIF(I:I,"德国股票粉（3）组【张小强】",J:J) -> 68904 | T32: 德国股票粉（3）组【张小强】
G33: 27 | H33: 45842 | I33: 波贝3期 | J33: 50000 | L33: 0.82013889 | S33: =SUMIF(I:I,"印度12期",J:J) -> 100000 | T33: 印度12期
G34: 28 | H34: 45842 | I34: 印度汤总 | J34: 12488 | L34: 0.95347222 | S34: =SUMIF(I:I,"印度13期",J:J) -> 50000 | T34: 印度13期
G35: 29 | H35: 45842 | I35: 拉总（印度）24 | J35: 8184 | L35: 0.98541667 | S35: =SUMIF(I:I,"印度14期",J:J) -> 50000 | T35: 印度14期
G36: 30 | H36: 45843 | M36: 后勤支出 | N36: 8147.0055 | O36: 发工资 | P36: 0.62708333 | S36: =SUMIF(I:I,"印度15期",J:J) -> 129228 | T36: 印度15期
G37: 31 | H37: 45843 | M37: 后勤支出 | N37: 7389.3272 | O37: 发工资 | P37: 0.62847222 | S37: =SUMIF(I:I,"印度汤总",J:J) -> 110488 | T37: 印度汤总
G38: 32 | H38: 45843 | M38: 后勤支出 | N38: 6170.5728 | O38: 发工资 | P38: 0.62986111 | S38: =SUMIF(I:I,"波贝3期",J:J) -> 100000 | T38: 波贝3期
G39: 33 | H39: 45843 | M39: 后勤支出 | N39: 675.38028 | O39: 发工资 | P39: 0.63125 | S39: =SUMIF(I:I,"波贝4期",J:J) -> 150000 | T39: 波贝4期
G40: 34 | H40: 45843 | M40: 后勤支出 | N40: 2657.5775 | O40: 发工资 | P40: 0.63263889 | S40: =SUMIF(I:I,"德国蟑螂哥渠道",J:J) -> 18400 | T40: 德国蟑螂哥渠道
G41: 35 | H41: 45843 | M41: 后勤支出 | N41: 816.90141 | O41: 发工资 | P41: 0.63333333 | S41: =SUMIF(I:I,"印度20期",J:J) -> 100800 | T41: 印度20期
G42: 36 | H42: 45843 | M42: 后勤支出 | N42: 4684.6175 | O42: 发工资 | P42: 0.63472222 | S42: =SUMIF(I:I,"印度21期",J:J) -> 50000 | T42: 印度21期
G43: 37 | H43: 45843 | M43: 后勤支出 | N43: 870.35028 | O43: 发工资 | P43: 0.63541667 | S43: =SUMIF(I:I,"海总-西班牙测试",J:J) -> 320 | T43: 海总-西班牙测试
G44: 38 | H44: 45843 | M44: 后勤支出 | N44: 902.49207 | O44: 发工资 | P44: 0.63680556 | S44: =SUMIF(I:I,"印度22期",J:J) -> 51248 | T44: 印度22期
G45: 39 | H45: 45843 | M45: 后勤支出 | N45: 563.38028 | O45: 发工资 | P45: 0.6375 | S45: =SUMIF(I:I,"印度24期",J:J) -> 100000 | T45: 印度24期
G46: 40 | H46: 45843 | M46: 后勤支出 | N46: 27.3 | O46: 发工资 | P46: 0.63958333 | S46: =SUMIF(I:I,"德国（海哥）",J:J) -> 7080 | T46: 德国（海哥）
G47: 41 | H47: 45843 | M47: 后勤支出 | N47: 5000 | O47: 发工资 | P47: 0.64027778 | S47: =SUMIF(I:I,"印度25期",J:J) -> 80000 | T47: 印度25期
G48: 42 | H48: 45843 | M48: 后勤支出 | N48: 13868.247 | O48: 6月分红- LH，138,682.47*10%=13868.247 | P48: 0.64652778 | S48: =SUMIF(I:I,"德国股票粉（1）组【张小强】",J:J) -> 9600 | T48: 德国股票粉（1）组【张小强】
G49: 43 | H49: 45843 | M49: 启航广告费 | N49: 2377.77 | O49: 1600*1.1/0.99-1600+600=2377.77 | P49: 0.88611111 | S49: =SUMIF(I:I,"B1印度",J:J) -> 50000 | T49: B1印度
G50: 44 | H50: 45844 | M50: 后勤支出 | N50: 27.3 | O50: 发工资 | P50: 0.50277778 | S50: =SUMIF(I:I,"意大利3期",J:J) -> 80000 | T50: 意大利3期
G51: 45 | H51: 45844 | I51: 济宁韦宁&香港有意思 二不限 3% | J51: 209.79 | L51: 0.69305556 | S51: =SUMIF(I:I,"老傅渠道",J:J) -> 140 | T51: 老傅渠道
G52: 46 | H52: 45844 | I52: 德国股票粉（3）组【张小强】 | J52: 1280 | L52: 0.70625 | S52: =SUMIF(I:I,"开户美国三不限户",J:J) -> 694.36 | T52: 开户美国三不限户
G53: 47 | H53: 45844 | I53: 德国股票粉（2）组【张小强】 | J53: 160 | L53: 0.70833333 | S53: =SUMIF(I:I,"海总/户合作mom",J:J) -> 5156 | T53: 海总/户合作mom
G54: 48 | H54: 45844 | M54: 波贝3期 | N54: 14152 | O54: 退款 | P54: 0.95277778 | S54: =SUMIF(I:I,"泰华&ME-FB海外户对接群",J:J) -> 1933.22 | T54: 泰华&ME-FB海外户对接群
G55: 49 | H55: 45845 | M55: 渠道BF 德国B | N55: 4290 | O55: 退款 | P55: 0.45347222 | S55: =SUMIF(I:I,"黑泽-欧洲户对接",J:J) -> 1120.8 | T55: 黑泽-欧洲户对接
G56: 50 | H56: 45845 | M56: 印度企业户 欧洲美金户 | N56: 5037.26 | O56: （5000-619.77）*1.15=5037.26U | P56: 0.62152778 | S56: =SUMIF(I:I,"济宁韦宁&香港有意思 二不限 3%",J:J) -> 209.79 | T56: 济宁韦宁&香港有意思 二不限 3%
G57: 51 | H57: 45845 | M57: 深圳芳林子 | N57: 15493.4 | O57: 13000*1.18*1.01=15493.4 | P57: 0.62361111 | S57: =SUMIF(I:I,"Nancy-印度户15➕1",J:J) -> 11323.12 | T57: Nancy-印度户15➕1
G58: 52 | H58: 45845 | M58: 海总新渠道 10+1 | N58: 3390 | O58: 3000*1.13=3390 | P58: 0.62986111 | S58: =SUMIF(I:I,"海总新渠道 10+1",J:J) -> 1817.25 | T58: 海总新渠道 10+1
G59: 53 | H59: 45845 | I59: 印度20期 | J59: 50400 | L59: 0.85347222 | S59: =J7 -> 138682.47 | T59: 6月结余
G60: 54 | H60: 45846 | I60: 拉总（印度）24 | J60: 3144 | L60: 0.038888889 | M60: 后勤支出 | N60: 62407.111 | O60: 6月分红- 张总138,682.47*0.45=62407.1115 | P60: 0.43263889 | S60: =SUM(S30:S59) -> 1512556.2
G61: 55 | H61: 45846 | M61: 广告配套 | N61: 100 | O61: 20个端口 | P61: 0.47430556
G62: 56 | H62: 45846 | M62: 广告配套 | N62: 225 | O62: 防护续费 | P62: 0.54861111
G63: 57 | H63: 45846 | M63: 深圳芳林子 | N63: 9412.86 | O63: 7898.02*1.18*1.01=9412.86 | P63: 0.58055556
G64: 58 | H64: 45846 | M64: 印度企业户 欧洲美金户 | N64: 3450 | O64: 3000*1.15=3450U | P64: 0.58194444
G65: 59 | H65: 45846 | M65: 海总新渠道 10+1 | N65: 3390 | O65: 3000*1.13=3390 | P65: 0.58263889
G66: 60 | H66: 45846 | I66: 德国股票粉（3）组【张小强】 | J66: 2772.8 | K66: 7月6-7日德国股票粉（3）组【张小强】 7/6 G25 有效2.66 k33 有效8.33 共计11 7/7 G-25有效6.33 合计: （11+6.33）*160=2772.8 | L66: 0.60902778
G67: 61 | H67: 45846 | I67: 黑泽-欧洲户对接 | J67: 1120.8 | K67: 退款 | L67: 0.70277778 | M67: 启航广告费 | N67: 2222.23 | O67: 2000*1.1/0.99=2222.23 | P67: 0.86944444
G68: 62 | H68: 45846 | I68: 拉总（印度）24 | J68: 6024 | L68: 0.92430556
G69: 63 | H69: 45847 | M69: 深圳芳林子 | N69: 21452.4 | O69: (15000+3000)*1.18*1.01=21452.4 | P69: 0.58055556
G70: 64 | H70: 45847 | M70: 海总新渠道 10+1 | N70: 14630 | O70: 3000*1.11+10000*1.13=14630 | P70: 0.58194444
G71: 65 | H71: 45847 | M71: 预支 | N71: 50000 | O71: 7月张总预支5w分红 | P71: 0.77222222
G72: 66 | H72: 45848 | I72: 拉总（印度）24 | J72: 3984 | L72: 0.53333333
G73: 67 | H73: 45848 | M73: 海总新渠道 10+1 | N73: 7970 | O73: 10000*1.13-3000*1.11=7970 | P73: 0.57569444
G74: 68 | H74: 45848 | M74: 深圳芳林子 | N74: 24524.35 | O74: 20577.57*1.18*1.01=24524.35 | P74: 0.57708333
G75: 69 | H75: 45848 | I75: 德国股票粉（3）组【张小强】 | J75: 1760 | K75: 7月8-9日德国股票粉（3）组【张小强】 7/8 k33 有效2 7/9 k33有效3 G25 有效6 共计有效9 合计: （2+3+6）*160=1760 | L75: 0.58819444
G76: 70 | H76: 45848 | I76: 印度13期 | J76: 50000 | L76: 0.67916667
G77: 71 | H77: 45848 | I77: 德国蟑螂哥渠道 | J77: 3520 | K77: 7/7 有效10个 7/8 有效8个 7/9 有效4 合计：(10+8+4)*160=3520 | L77: 0.70138889
G78: 72 | H78: 45848 | I78: 波贝4期 | J78: 50000 | L78: 0.72638889
G79: 73 | H79: 45848 | I79: 印度20期 | J79: 50400 | L79: 0.92638889
G80: 74 | H80: 45849 | M80: 海总新渠道 10+1 | N80: 4520 | O80: 4000*1.13=4,520 | P80: 0.52777778
G81: 75 | H81: 45849 | M81: 深圳芳林子 | N81: 36945.8 | O81: 31000*1.18*1.01=36945.8 | P81: 0.59861111
G82: 76 | H82: 45849 | I82: 德国蟑螂哥渠道 | J82: 1440 | K82: 7/10 9*160=1440 | L82: 0.67013889 | M82: 深圳芳林子 | N82: 1161.5 | O82: 1000*1.15*1.01=1161.5 | P82: 0.87013889
G83: 77 | H83: 45849 | M83: 十月二不限——（泰华） | N83: 1221 | O83: (2600-1,483.17)*1.01+21*4=1212 | P83: 0.89861111
G84: 78 | H84: 45850 | M84: 海总新渠道 10+1 | N84: 18080 | O84: 16000*1.13=18,080 | P84: 0.51111111
G85: 79 | H85: 45850 | I85: 德国蟑螂哥渠道 | J85: 1600 | K85: 7/11 有效10 10*160=1600 | L85: 14：10 | M85: 深圳芳林子 | N85: 24421.8 | O85: 500*1.16*1.01=585.8，20000*1.18*1.01=23836,585.8+23836=24,421.80 | P85: 0.59236111
G86: 80 | H86: 45850 | I86: 波贝4期 | J86: 50000 | L86: 0.74513889 | M86: 印度企业户 欧洲美金户 | N86: 1130 | O86: 1000×1.13=1130U | P86: 0.78888889
G87: 81 | H87: 45851 | M87: 海总新渠道 10+1 | N87: 11300 | O87: 10000*1.13=11,300 | P87: 0.57013889
G88: 82 | H88: 45851 | M88: 深圳芳林子 | N88: 11918 | O88: 10000*1.18*1.01=11918 | P88: 0.59027778
G89: 83 | H89: 45851 | M89: 印度20期 | N89: 15540 | O89: 退款 | P89: 0.63541667
G90: 84 | H90: 45851 | I90: 德国股票粉（3）组【张小强】 | J90: 5331.2 | K90: 7月10-12日德国股票粉（3）组【张小强】 7/10 L39 有效2 G25 有效2.66 共计有效4.66 7/11 G25有效2 7/12 G25 有效10.33 L39 有效16.33 共计26.66 合计: （4.66+2+26.66）*160=5331.2 | L90: 0.70277778
G91: 85 | H91: 45851 | I91: 波贝4期 | J91: 50000 | L91: 0.90277778 | M91: 十月二不限——（泰华） | N91: 1005 | O91: (1800-805)*1.01=1005 | P91: 0.94722222
G92: 86 | H92: 45852 | I92: 印度21期 | J92: 50000 | L92: 0.95208333
G93: 87 | H93: 45852 | I93: 德国蟑螂哥渠道 | J93: 640 | K93: 7/12 有效4 4*160=640 | L93: 0.17430556 | M93: 海总新渠道 10+1 | N93: 22600 | O93: 20000*1.13=22600 | P93: 0.5875
G94: 88 | H94: 45852 | M94: 深圳芳林子 | N94: 35754 | O94: 30000*1.18*1.01=35754 | P94: 0.59652778
G95: 89 | H95: 45852 | I95: 印度14期 | J95: 50000 | L95: 0.70625 | M95: 凤凰渠道-泰华 | N95: 3068.38 | O95: (3500-2822.94)+456.3225+210+1500*1.15=3068.38 | P95: 0.71527778
G96: 90 | H96: 45852 | I96: 德国股票粉（3）组【张小强】 | J96: 4480 | K96: 7月13日德国股票粉（3）组【张小强】 7/13 E20有效1 008D有效27 共计有效28 合计: 28*160=4480 | L96: 0.77013889
G97: 91 | H97: 45852 | I97: 海总-西班牙测试 | J97: 320 | K97: 6月18-30日 海总-西班牙测试 6/18 有效2 6/27 有效1 6/30 有效1 合计: (2+1+1)*80=320 | L97: 0.75902778 | M97: 十月二不限——（泰华） | N97: 808 | O97: 800*1.01=808
G98: 92 | H98: 45853 | M98: 凤凰渠道-泰华 | N98: 4630 | O98: 4000*1.15+30=4630 | P98: 11：55
G99: 93 | H99: 45853 | M99: 济宁韦宁&香港有意思 二不限 3% | N99: 545 | O99: 500*1.09=545 | P99: 15：21
G100: 94 | H100: 45853 | I100: 德国股票粉（3）组【张小强】 | J100: 9120 | K100: 7月14日德国股票粉（3）组【张小强】 7/14 E20 有效6 7/14 F25 有效32 005A有效2 016群 有效17 共计有效51 合计: (6+51)*160=9120 | L100: 0.66805556 | M100: 广告配套 | N100: 108 | O100: WS计数号9个 | P100: 0.67777778
G101: 95 | H101: 45853 | M101: 海总新渠道 10+1 | N101: 562.61 | O101: （1000-493.14）*1.11=562.61U | P101: 18：33
G102: 96 | H102: 45853 | M102: 凤凰渠道-泰华 | N102: 2360 | O102: 2000*1.15+60=2360 | P102: 20：45
...

Sheet 2025年6月收支财务报表
C1: 2025年6月收支财务报表
C4: 财务统计 STATISTICS | G4: 6月收支明细 DETAIL | S4: =SUMIF(M:M,"广告配套",N:N) -> 2479.45 | T4: U支出的广告配套（不含RMB支出）
G5: 序号 | H5: 日期 | I5: 收入 | M5: 支出
C6: 月份查询 | I6: 项目 | J6: 金额 | K6: 备注 | L6: 时间 | M6: 项目 | N6: 金额 | O6: 备注 | P6: 时间 | S6: =SUMIF(M:M,"后勤支出",N:N) -> 462600.09 | T6: 后勤支出
C7: 6月 | D7: ▼ | G7: 1 | H7: 45809 | I7: 5月结余 | J7: ='2025年5月收支财务报表'!C13 -> 396123 | S7: =SUMIF(M:M,"深圳芳林子",N:N) -> 314138.57 | T7: 深圳芳林子
C8: 收入 | G8: 2 | H8: 45809 | I8: 白马2期 | J8: 30800 | L8: 0.65972222 | S8: =SUMIF(M:M,"海总-MC开户对接群（果果）",N:N) -> 6711.28 | T8: 海总-MC开户对接群（果果）
C9: =C21 -> 965658.5 | G9: 3 | H9: 45809 | I9: 德国 张总（王总） | J9: 2295 | K9: 5月29-31日 德国 张总（王总） 5/29 有效5 5/30 有效3 5/31 有效9 合计：(5+3+9)*135=2295 | L9: 0.66875 | S9: =SUMIF(M:M,"十月二不限——（泰华）",N:N) -> 13192.75 | T9: 十月二不限——（泰华）
C10: 支出 | G10: 4 | H10: 45809 | I10: 拉总（印度）24 | J10: 5856 | L10: 0.94236111 | S10: =SUMIF(M:M,"印度企业户 欧洲美金户",N:N) -> 4743.13 | T10: 印度企业户 欧洲美金户
C11: =C23 -> 826976.03 | G11: 5 | H11: 45810 | M11: 后勤支出 | N11: 178255.35 | O11: 5月分红- B哥396,123.00 *0.45=178255.35 | P11: 0.42152778 | S11: =SUMIF(M:M,"凤凰渠道-泰华",N:N) -> 3896.76 | T11: 凤凰渠道-泰华
C12: 结余 | G12: 6 | H12: 45810 | M12: 深圳芳林子 | N12: 3945.99 | O12: 15000-11448.25=3551.75*1.1*1.01=3945.99 | P12: 0.48958333 | S12: =SUMIF(M:M,"泰华&ME-FB海外户对接群",N:N) -> 3603.2 | T12: 泰华&ME-FB海外户对接群
C13: =C9-C11 -> 138682.47 | G13: 7 | H13: 45810 | I13: 白马3期 | J13: 50400 | L13: 0.60625 | S13: =SUMIF(M:M,"黑泽-欧洲户对接",N:N) -> 2505.8 | T13: 黑泽-欧洲户对接
G14: 8 | H14: 45811 | M14: 广告配套 | N14: 208.21 | O14: 耐用号*5 | P14: 0.44583333 | S14: =SUMIF(M:M,"开户美国三不限户",N:N) -> 1170 | T14: 开户美国三不限户
C15: 任意时段查询 | G15: 9 | H15: 45811 | M15: 深圳芳林子 | N15: 16665 | O15: 15000*1.1*1.01=16665 | P15: 0.4625 | S15: =SUMIF(M:M,"济宁韦宁&香港有意思 二不限 3%",N:N) -> 520 | T15: 济宁韦宁&香港有意思 二不限 3%
C16: 起始日期： | G16: 10 | H16: 45811 | I16: 白马2期 | J16: 31444 | K16: 尾款 | L16: 0.59513889 | S16: =SUMIF(M:M,"海总新渠道 10+1",N:N) -> 1110 | T16: 海总新渠道 10+1
C17: 45292 | G17: 11 | H17: 45811 | I17: 拉总（印度）24 | J17: 840 | L17: 14.31 | S17: =SUMIF(M:M,"ALEX&西班牙",N:N) -> 1275 | T17: ALEX&西班牙
C18: 结束日期： | G18: 12 | H18: 45811 | I18: 德国 张总（王总） | J18: 405 | K18: 6/2 有效3 合计：3*135=405 | L18: 0.70625 | M18: 深圳芳林子 | N18: 11204.01 | O18: （10000-853.32）*1.1918+开户费150*2*1.01=11204.01 | P18: 0.70625 | S18: =SUMIF(M:M,"老傅渠道",N:N) -> 6630 | T18: 老傅渠道
C19: 72805 | G19: 13 | H19: 45811 | I19: 渠道BF 德国B | J19: 6500 | L19: 0.92916667 | S19: =SUMIF(M:M,"印度006对接—henry",N:N) -> 2400 | T19: 印度006对接—henry
C20: 收入 | G20: 14 | H20: 45812 | M20: 深圳芳林子 | N20: 16665 | O20: 15000*1.1*1.01=16665 | P20: 0.45416667 | S20: =SUM(S4:S19) -> 826976.03
C21: =SUMIFS(J:J,H:H,">="&$C$17,H:H,"<="&$C$19) -> 965658.5 | G21: 15 | H21: 45812 | M21: 海总-MC开户对接群（果果） | N21: 505 | O21: 500*1.01=505 | P21: 16：29
C22: 支出 | G22: 16 | H22: 45812 | M22: 十月二不限——（泰华） | N22: 838.89 | O22: (1400-611)*1.01+42=838.89 | P22: 0.88819444 | S22: 往上支出-------------------分割线-------------------往下收入
C23: =SUMIFS(N:N,H:H,">="&$C$17,H:H,"<="&$C$19) -> 826976.03 | G23: 17 | H23: 45813 | I23: 海哥-奥地利 | J23: 270 | L23: 0.55694444 | M23: 印度企业户 欧洲美金户 | N23: 560 | O23: 500*1.12=560U | P23: 0.58958333
C24: 结余 | G24: 18 | H24: 45813 | M24: 后勤支出 | N24: 13932.313 | O24: 发工资 | P24: 0.60763889 | S24: =SUMIF(I:I,"白马2期",J:J) -> 97636 | T24: 白马2期
C25: =C21-C23 -> 138682.47 | G25: 19 | H25: 45813 | M25: 后勤支出 | N25: 8083.98 | O25: 发工资 | P25: 0.60972222 | S25: =SUMIF(I:I,"德国 张总（王总）",J:J) -> 2700 | T25: 德国 张总（王总）
G26: 20 | H26: 45813 | M26: 后勤支出 | N26: 9207.0789 | O26: 发工资 | P26: 0.60972222 | S26: =SUMIF(I:I,"拉总（印度）24",J:J) -> 114504 | T26: 拉总（印度）24
G27: 21 | H27: 45813 | M27: 后勤支出 | N27: 778.36637 | O27: 发工资 | P27: 0.61180556 | S27: =SUMIF(I:I,"白马3期",J:J) -> 166292 | T27: 白马3期
G28: 22 | H28: 45813 | M28: 后勤支出 | N28: 8531.9161 | O28: 发工资 | P28: 0.61319444 | S28: =SUMIF(I:I,"渠道BF 德国B",J:J) -> 6500 | T28: 渠道BF 德国B
G29: 23 | H29: 45813 | M29: 后勤支出 | N29: 910.9009 | O29: 发工资 | P29: 0.61458333 | S29: =SUMIF(I:I,"海哥-奥地利",J:J) -> 3870 | T29: 海哥-奥地利
G30: 24 | H30: 45813 | M30: 后勤支出 | N30: 7253.8711 | O30: 发工资 | P30: 0.61597222 | S30: =SUMIF(I:I,"印度十期",J:J) -> 50000 | T30: 印度十期
G31: 25 | H31: 45813 | M31: 后勤支出 | N31: 667.55556 | O31: 发工资 | P31: 0.61666667 | S31: =SUMIF(I:I,"印度11期",J:J) -> 100000 | T31: 印度11期
G32: 26 | H32: 45813 | M32: 后勤支出 | N32: 555.55556 | O32: 发工资 | P32: 0.61736111 | S32: =SUMIF(I:I,"蟑螂哥西班牙渠道（3梯队）",J:J) -> 100 | T32: 蟑螂哥西班牙渠道（3梯队）
G33: 27 | H33: 45813 | M33: 后勤支出 | N33: 555.55556 | O33: 发工资 | P33: 0.61805556 | S33: =SUMIF(I:I,"德国股票粉（2）组【张小强】",J:J) -> 13549.5 | T33: 德国股票粉（2）组【张小强】
G34: 28 | H34: 45813 | M34: 后勤支出 | N34: 1000 | O34: 发工资 | P34: 0.61944444 | S34: =SUMIF(I:I,"ALEX&西班牙",J:J) -> 1700 | T34: ALEX&西班牙
G35: 29 | H35: 45813 | M35: 后勤支出 | N35: 5000 | O35: 发工资 | P35: 0.62013889 | S35: =SUMIF(I:I,"德国蟑螂哥渠道",J:J) -> 8700 | T35: 德国蟑螂哥渠道
G36: 30 | H36: 45813 | M36: 后勤支出 | N36: 39612.3 | O36: 5月分红- LH，396,123.00*10%=39612.3 | P36: 0.62638889 | S36: =SUMIF(I:I,"GT海总欧洲金融户20+9+1",J:J) -> 424 | T36: GT海总欧洲金融户20+9+1
G37: 31 | H37: 45813 | M37: 十月二不限——（泰华） | N37: 1031 | O37: 1000*1.01+21=1031 | P37: 0.94513889 | S37: =SUMIF(I:I,"GT-HY&papa 二不限",J:J) -> 1360 | T37: GT-HY&papa 二不限
G38: 32 | H38: 45814 | M38: 广告配套 | N38: 36 | O38: BM*10 | P38: 0.50347222 | S38: =SUMIF(I:I,"老傅渠道",J:J) -> 2200 | T38: 老傅渠道
G39: 33 | H39: 45814 | I39: 海哥-奥地利 | J39: 270 | L39: 0.51319444 | M39: 深圳芳林子 | N39: 16210.02 | O39: (15000-409.52)*1.1*1.01=16210.02 | P39: 0.56736111 | S39: =J7 -> 396123 | T39: 5月结余
G40: 34 | H40: 45814 | M40: 印度企业户 欧洲美金户 | N40: 560 | O40: 500*1.12=560U | P40: 0.91319444 | S40: =SUM(S24:S39) -> 965658.5
G41: 35 | H41: 45814 | M41: 凤凰渠道-泰华 | N41: 1911 | O41: （5000-3938.24）+530+320=1911.76 | P41: 0.91458333
G42: 36 | H42: 45815 | I42: 拉总（印度）24 | J42: 11040 | L42: 0.55972222
G43: 37 | H43: 45815 | I43: 海哥-奥地利 | J43: 180 | L43: 0.58888889 | M43: 深圳芳林子 | N43: 11110 | O43: 10000*1.1*1.01=11110 | P43: 0.69652778
G44: 38 | H44: 45815 | I44: 白马3期 | J44: 50000 | L44: 0.79166667
G45: 39 | H45: 45816 | M45: 十月二不限——（泰华） | N45: 1259.26 | O45: (2000-774)*1.01+21=1259.26 | P45: 0.87013889
G46: 40 | H46: 45817 | M46: 深圳芳林子 | N46: 40501 | O46: 15000*1.10*1.01+20000*1.18*1.01=40501 | P46: 0.44444444
G47: 41 | H47: 45817 | I47: 海哥-奥地利 | J47: 360 | L47: 0.45625 | M47: 广告配套 | N47: 100 | O47: 20个端口 | P47: 0.45833333
G48: 42 | H48: 45817 | M48: 深圳芳林子 | N48: 5555 | O48: 5000*1.1*1.01=5555 | P48: 0.47152778
G49: 43 | H49: 45817 | M49: 广告配套 | N49: 225 | O49: 防护续费 | P49: 0.4875
G50: 44 | H50: 45817 | M50: 海总-MC开户对接群（果果） | N50: 270.77 | O50: (500-231.91)*1.01=270.77 | P50: 0.66597222
G51: 45 | H51: 45817 | I51: 印度十期 | J51: 50000 | L51: 0.66805556 | M51: 十月二不限——（泰华） | N51: 1010 | O51: 1000*1.01=1010 | P51: 0.80416667
G52: 46 | H52: 45817 | I52: 白马3期 | J52: 50000 | L52: 0.99722222
G53: 47 | H53: 45818 | I53: 海哥-奥地利 | J53: 540 | L53: 0.50763889
G54: 48 | H54: 45818 | I54: 老傅渠道 | J54: 2200 | K54: 退款 | L54: 0.56597222 | M54: 深圳芳林子 | N54: 43127 | O54: 12000*1.10*1.01+25000*1.18*1.01=43127 | P54: 0.58263889
G55: 49 | H55: 45818 | M55: 海总-MC开户对接群（果果） | N55: 505 | O55: 500*1.01=505 | P55: 0.82777778
G56: 50 | H56: 45818 | M56: 十月二不限——（泰华） | N56: 972 | O56: 900*1.01+21*3=972 | P56: 0.88819444
G57: 51 | H57: 45819 | I57: 海哥-奥地利 | J57: 270 | L57: 0.43333333 | M57: 广告配套 | N57: 208.69 | O57: 耐用号*5 | P57: 0.52916667
G58: 52 | H58: 45819 | M58: 深圳芳林子 | N58: 31269.6 | O58: 12000*1.18*1.01+15000*1.10*1.01+150*2*1.01=31269.6 | P58: 0.58541667
G59: 53 | H59: 45819 | I59: 白马2期 | J59: 35392 | K59: 余款 | L59: 0.69930556 | M59: 印度006对接—henry | N59: 2400 | P59: 0.81805556
G60: 54 | H60: 45819 | M60: 海总-MC开户对接群（果果） | N60: 505 | O60: 500*1.01=505 | P60: 0.84444444
G61: 55 | H61: 45820 | I61: 海哥-奥地利 | J61: 810 | L61: 0.45069444 | M61: 深圳芳林子 | N61: 25330.8 | O61: 11000*1.18*1.01+11000*1.10*1.01=25330.8 | P61: 0.575
G62: 56 | H62: 45820 | M62: 海总-MC开户对接群（果果） | N62: 635.34 | O62: (1000-370.95)*1.01=635.34 | P62: 0.64097222
G63: 57 | H63: 45820 | M63: 深圳芳林子 | N63: 4444 | O63: 4000*1.01*1.1=4444 | P63: 0.65347222
G64: 58 | H64: 45820 | I64: 印度11期 | J64: 50000 | L64: 0.80694444 | M64: 十月二不限——（泰华） | N64: 1803.86 | O64: (2300-514)*1.01=1803.86 | P64: 0.90902778
G65: 59 | H65: 45821 | I65: 白马3期 | J65: 15892 | L65: 0.55 | M65: 深圳芳林子 | N65: 50439.4 | O65: 33000*1.18*1.01+10000*1.10*1.01=50439.4 | P65: 0.58125
G66: 60 | H66: 45821 | M66: 后勤支出 | N66: 178255.35 | O66: 5月分红- 张总396,123.00 *0.45=178255.35 | P66: 0.67083333
G67: 61 | H67: 45821 | M67: 凤凰渠道-泰华 | N67: 1985.76 | O67: 3000-1435+420=1985+0.76=1985.76 | P67: 0.68263889
G68: 62 | H68: 45821 | M68: 海总-MC开户对接群（果果） | N68: 183 | O68: （1300-1118.81）*1.01=183.0019 | P68: 0.75763889
G69: 63 | H69: 45821 | M69: 广告配套 | N69: 142 | O69: WS计数号13个 | P69: 0.86527778
G70: 64 | H70: 45821 | I70: 海哥-奥地利 | J70: 810 | L70: 0.88888889 | M70: 十月二不限——（泰华） | N70: 1153 | O70: 1100*1.01+42=1153 | P70: 0.90625
G71: 65 | H71: 45822 | I71: 海哥-奥地利 | J71: 270 | L71: 0.47083333
G72: 66 | H72: 45822 | I72: 拉总（印度）24 | J72: 3192 | L72: 0.58125 | M72: 广告配套 | N72: 209.1 | O72: 耐用号*5 | P72: 0.65555556
G73: 67 | H73: 45822 | M73: 海总-MC开户对接群（果果） | N73: 505 | O73: 500*1.01=505 | P73: 0.72083333
G74: 68 | H74: 45822 | I74: 印度11期 | J74: 50000 | L74: 0.81041667
G75: 69 | H75: 45823 | M75: 十月二不限——（泰华） | N75: 1025.15 | O75: (1700-685)*1.01=1025.15 | P75: 0.86597222
G76: 70 | H76: 45824 | I76: 德国股票粉（2）组【张小强】 | J76: 1350 | K76: 6月15日 德国股票粉（2）组【张小强】 6/15 C2有效4 F1有效5 共计有效9 合计: 9*150=1350 | L76: 0.47916667 | M76: 深圳芳林子 | N76: 13978.4 | O76: 4000*2*1.18*1.01+4000*1.10*1.01=13978.4 | P76: 0.57569444
G77: 71 | H77: 45824 | M77: 广告配套 | N77: 500 | O77: 换TRX | P77: 0.58194444
G78: 72 | H78: 45824 | I78: GT海总欧洲金融户20+9+1 | J78: 424 | L78: 0.65069444
G79: 73 | H79: 45824 | I79: GT-HY&papa 二不限 | J79: 1088 | L79: 0.65138889 | M79: 十月二不限——（泰华） | N79: 1010 | O79: 1000*1.01=1010 | P79: 0.90833333
G80: 74 | H80: 45825 | I80: 拉总（印度）24 | J80: 4416 | L80: 12：59 | M80: 深圳芳林子 | N80: 9130.4 | O80: 3000*1.18*1.01+5000*1.10*1.01=9130.4 | P80: 0.57361111
G81: 75 | H81: 45825 | M81: 海总-MC开户对接群（果果） | N81: 573.52 | O81: （500*2-432.16）*1.01=573.52 | P81: 0.88263889
G82: 76 | H82: 45825 | M82: 泰华&ME-FB海外户对接群 | N82: 1283.2 | O82: 2000*1.16+50-1086.8=1283.2 | P82: 0.89166667
G83: 77 | H83: 45825 | M83: 十月二不限——（泰华） | N83: 1306.94 | O83: (1400-106)*1.01=1306.94 | P83: 0.89583333
G84: 78 | H84: 45825 | M84: 泰华&ME-FB海外户对接群 | N84: 2320 | O84: 2000*1.16=2320 | P84: 0.93472222
G85: 79 | H85: 45825 | M85: 海总-MC开户对接群（果果） | N85: 505 | O85: 500*1.01=505 | P85: 0.97916667
G86: 80 | H86: 45826 | I86: 拉总（印度）24 | J86: 31104 | L86: 0.49166667 | M86: 深圳芳林子 | N86: 4191.76 | O86: (9000-5482.83)*1.18*1.01=4191.76 | P86: 0.56875
G87: 81 | H87: 45826 | M87: 广告配套 | N87: 200 | O87: 防护续费 | P87: 0.58958333
G88: 82 | H88: 45826 | I88: 德国股票粉（2）组【张小强】 | J88: 1500 | K88: 6月16-17 日 德国股票粉（2）组【张小强】 6/16 M1群有效1 6/17 T2有效7 H1有效2 合计: （1+7+2）*150=1500 | L88: 0.59305556
G89: 83 | H89: 45826 | I89: 海哥-奥地利 | J89: 90 | L89: 0.60902778 | M89: 印度企业户 欧洲美金户 | N89: 603.47 | O89: (2000-1461.19)*1.12=603.47 | P89: 0.76527778
G90: 84 | H90: 45826 | I90: 蟑螂哥西班牙渠道（3梯队） | J90: 100 | L90: 0.80833333
G91: 85 | H91: 45827 | M91: 海总-MC开户对接群（果果） | N91: 1185.53 | O91: (1500-326.2)*1.01=1185.53 | P91: 0.59027778
G92: 86 | H92: 45828 | M92: 十月二不限——（泰华） | N92: 963.54 | O92: (2100-1146)*1.01=963.54 | P92: 0.48958333
G93: 87 | H93: 45828 | M93: 深圳芳林子 | N93: 3575.4 | O93: 3000*1.18*1.01=3575.4 | P93: 0.58055556
G94: 88 | H94: 45828 | I94: 德国股票粉（2）组【张小强】 | J94: 1350 | K94: 6月18-19 日 德国股票粉（2）组【张小强】 6/18 L2有效2 J2有效3 6/19 M5有效1 K3有效3 合计: （2+3+1+3）*150=1350 | L94: 0.58680556
G95: 89 | H95: 45828 | I95: 拉总（印度）24 | J95: 11280 | L95: 0.58888889 | M95: 印度企业户 欧洲美金户 | N95: 560 | O95: 500*1.12=560U | P95: 0.60347222
G96: 90 | H96: 45828 | M96: 深圳芳林子 | N96: 1343.3 | O96: 1000*1.18*1.01+150*1.01=1343.3 | P96: 0.62916667
G97: 91 | H97: 45828 | M97: 印度企业户 欧洲美金户 | N97: 560 | O97: 500*1.12=560U | P97: 0.725
G98: 92 | H98: 45829 | M98: 深圳芳林子 | N98: 3575.4 | O98: 3000*1.18*1.01=3575.4 | P98: 0.58888889
G99: 93 | H99: 45829 | I99: 拉总（印度）24 | J99: 15624 | L99: 0.63680556 | M99: 印度企业户 欧洲美金户 | N99: 560 | O99: 500*1.12=560U | P99: 0.97222222
G100: 94 | H100: 45831 | M100: 黑泽-欧洲户对接 | N100: 354.2 | O100: (3500-3285.30)*1.0908+30*4=354.20 | P100: 0.59236111
G101: 95 | H101: 45831 | I101: 德国股票粉（2）组【张小强】 | J101: 1500 | K101: 6月20-23日 德国股票粉（2）组【张小强】 6/20 B5有效1 A3有效2 6/21 B5确认有效1 A3确认有效1 6/22 A5确认有效5个 合计: （3+2+5）*150=1500 | L101: 16：22
G102: 96 | H102: 45831 | I102: ALEX&西班牙 | J102: 1700 | L102: 17：19 | M102: 海总-MC开户对接群（果果） | N102: 430.56 | O102: （1000-573.7）*1.01=430.56 | P102: 0.73055556
...

Sheet 2025年5月收支财务报表
C1: 2025年5月收支财务报表
C4: 财务统计 STATISTICS | G4: 5月收支明细 DETAIL | S4: =SUMIF(M:M,"广告配套",N:N) -> 3004.2273 | T4: U支出的广告配套（不含RMB支出）
G5: 序号 | H5: 日期 | I5: 收入 | M5: 支出
C6: 月份查询 | I6: 项目 | J6: 金额 | K6: 备注 | L6: 时间 | M6: 项目 | N6: 金额 | O6: 备注 | P6: 时间 | S6: =SUMIF(M:M,"后勤支出",N:N) -> 160029.02 | T6: 后勤支出
C7: 5月 | D7: ▼ | G7: 1 | H7: 45778 | I7: 4月结余 | J7: ='2025年4月收支财务报表'!C13 -> 234903.21 | M7: 深圳芳林子 | N7: 19998 | O7: 18000*1.1*1.01=19998 | P7: 0.45347222 | S7: =SUMIF(M:M,"深圳芳林子",N:N) -> 615726.92 | T7: 深圳芳林子
C8: 收入 | G8: 2 | H8: 45778 | M8: 深圳芳林子 | N8: 5555 | O8: 5000*1.1*1.01=5555 | P8: 0.48819444 | S8: =SUMIF(M:M,"十月二不限——（泰华）",N:N) -> 15197.11 | T8: 十月二不限——（泰华）
C9: =C21 -> 1361013.5 | G9: 3 | H9: 45778 | M9: 广告配套 | N9: 500 | O9: 矿工费TRX | P9: 0.63958333 | S9: =SUMIF(M:M,"印度企业户 欧洲美金户",N:N) -> 27871 | T9: 印度企业户 欧洲美金户
C10: 支出 | G10: 4 | H10: 45778 | M10: 意大利（海哥） | N10: 10 | P10: 0.69166667 | S10: =SUMIF(M:M,"Y-5208 FB欧/美户",N:N) -> 3986.8 | T10: Y-5208 FB欧/美户
C11: =C23 -> 964890.53 | G11: 5 | H11: 45778 | M11: 意大利（海哥） | N11: =21000-N10 -> 20990 | O11: 30000-75*120=21000（退款） | P11: 0.7 | S11: =SUMIF(M:M,"海总-MC开户对接群（果果）",N:N) -> 9923.28 | T11: 海总-MC开户对接群（果果）
C12: 结余 | G12: 6 | H12: 45778 | M12: 十月二不限——（泰华） | N12: 1435 | P12: 0.71111111 | S12: =SUMIF(M:M,"海总-黑泽-欧洲户对接",N:N) -> 3983.33 | T12: 海总-黑泽-欧洲户对接
C13: =C9-C11 -> 396123 | G13: 7 | H13: 45778 | I13: 德国 张总（王总） | J13: 3915 | K13: 4月30日 德国 张总（王总） 4/30 德国单导 有效26 4/30 H1 有效3 合计：(26+3)*135=3915 | L13: 0.81875 | M13: 广告配套 | N13: 34 | O13: 开电报会员一年测试 | P13: 0.81944444 | S13: =SUMIF(M:M,"启航广告费",N:N) -> 4545.64 | T13: 启航广告费
G14: 8 | H14: 45778 | M14: 广告配套 | N14: 282 | O14: IP+ws计数号 | P14: 0.83402778 | S14: =SUMIF(M:M,"泰华&ME-FB海外户对接群-Mark",N:N) -> 1385 | T14: 泰华&ME-FB海外户对接群-Mark
C15: 任意时段查询 | G15: 9 | H15: 45778 | M15: 十月二不限——（泰华） | N15: 1010 | P15: 0.99652778 | S15: =SUMIF(M:M,"Nancy-印度户15➕1",N:N) -> 20642.2 | T15: Nancy-印度户15➕1
C16: 起始日期： | G16: 10 | H16: 45779 | M16: 老傅渠道 | N16: 8470 | P16: 0.00069444444 | S16: =SUMIF(M:M,"T86 共享额度户P6",N:N) -> 1100 | T16: T86 共享额度户P6
C17: 45292 | G17: 11 | H17: 45779 | M17: 印度企业户 欧洲美金户 | N17: 11110 | O17: 10000*1.11=11100U，转多了10U | P17: 0.44236111
C18: 结束日期： | G18: 12 | H18: 45779 | M18: 深圳芳林子 | N18: 8888 | O18: 8000*1.1*1.01=8888 | P18: 0.45347222
C19: 72805 | G19: 13 | H19: 45779 | M19: Y-5208 FB欧/美户 | N19: 3270 | O19: 3000×1.09=3270 | P19: 0.61597222
C20: 收入 | G20: 14 | H20: 45779 | I20: 印度6期 | J20: 36824 | K20: 尾款 | L20: 0.65347222 | S20: =SUMIF(M:M,"意大利（海哥）",N:N) -> 21000 | T20: 意大利（海哥） | U20: 退款
C21: =SUMIFS(J:J,H:H,">="&$C$17,H:H,"<="&$C$19) -> 1361013.5 | G21: 15 | H21: 45779 | I21: 德国 张总（王总） | J21: 6210 | K21: 5.1 德国单导 4915215411390 7 4915213020236 5 4915217743336 12 4915219367517 5 4915212897643 5 4915210591435 7 4915510564480 5 共计46 合计：46*135=6210 | L21: 0.87569444 | M21: 后勤支出 | N21: 52310.7 | O21: 4月分红- B哥116,246*0.45=52310.7 | P21: 0.91666667 | S21: =SUMIF(M:M,"渠道F 马来K",N:N) -> 130 | T21: 渠道F 马来K | U21: 退款
C22: 支出 | G22: 16 | H22: 45779 | M22: 十月二不限——（泰华） | N22: 947.38 | O22: 900-162=738*1.01=745.38+202=947.38 | P22: 0.99791667 | S22: =SUMIF(M:M,"印度006对接—henry",N:N) -> 759 | T22: 印度006对接—henry
C23: =SUMIFS(N:N,H:H,">="&$C$17,H:H,"<="&$C$19) -> 964890.53 | G23: 17 | H23: 45780 | M23: 深圳芳林子 | N23: 25118.7 | O23: 21000*1.1*1.01=23331，1500*1.18*1.01=1787.7，合计：25118.7 | P23: 0.42916667 | S23: =SUMIF(M:M,"印度驻场-lala(郑总）",N:N) -> 3887 | T23: 印度驻场-lala(郑总）
C24: 结余 | G24: 18 | H24: 45780 | M24: 印度企业户 欧洲美金户 | N24: 6650 | O24: 6000*1.11=6660-10=6650U | P24: 0.52361111 | S24: =SUMIF(M:M,"日本001对接_Chirs",N:N) -> 24420 | T24: 日本001对接_Chirs
C25: =C21-C23 -> 396123 | G25: 19 | H25: 45780 | I25: 德国 张总（王总） | J25: 10395 | K25: 5月2日 德国 张总（王总） 5/2 德国单导 4915215411390 5 4915213020236 5 4915217743336 5 4915219367517 3 4915212897643 2 4915210678752 6 4915210276617 5 4915210756851 6 4915217927758 5 4915217743410 2 4915213086520 6 4915212392118 1 4917686639880 5 4915510461712 5 4915210797499 5 4917673986846 5 4915510564480 6 4915210746583 0 总 77 合计：77*135=10395 | L25: 0.85 | S25: =SUMIF(M:M,"老傅渠道",N:N) -> 47300 | T25: 老傅渠道
G26: 20 | H26: 45781 | M26: 深圳芳林子 | N26: 27775 | O26: 25000*1.1*1.01=27775 | P26: 0.45833333 | S26: =SUM(S4:S25) -> 964890.53
G27: 21 | H27: 45782 | I27: 印度7期 | J27: 50000 | L27: 0.79166667
G28: 22 | H28: 45782 | M28: 印度企业户 欧洲美金户 | N28: 6216 | O28: 5600*1.11=6216U | P28: 0.43958333 | S28: 往上支出-------------------分割线-------------------往下收入
G29: 23 | H29: 45782 | M29: 深圳芳林子 | N29: 23331 | O29: (17500+3500)*1.10*1.01=23331 | P29: 0.44027778
G30: 24 | H30: 45782 | M30: 老傅渠道 | N30: 10670 | P30: 0.59027778 | S30: =SUMIF(I:I,"德国 张总（王总）",J:J) -> 38880 | T30: 德国 张总（王总）
G31: 25 | H31: 45782 | M31: 后勤支出 | N31: 9845.852 | O31: 发工资 | P31: 0.64375 | S31: =SUMIF(I:I,"印度6期",J:J) -> 36824 | T31: 印度6期
G32: 26 | H32: 45782 | M32: 后勤支出 | N32: 3428.2577 | O32: 发工资 | P32: 0.64583333 | S32: =SUMIF(I:I,"印度7期",J:J) -> 130000 | T32: 印度7期
G33: 27 | H33: 45782 | M33: 后勤支出 | N33: 2774.057 | O33: 发工资 | P33: 0.64652778 | S33: =SUMIF(I:I,"渠道30 日股粉（张总） 谷歌",J:J) -> 28000 | T33: 渠道30 日股粉（张总） 谷歌
G34: 28 | H34: 45782 | M34: 后勤支出 | N34: 689.81987 | O34: 发工资 | P34: 0.64861111 | S34: =SUMIF(I:I,"印度15期",J:J) -> 7680 | T34: 印度15期
G35: 29 | H35: 45782 | M35: 后勤支出 | N35: 4647.3647 | O35: 发工资 | P35: 0.65 | S35: =SUMIF(I:I,"德国股票粉3组【张小强】",J:J) -> 29025 | T35: 德国股票粉3组【张小强】
G36: 30 | H36: 45782 | M36: 后勤支出 | N36: 889.58003 | O36: 发工资 | P36: 0.65138889 | S36: =SUMIF(I:I,"德国股票粉4组【张小强】",J:J) -> 5714 | T36: 德国股票粉4组【张小强】
G37: 31 | H37: 45782 | M37: 后勤支出 | N37: 3181.2574 | O37: 发工资 | P37: 0.65277778 | S37: =SUMIF(I:I,"印度8期",J:J) -> 202256 | T37: 印度8期
G38: 32 | H38: 45782 | M38: 后勤支出 | N38: 914.5071 | O38: 发工资 | P38: 0.65416667 | S38: =SUMIF(I:I,"印度B1",J:J) -> 23576 | T38: 印度B1
G39: 33 | H39: 45782 | M39: 后勤支出 | N39: 567.85952 | O39: 发工资 | P39: 0.65486111 | S39: =SUMIF(I:I,"印度BB1",J:J) -> 91756 | T39: 印度BB1
G40: 34 | H40: 45782 | M40: 后勤支出 | N40: 566.68771 | O40: 发工资 | P40: 0.65625 | S40: =SUMIF(I:I,"渠道F 马来K",J:J) -> 6500 | T40: 渠道F 马来K
G41: 35 | H41: 45782 | M41: 后勤支出 | N41: 1000 | O41: 发工资 | P41: 0.65902778 | S41: =SUMIF(I:I,"印度9期",J:J) -> 313056 | T41: 印度9期
G42: 36 | H42: 45782 | M42: 后勤支出 | N42: 5277.7778 | O42: 发工资 | P42: 0.65972222 | S42: =SUMIF(I:I,"波贝2期",J:J) -> 124572 | T42: 波贝2期
G43: 37 | H43: 45782 | M43: 后勤支出 | N43: 11624.6 | O43: 4月分红- LH，116,246*10%= 11624.6 | P43: 0.67777778 | S43: =SUMIF(I:I,"印度8期补群",J:J) -> 50000 | T43: 印度8期补群
G44: 38 | H44: 45782 | I44: 印度7期 | J44: 50000 | L44: 0.78611111 | S44: =SUMIF(I:I,"白马2期",J:J) -> 22400 | T44: 白马2期
G45: 39 | H45: 45783 | I45: 渠道30 日股粉（张总） 谷歌 | J45: 12500 | L45: 0.55277778 | M45: 日本001对接_Chirs | N45: 10 | P45: 0.52638889
G46: 40 | H46: 45783 | M46: 日本001对接_Chirs | N46: =6600-N45 -> 6590 | P46: 0.52847222
G47: 41 | H47: 45783 | M47: 后勤支出 | N47: 10000 | O47: 换汇RMB | P47: 0.54583333 | S47: =SUMIF(I:I,"Y-5208 FB欧/美户",J:J) -> 2853.5 | T47: Y-5208 FB欧/美户
G48: 42 | H48: 45783 | I48: 德国 张总（王总） | J48: 5670 | K48: 5月5日 德国 张总（王总） 5/5 邀请码：3EZVVU1NE 工单链接：https://dash.qukazhen.com/web#/accountshow/3EZVVU1NE 访问密码：WZ430 备注信息：王总德国 4915210678752 6 4917686639880 5 4915210276617 6 4915217927758 6 4915210797499 5 4917673986846 5 4915213125027 6 4915210756851 3 4915210746583 0 共计有效 42 合计：42*135=5670 | L48: 0.66805556 | M48: 十月二不限——（泰华） | N48: 1160 | P48: 0.95763889 | S48: =SUMIF(I:I,"T86 共享额度户P6",J:J) -> 971 | T48: T86 共享额度户P6
G49: 43 | H49: 45784 | M49: 海总-MC开户对接群（果果） | N49: 1010 | P49: 0.49444444 | S49: =SUMIF(I:I,"欧洲户&hz唐",J:J) -> 1745.86 | T49: 欧洲户&hz唐
G50: 44 | H50: 45784 | M50: 深圳芳林子 | N50: 1770.67 | O50: 1593.76*1.10*1.01=1770.67 | P50: 0.57847222 | S50: =SUMIF(I:I,"印度企业户 欧洲美金户",J:J) -> 9814.58 | T50: 印度企业户 欧洲美金户
G51: 45 | H51: 45784 | M51: 印度企业户 欧洲美金户 | N51: 2775 | O51: 2500*1.11=2775U | P51: 0.60416667 | S51: =SUMIF(I:I,"CH加白户14➕1-Nancy",J:J) -> 486.38 | T51: CH加白户14➕1-Nancy
G52: 46 | H52: 45784 | M52: 广告配套 | N52: 255.1473 | O52: VPN续费明细：续费1季度 | P52: 0.60972222 | S52: 234903.21 | T52: 4月结余
G53: 47 | H53: 45784 | I53: 印度15期 | J53: 7680 | L53: 0.64166667 | M53: 老傅渠道 | N53: 2860 | P53: 0.65208333 | S53: =SUM(S30:S52) -> 1361013.5
G54: 48 | H54: 45784 | I54: 德国 张总（王总） | J54: 3780 | K54: 5月6日 德国 张总（王总） 5/6 4915217927758 5 4915210797499 6 4917673986846 6 4915213125027 7 4915210756851 1 4915210276617 2 4915210746583 1 总计28 合计：28*135=3780 | L54: 0.88472222 | M54: 日本001对接_Chirs | N54: 7260 | P54: 0.9625
G55: 49 | H55: 45785 | I55: CH加白户14➕1-Nancy | J55: 486.38 | K55: 退款 | L55: 0.11388889 | M55: Y-5208 FB欧/美户 | N55: 635 | O55: 80+500×1.11=635 | P55: 0.84583333
G56: 50 | H56: 45785 | I56: 渠道30 日股粉（张总） 谷歌 | J56: 12500 | L56: 0.93055556
G57: 51 | H57: 45786 | M57: 深圳芳林子 | N57: 22220 | O57: 20000*1.10*1.01=22220 | P57: 0.56944444
G58: 52 | H58: 45786 | M58: 印度企业户 欧洲美金户 | N58: 560 | O58: 500×1.12=560U | P58: 0.65069444
G59: 53 | H59: 45786 | I59: 德国股票粉3组【张小强】 | J59: 4185 | K59: 5月7-8日 德国股票粉二组【张小强】 5/7 55群 有效11 5/8 55群 有效20 合计 (11+20)*135=4185 | L59: 0.67638889 | M59: 海总-MC开户对接群（果果） | N59: 505 | O59: 500*1.01=505 | P59: 0.70138889
G60: 54 | H60: 45786 | I60: 印度8期 | J60: 50000 | L60: 0.72430556 | M60: 老傅渠道 | N60: 5940 | P60: 0.73888889
G61: 55 | H61: 45786 | I61: 印度企业户 欧洲美金户 | J61: 1099 | K61: 退款 | L61: 0.80902778 | M61: 广告配套 | N61: 165 | O61: 主页 | P61: 0.89375
G62: 56 | H62: 45787 | M62: 日本001对接_Chirs | N62: 7040 | P62: 0.50277778
G63: 57 | H63: 45787 | M63: 广告配套 | N63: 225 | O63: 防护续费 | P63: 0.50833333
G64: 58 | H64: 45787 | M64: 十月二不限——（泰华） | N64: 484.8 | P64: 0.51041667
G65: 59 | H65: 45787 | M65: 老傅渠道 | N65: 4950 | P65: 0.57291667
G66: 60 | H66: 45787 | M66: 印度企业户 欧洲美金户 | N66: 560 | O66: 500*1.12=560u | P66: 0.59166667
G67: 61 | H67: 45787 | M67: 广告配套 | N67: 100 | O67: 20个端口 | P67: 0.59652778
G68: 62 | H68: 45787 | M68: 深圳芳林子 | N68: 11796.79 | P68: 0.60694444
G69: 63 | H69: 45787 | I69: 印度B1 | J69: 22400 | L69: 0.61041667
G70: 64 | H70: 45787 | I70: 德国股票粉3组【张小强】 | J70: 4185 | K70: 5月9日 德国股票粉二组【张小强】 5/9 55群 有效13 5/9 59群 有效18 合计: (13+18)*135=4185 | L70: 0.70902778 | M70: 深圳芳林子 | N70: 16664.55 | O70: 14999.6*1.1*1.01=16664.55 | P70: 0.69930556
G71: 65 | H71: 45787 | I71: 德国 张总（王总） | J71: 3645 | K71: 5月7-9日 德国 张总（王总） "5/7 4915210746583 4 4915210756851 1 4915210276617 1 共计有效6" "5/8 4915258379487 3 4917686639880 2 共计有效5" "5/9 4915213086520 4 4915210797499 5 4917673986846 5 4915210276617 1 4915210746583 1 共计有效16" 合计：(6+5+16)*135=3645 | L71: 0.79236111
G72: 66 | H72: 45788 | M72: 深圳芳林子 | N72: 11110 | O72: 10000*1.1*1.01=11110 | P72: 0.49305556
G73: 67 | H73: 45788 | I73: 德国股票粉3组【张小强】 | J73: 6885 | K73: 5月10日 德国股票粉二组【张小强】 5/10 81群 有效21 5/10 45群 有效30 合计: (21+30)*135=6885 | L73: 0.61111111 | M73: 老傅渠道 | N73: 5610 | P73: 0.67222222
G74: 68 | H74: 45789 | M74: 深圳芳林子 | N74: 22220.01 | O74: 20000*1.10*1.01=22220+.01=22220.01 | P74: 0.58263889
G75: 69 | H75: 45789 | I75: 德国股票粉3组【张小强】 | J75: 4185 | K75: 5月11日 德国股票粉二组【张小强】 5/11 44群 有效29 5/11 24群 有效2 合计: (29+2)*135=4185 | L75: 0.72847222 | M75: 深圳芳林子 | N75: 1830.92 | O75: 1647.99*1.10*1.01=1830.92 | P75: 0.7
G76: 70 | H76: 45789 | I76: 印度8期 | J76: 50000 | L76: 0.76458333
G77: 71 | H77: 45790 | I77: 印度B1 | J77: 1176 | L77: 0.59652778 | M77: 海总-MC开户对接群（果果） | N77: 1644 | O77: 2000-372.38=1627.62*1.01=1644 | P77: 0.60416667
G78: 72 | H78: 45790 | M78: 深圳芳林子 | N78: 24442 | O78: 22000*1.10*1.01=24442 | P78: 0.62152778
G79: 73 | H79: 45790 | M79: Y-5208 FB欧/美户 | N79: 81.8 | O79: 40+1000×1.12-(618.01+460.19)=81.8 | P79: 0.70069444
G80: 74 | H80: 45790 | M80: 老傅渠道 | N80: 5170 | P80: 0.72638889
G81: 75 | H81: 45790 | M81: 印度驻场-lala(郑总） | N81: 3243 | P81: 0.87013889
G82: 76 | H82: 45790 | M82: 十月二不限——（泰华） | N82: 776.98 | P82: 0.94027778
G83: 77 | H83: 45791 | M83: 广告配套 | N83: 208.15 | O83: 耐用号*5 | P83: 0.53194444
G84: 78 | H84: 45791 | M84: 深圳芳林子 | N84: 9918.3 | O84: 32000-15000-8072.64=8927.36，8927.36*1.10*1.01=9918.3 | P84: 0.58472222
G85: 79 | H85: 45791 | M85: 海总-黑泽-欧洲户对接 | N85: 454.04 | O85: (500*1.0908)-91.36=454.04 | P85: 0.59791667
G86: 80 | H86: 45791 | I86: 印度BB1 | J86: 20000 | L86: 0.64722222
G87: 81 | H87: 45791 | I87: 德国股票粉3组【张小强】 | J87: 8505 | K87: 5月12-14日 德国股票粉二组【张小强】 5/12 61群 有效13 5/12 24群 有效9 5/13 61群 有效28 5/14 24群 有效13 合计: (13+9+28+13)*135=8505 | L87: 0.59236111
G88: 82 | H88: 45791 | I88: 印度8期 | J88: 50000 | L88: 0.77777778 | M88: 启航广告费 | N88: 1357.29 | P88: 0.82638889
G89: 83 | H89: 45792 | M89: 深圳芳林子 | N89: 18967.8 | O89: 16000*1.10*1.01+1000*1.18*1.01=18967.8 | P89: 0.56805556
G90: 84 | H90: 45792 | M90: 深圳芳林子 | N90: 1111 | O90: 1000*1.10*1.01=1111 | P90: 0.59305556
G91: 85 | H91: 45792 | I91: 渠道30 日股粉（张总） 谷歌 | J91: 3000 | L91: 0.66180556 | M91: 日本001对接_Chirs | N91: 3520 | P91: 0.62222222
G92: 86 | H92: 45792 | M92: 海总-MC开户对接群（果果） | N92: 178.45 | O92: 1000-823.32=176.68*1.01=178.45 | P92: 0.64652778
G93: 87 | H93: 45792 | M93: 十月二不限——（泰华） | N93: 624.98 | O93: (1200-602)*1.01+21=624.98 | P93: 0.67222222
G94: 88 | H94: 45792 | M94: 广告配套 | N94: 18 | O94: 5个BM | P94: 0.675
G95: 89 | H95: 45792 | I95: 德国 张总（王总） | J95: 4860 | K95: 5月10-14日 德国 张总（王总） 5/10 4917686639880 1 4915210276617 1 共计有效2 5/12 4915213086520 5 4917673986846 0 4915217927758 2 有效7 5/13 K3群 有效13 5/14 F7 有效12 E8 有效2 共计有效14 合计：(2+7+13+14)*135=4860 | L95: 0.67847222 | M95: 海总-黑泽-欧洲户对接 | N95: 545.4 | O95: 500*1.08*1.01=545.4 | P95: 0.78680556
G96: 90 | H96: 45792 | I96: 印度8期 | J96: 50000 | L96: 0.79861111
G97: 91 | H97: 45793 | M97: 深圳芳林子 | N97: 26664 | O97: 24000*1.10*1.01=26664 | P97: 0.57430556
G98: 92 | H98: 45793 | M98: 深圳芳林子 | N98: 11110 | O98: 10000*1.10*1.01=11110 | P98: 0.70902778
G99: 93 | H99: 45793 | I99: 印度BB1 | J99: 30000 | L99: 17：44 | M99: 十月二不限——（泰华） | N99: 1599 | O99: 1500*1.01+42*2=1599 | P99: 0.76319444
G100: 94 | H100: 45793 | M100: 海总-MC开户对接群（果果） | N100: 1010 | O100: 1000*1.01=1010 | P100: 0.88611111
G101: 95 | H101: 45793 | M101: 广告配套 | N101: 11 | O101: 3个bm | P101: 0.89513889
G102: 96 | H102: 45793 | M102: 海总-黑泽-欧洲户对接 | N102: 605.4 | O102: 60（开户费）+500*1.08*1.01=605.4 | P102: 0.92638889
...

Sheet 2025年4月收支财务报表
C1: 2025年4月收支财务报表
C4: 财务统计 STATISTICS | G4: 2025年4月收支明细 DETAIL | S4: =SUMIF(M:M,"广告配套",N:N) -> 3018.52 | T4: U支出的广告配套（不含RMB支出）
G5: 序号 | H5: 日期 | I5: 收入 | M5: 支出
C6: 月份查询 | I6: 项目 | J6: 金额 | K6: 备注 | L6: 时间 | M6: 项目 | N6: 金额 | O6: 备注 | P6: 时间 | S6: =SUMIF(M:M,"后勤支出",N:N) -> 259984.87 | T6: 后勤支出
C7: 4月 | D7: ▼ | G7: 1 | H7: 45748 | I7: 3月结余 | J7: ='2025年3月收支财务报表'!C13 -> 323365.14 | M7: 海总-黑泽-欧洲户对接 | N7: 545.4 | O7: 500*1.08*1.01=545.4 | P7: 0.48333333 | S7: =SUMIF(M:M,"海总-黑泽-欧洲户对接",N:N) -> 4543.2 | T7: 海总-黑泽-欧洲户对接
C8: 收入 | G8: 2 | H8: 45748 | I8: 渠道30 日股粉（张总） FB | J8: 100 | L8: 0.4875 | S8: =SUMIF(M:M,"海总- BM户对接",N:N) -> 530 | T8: 海总- BM户对接
C9: =C21 -> 1286870.5 | G9: 3 | H9: 45748 | I9: 渠道30 日股粉（张总） FB | J9: 17900 | K9: 预付100个 | L9: 0.49305556 | M9: 大表哥 FB&意大利 | N9: 10 | P9: 0.57777778 | S9: =SUMIF(M:M,"海总-全球户",N:N) -> 3260 | T9: 海总-全球户
C10: 支出 | G10: 4 | H10: 45748 | M10: 大表哥 FB&意大利 | N10: =1400-N9 -> 1390 | P10: 0.57847222 | S10: =SUMIF(M:M,"深圳芳林子",N:N) -> 320642.63 | T10: 深圳芳林子
C11: =C23 -> 1051967.3 | G11: 5 | H11: 45748 | M11: 海总-黑泽-欧洲户对接 | N11: 545.4 | O11: 500*1.08*1.01=545.4 | P11: 0.59722222 | S11: =SUMIF(M:M,"Y-5208 FB欧/美户",N:N) -> 12009.9 | T11: Y-5208 FB欧/美户
C12: 结余 | G12: 6 | H12: 45748 | M12: 大表哥 FB&意大利 | N12: 3000 | P12: 0.65208333 | S12: =SUMIF(M:M,"十月二不限——（泰华）",N:N) -> 9282 | T12: 十月二不限——（泰华）
C13: =C9-C11 -> 234903.21 | G13: 7 | H13: 45748 | M13: 海总- BM户对接 | N13: 530 | O13: -500*1.06=-530 | P13: 0.67222222 | S13: =SUMIF(M:M,"启航广告费",N:N) -> 1268.25 | T13: 启航广告费
G14: 8 | H14: 45748 | I14: 印度13期 | J14: 11172 | K14: 28*399=11172 | L14: 0.76666667 | M14: 广告配套 | N14: 13 | O14: 6个主页 | P14: 0.83333333 | S14: =SUMIF(M:M,"账单户充值",N:N) -> 9003.62 | T14: 账单户充值
C15: 任意时段查询 | G15: 9 | H15: 45749 | M15: 浩天 意大利对接群 | N15: 1300 | P15: 0.56597222 | S15: =SUMIF(M:M,"印度企业户 欧洲美金户",N:N) -> 78938.92 | T15: 印度企业户 欧洲美金户
C16: 起始日期： | G16: 10 | H16: 45749 | M16: 印度003对接—胖鱼 | N16: 4301 | P16: 0.57222222 | S16: =SUMIF(M:M,"CH加白户14➕1-Nancy",N:N) -> 48788.5 | T16: CH加白户14➕1-Nancy
C17: 45292 | G17: 11 | H17: 45749 | M17: 后勤支出 | N17: 100514.32 | O17: 3月分红- B哥 | P17: 0.60763889 | S17: =SUMIF(M:M,"HY&papa 二不限",N:N) -> 3814.28 | T17: HY&papa 二不限
C18: 结束日期： | G18: 12 | H18: 45749 | M18: 海总-全球户 | N18: 270 | P18: 0.63333333 | S18: =SUMIF(M:M,"MY &Shen SSS户 70+13%U1",N:N) -> 3101.6 | T18: ZJL&Shen 印度企业户 15+1/MY &Shen SSS户 70+13%U1
C19: 72805 | G19: 13 | H19: 45749 | M19: 海总-德国🇩🇪粉 | N19: 10 | P19: 0.64722222 | S19: =SUMIF(M:M,"R9GT&SHEN 欧 ",N:N) -> 1090 | T19: R9GT&SHEN 欧
C20: 收入 | G20: 14 | H20: 45749 | M20: 海总-德国🇩🇪粉 | N20: =1400-N19 -> 1390 | P20: 0.66180556 | S20: =SUMIF(M:M,"Andy- 美金谷歌户25+5%",N:N) -> 321 | T20: Andy- 美金谷歌户25+5%
C21: =SUMIFS(J:J,H:H,">="&$C$17,H:H,"<="&$C$19) -> 1286870.5 | G21: 15 | H21: 45749 | M21: 海总-黑泽-欧洲户对接 | N21: 120 | O21: 开户费 | P21: 0.71111111 | S21: =SUMIF(M:M,"欧洲户&hz唐",N:N) -> 2520 | T21: 欧洲户&hz唐
C22: 支出 | G22: 16 | H22: 45749 | M22: 广告配套 | N22: 31 | O22: 动态IP2个、计数号*2 | P22: 0.81180556 | S22: =SUMIF(M:M,"凤凰渠道-泰华",N:N) -> 2474 | T22: 凤凰渠道-泰华
C23: =SUMIFS(N:N,H:H,">="&$C$17,H:H,"<="&$C$19) -> 1051967.3 | G23: 17 | H23: 45749 | M23: 浩天 意大利对接群 | N23: 3000 | P23: 0.86180556 | S23: =SUMIF(M:M,"钱包转款小额测试",N:N) -> 10 | T23: 钱包转款小额测试
C24: 结余 | G24: 18 | H24: 45749 | I24: 印度4期-啊光 | J24: 50000 | L24: 0.94097222 | S24: =SUMIF(M:M,"大表哥 FB&意大利",N:N) -> 17100 | T24: 大表哥 FB&意大利
C25: =C21-C23 -> 234903.21 | G25: 19 | H25: 45750 | M25: 老傅渠道 | N25: 5360 | P25: 0.56388889 | S25: =SUMIF(M:M,"浩天 意大利对接群",N:N) -> 19200 | T25: 浩天 意大利对接群
G26: 20 | H26: 45750 | M26: 海总-🌙日本🇯🇵-岳 | N26: 10 | P26: 0.56597222 | S26: =SUMIF(M:M,"海总-德国🇩🇪粉",N:N) -> 7900 | T26: 海总-德国🇩🇪粉
G27: 21 | H27: 45750 | M27: 海总-🌙日本🇯🇵-岳 | N27: =4800-N26 -> 4790 | P27: 0.56666667 | S27: =SUMIF(M:M,"老傅渠道",N:N) -> 118680 | T27: 老傅渠道
G28: 22 | H28: 45750 | M28: 广告配套 | N28: 270 | O28: IP*30 | P28: 0.56944444 | S28: =SUMIF(M:M,"海总-🌙日本🇯🇵-岳",N:N) -> 19072 | T28: 海总-🌙日本🇯🇵-岳
G29: 23 | H29: 45750 | M29: 广告配套 | N29: 15 | O29: 7个主页 | P29: 0.58402778 | S29: =SUMIF(M:M,"印度003对接—胖鱼",N:N) -> 5014 | T29: 印度003对接—胖鱼
G30: 24 | H30: 45750 | M30: 深圳芳林子 | N30: 2686.6 | O30: 150*2*1.01+2000*1.18*1.01=2686.6 | P30: 0.65694444 | S30: =SUMIF(M:M,"印度驻场-lala(郑总）",N:N) -> 17411 | T30: 印度驻场-lala(郑总）
G31: 25 | H31: 45750 | M31: 印度驻场-lala(郑总） | N31: 6532 | P31: 0.67361111 | S31: =SUMIF(M:M,"印度006对接—henry",N:N) -> 5543 | T31: 印度006对接—henry
G32: 26 | H32: 45750 | M32: 浩天 意大利对接群 | N32: 3400 | P32: 0.68888889 | S32: =SUMIF(M:M,"渠道30 日股粉（张总） FB",N:N) -> 52740 | T32: 渠道30 日股粉（张总） FB退款 | U32: 4/21已退
G33: 27 | H33: 45750 | M33: 广告配套 | N33: 20 | O33: 9个主页 | P33: 0.88333333 | S33: =SUMIF(M:M,"德国股民单粉——summer",N:N) -> 12150 | T33: 德国股民单粉——summer退款 | U33: 4/10已退
G34: 28 | H34: 45751 | I34: 渠道30 日股粉（张总） FB | J34: 9000 | K34: 预付50个 | L34: 0.50555556 | M34: 浩天 意大利对接群 | N34: 3000 | P34: 0.64097222 | S34: =SUMIF(M:M,"海哥一期（印度1500）",N:N) -> 12556 | T34: 海哥一期（印度1500） | U34: 4/26已退
G35: 29 | H35: 45751 | M35: 老傅渠道 | N35: 8640 | P35: 0.84722222 | S35: 往上支出-------------------分割线-------------------往下收入
G36: 30 | H36: 45751 | I36: 意大利（海哥） | J36: 30000 | L36: 0.98263889 | S36: =SUM(S4:S34) -> 1051967.3
G37: 31 | H37: 45752 | M37: 后勤支出 | N37: 22336.515 | O37: 3月分红- LH | P37: 0.60069444
G38: 32 | H38: 45752 | M38: 后勤支出 | N38: 5096.5079 | O38: 发工资 | P38: 0.62916667 | S38: =SUMIF(I:I,"海总-🌙日本🇯🇵-岳",J:J) -> 7936 | T38: 海总-🌙日本🇯🇵-岳
G39: 33 | H39: 45752 | M39: 后勤支出 | N39: 3489.2132 | O39: 发工资 | P39: 0.63194444 | S39: =SUMIF(I:I,"浩天 意大利对接群",J:J) -> 6300 | T39: 浩天 意大利对接群
G40: 34 | H40: 45752 | M40: 后勤支出 | N40: 2792.003 | O40: 发工资 | P40: 0.63263889 | S40: =SUMIF(I:I,"大表哥 FB&意大利",J:J) -> 2100 | T40: 大表哥 FB&意大利
G41: 35 | H41: 45752 | M41: 后勤支出 | N41: 658.59498 | O41: 发工资 | P41: 0.63333333 | S41: =SUMIF(I:I,"欧洲三不限-泰华3➕1（0.84）",J:J) -> 352.55 | T41: 欧洲三不限-泰华3➕1（0.84）
G42: 36 | H42: 45752 | M42: 后勤支出 | N42: 3745.4435 | O42: 发工资 | P42: 0.63472222 | S42: =SUMIF(I:I,"印度企业户 欧洲美金户下户",J:J) -> 2423.8 | T42: 印度企业户 欧洲美金户下户
G43: 37 | H43: 45752 | M43: 后勤支出 | N43: 846.76058 | O43: 发工资 | P43: 0.63541667 | S43: =SUMIF(I:I,"海总- BM户对接",J:J) -> 497 | T43: 海总- BM户对接
G44: 38 | H44: 45752 | M44: 后勤支出 | N44: 2243.7239 | O44: 发工资 | P44: 0.63680556 | S44: =SUMIF(I:I,"济宁韦宁&香港有意思 二不限 3%",J:J) -> 300 | T44: 济宁韦宁&香港有意思 二不限 3%
G45: 39 | H45: 45752 | M45: 后勤支出 | N45: 667.55556 | O45: 发工资 | P45: 0.6375 | S45: =SUMIF(I:I,"Andy- 美金谷歌户25+5%",J:J) -> 300 | T45: Andy- 美金谷歌户25+5%
G46: 40 | H46: 45752 | M46: 后勤支出 | N46: 1246.5804 | O46: 发工资 | P46: 0.63819444 | S46: =SUMIF(I:I,"CH加白户14➕1-Nancy",J:J) -> 11236 | T46: CH加白户14➕1-Nancy
G47: 41 | H47: 45752 | M47: 后勤支出 | N47: 555.55556 | O47: 发工资 | P47: 0.63958333 | S47: =SUMIF(I:I,"渠道30 日股粉（张总） FB",J:J) -> 171000 | T47: 渠道30 日股粉（张总） FB
G48: 42 | H48: 45752 | M48: 后勤支出 | N48: 5277.7778 | O48: 发工资 | P48: 0.64027778 | S48: =SUMIF(I:I,"印度13期",J:J) -> 11172 | T48: 印度13期
G49: 43 | H49: 45752 | M49: 印度003对接—胖鱼 | N49: 713 | P49: 0.68958333 | S49: =SUMIF(I:I,"印度4期-啊光",J:J) -> 100000 | T49: 印度4期-啊光
G50: 44 | H50: 45752 | I50: 海总-🌙日本🇯🇵-岳 | J50: 4032 | L50: 0.69305556 | M50: 广告配套 | N50: 900 | O50: 机器人防护 | P50: 0.77291667 | S50: =SUMIF(I:I,"意大利（海哥）",J:J) -> 30000 | T50: 意大利（海哥） | U50: 5/1 退21000
G51: 45 | H51: 45752 | M51: 浩天 意大利对接群 | N51: 2500 | P51: 0.84027778 | S51: =SUMIF(I:I,"德国股民单粉——summer",J:J) -> 20250 | T51: 德国股民单粉——summer | U51: 4/10退12150
G52: 46 | H52: 45752 | I52: 渠道30 日股粉（张总） FB | J52: 36000 | K52: 预付200个 | L52: 0.8625 | M52: 老傅渠道 | N52: 23100 | P52: 0.86736111 | S52: =SUMIF(I:I,"意大利二期",J:J) -> 50000 | T52: 意大利二期
G53: 47 | H53: 45752 | M53: 浩天 意大利对接群 | N53: 3000 | P53: 0.92152778 | S53: =SUMIF(I:I,"德国股票粉1组【张小强】4/10开始",J:J) -> 44685 | T53: 德国股票粉1组【张小强】4/10开始
G54: 48 | H54: 45753 | I54: 德国股民单粉——summer | J54: 6750 | L54: 0.03125 | S54: =SUMIF(I:I,"印度5期-阿光",J:J) -> 100000 | T54: 印度5期-阿光4/14开始
G55: 49 | H55: 45753 | M55: 海总-德国🇩🇪粉 | N55: 3000 | P55: 0.54236111 | S55: =SUMIF(I:I,"印度19期",J:J) -> 10528 | T55: 印度19期
G56: 50 | H56: 45753 | M56: 老傅渠道 | N56: 18480 | P56: 0.94236111 | S56: =SUMIF(I:I,"海哥一期（印度1500）",J:J) -> 30000 | T56: 海哥一期（印度1500）
G57: 51 | H57: 45753 | I57: 渠道30 日股粉（张总） FB | J57: 36000 | K57: 预付200个 | L57: 0.94652778 | S57: =SUMIF(I:I,"印度B哥（汤总）",J:J) -> 123200 | T57: 印度B哥（汤总）
G58: 52 | H58: 45754 | M58: 海总-全球户 | N58: 270 | P58: 0.58263889 | S58: =SUMIF(I:I,"印度6期",J:J) -> 130000 | T58: 印度6期
G59: 53 | H59: 45754 | M59: Y-5208 FB欧/美户 | N59: 786.5 | O59: 1000-278.4=721.6×1.09=786.5 | P59: 0.59375 | S59: =SUMIF(I:I,"印度15期",J:J) -> 50000 | T59: 印度15期
G60: 54 | H60: 45754 | I60: 欧洲三不限-泰华3➕1（0.84） | J60: 352.55 | K60: 退款 | L60: 0.59583333 | M60: 十月二不限——（泰华） | N60: 280 | O60: 开户费 | P60: 0.64166667 | S60: =SUMIF(I:I,"渠道F 马来K",J:J) -> 6500 | T60: 渠道F 马来K
G61: 55 | H61: 45754 | M61: 欧洲户&hz唐 | N61: 2520 | O61: 2000×1.16+200=2520 | P61: 0.66388889 | S61: =SUMIF(I:I,"德国 张总（王总）",J:J) -> 4725 | T61: 德国 张总（王总）
G62: 56 | H62: 45754 | I62: 印度企业户 欧洲美金户下户 | J62: 2423.8 | K62: 退款 | L62: 0.67430556 | S62: =SUMIF(I:I,"印度7期",J:J) -> 50000 | T62: 印度7期
G63: 57 | H63: 45754 | I63: 浩天 意大利对接群 | J63: 3300 | K63: 退款 | L63: 0.78194444 | M63: 启航广告费 | N63: 1268.25 | P63: 0.81875 | S63: =J7 -> 323365.14 | T63: 3月结余
G64: 58 | H64: 45754 | M64: 广告配套 | N64: 8.24 | O64: 主页 4 | P64: 0.875 | S64: =SUM(S38:S63) -> 1286870.5
G65: 59 | H65: 45754 | M65: 广告配套 | N65: 8.5 | O65: BM 1 | P65: 0.925
G66: 60 | H66: 45754 | M66: Y-5208 FB欧/美户 | N66: 1120 | O66: 1000×1.12=1120 | P66: 0.92986111
G67: 61 | H67: 45755 | I67: 德国股民单粉——summer | J67: 13500 | L67: 0.10763889 | M67: Y-5208 FB欧/美户 | N67: 1090 | O67: 1000×1.09=1090 | P67: 0.46875
G68: 62 | H68: 45755 | M68: 广告配套 | N68: 8.5 | O68: BM 1 | P68: 0.50486111
G69: 63 | H69: 45755 | M69: 海总-德国🇩🇪粉 | N69: 3100 | P69: 0.51458333
G70: 64 | H70: 45755 | M70: 广告配套 | N70: 365 | O70: 防护续费 | P70: 0.53541667
G71: 65 | H71: 45755 | M71: 海总-全球户 | N71: 540 | O71: 开户费 | P71: 0.63541667
G72: 66 | H72: 45755 | M72: 广告配套 | N72: 12.37 | O72: 主页 6 | P72: 0.83402778
G73: 67 | H73: 45755 | M73: 印度驻场-lala(郑总） | N73: 2139 | P73: 0.90694444
G74: 68 | H74: 45755 | I74: 意大利二期 | J74: 50000 | L74: 0.93333333
G75: 69 | H75: 45756 | M75: 账单户充值 | N75: 1000.52 | P75: 0.43472222
G76: 70 | H76: 45756 | M76: 广告配套 | N76: 51 | O76: 计数器 | P76: 0.43680556
G77: 71 | H77: 45756 | M77: 深圳芳林子 | N77: 184.54 | O77: 166.1*1.10*1.01=184.54 | P77: 0.57361111
G78: 72 | H78: 45756 | M78: 印度006对接—henry | N78: 10 | P78: 0.67013889
G79: 73 | H79: 45756 | M79: 印度006对接—henry | N79: =2300-N78 -> 2290 | P79: 0.675
G80: 74 | H80: 45756 | M80: 海总-全球户 | N80: 1080 | O80: 4套开户费 | P80: 0.76041667
G81: 75 | H81: 45756 | M81: 广告配套 | N81: 40.88 | O81: 耐用号*1 | P81: 0.76597222
G82: 76 | H82: 45756 | M82: 广告配套 | N82: 37.5 | O82: 主页：3;BM：5;主页；1 | P82: 0.87430556
G83: 77 | H83: 45756 | M83: 十月二不限——（泰华） | N83: 74 | O83: 开户费 | P83: 0.88472222
G84: 78 | H84: 45756 | M84: 海总-全球户 | N84: 40 | O84: 耐用BM*4 | P84: 0.91041667
G85: 79 | H85: 45756 | M85: 广告配套 | N85: 50 | O85: 计数器 | P85: 0.93680556
G86: 80 | H86: 45756 | M86: 广告配套 | N86: 122.63 | O86: 耐用号*3 | P86: 0.96458333
G87: 81 | H87: 45757 | M87: 深圳芳林子 | N87: 12301.8 | O87: 10000*1.10*1.01+1000*1.18*1.01=12301.8 | P87: 0.57638889
G88: 82 | H88: 45757 | M88: 海总-全球户 | N88: 270 | O88: 开户费 | P88: 0.60347222
G89: 83 | H89: 45757 | M89: 广告配套 | N89: 5 | O89: 申诉个号1个 | P89: 0.60763889
G90: 84 | H90: 45757 | M90: 十月二不限——（泰华） | N90: 74 | O90: 开户费 | P90: 0.62013889
G91: 85 | H91: 45757 | M91: 账单户充值 | N91: 1000.62 | P91: 0.64791667
G92: 86 | H92: 45757 | M92: 广告配套 | N92: 100 | O92: 计数器 | P92: 0.66180556
G93: 87 | H93: 45757 | M93: 德国股民单粉——summer | N93: 10 | O93: 退款 | P93: 0.66666667
G94: 88 | H94: 45757 | M94: 德国股民单粉——summer | N94: =12150-N93 -> 12140 | O94: 退款 | P94: 0.66944444
G95: 89 | H95: 45757 | M95: Y-5208 FB欧/美户 | N95: 1170.3 | O95: 1000×1.09=1090，1090+80.3=1170.3 | P95: 0.73541667
G96: 90 | H96: 45757 | M96: 海总-德国🇩🇪粉 | N96: 400 | P96: 0.80902778
G97: 91 | H97: 45757 | I97: 印度4期-啊光 | J97: 50000 | L97: 0.82708333 | M97: 海总-🌙日本🇯🇵-岳 | N97: 7360 | P97: 0.87847222
G98: 92 | H98: 45757 | I98: 渠道30 日股粉（张总） FB | J98: 36000 | K98: 预付200个 | L98: 0.87847222 | M98: 广告配套 | N98: 10.22 | O98: 主页：5 | P98: 0.90625
G99: 93 | H99: 45757 | M99: 老傅渠道 | N99: 26990 | P99: 0.94444444
G100: 94 | H100: 45757 | I100: 海总- BM户对接 | J100: 497 | L100: 0.96388889
G101: 95 | H101: 45758 | M101: 深圳芳林子 | N101: 12221 | O101: 11000*1.10*1.01=12221 | P101: 0.57083333
G102: 96 | H102: 45758 | I102: 德国股票粉1组【张小强】4/10开始 | J102: 7425 | K102: 4月10日 德国股票粉二组【张小强】 F6 有效27 B2 有效28 合计 (27+28)*135=7425 | L102: 0.575 | M102: 印度006对接—henry | N102: 1794 | P102: 0.60625
...

Sheet 2025年3月收支财务报表
C1: 2025年3月收支财务报表
C4: 财务统计 STATISTICS | G4: 2025年3月收支明细 DETAIL | S4: =SUMIF(M:M,"广告配套",N:N) -> 3258.6167 | T4: U支出的广告配套（不含RMB支出）
G5: 序号 | H5: 日期 | I5: 收入 | M5: 支出
C6: 月份查询 | I6: 项目 | J6: 金额 | K6: 备注 | L6: 时间 | M6: 项目 | N6: 金额 | O6: 备注 | P6: 时间 | S6: =SUMIF(M:M,"后勤支出",N:N) -> 263202.52 | T6: 后勤支出
C7: 3月 | D7: ▼ | G7: 1 | H7: 45717 | I7: 2月结余 | J7: ='2025年2月收支财务报表'!C25 -> 220136.4 | S7: =SUMIF(M:M,"启航广告费",N:N) -> 21044.15 | T7: 启航广告费
C8: 收入 | G8: 2 | H8: 45717 | I8: 浩天 意大利对接群 | J8: 4900 | K8: 退款 | L8: 0.15555556 | M8: 印度003对接—胖鱼 | N8: 6900 | P8: 0.44375 | S8: =SUMIF(M:M,"CH加白户14➕1",N:N) -> 10554.1 | T8: CH加白户14➕1
C9: =C21 -> 1450200.2 | G9: 3 | H9: 45717 | M9: 印度003对接—胖鱼 | N9: 13800 | P9: 0.59513889 | S9: =SUMIF(M:M,"印度企业户 欧洲美金户下户",N:N) -> 19684 | T9: 印度企业户 欧洲美金户下户
C10: 支出 | G10: 4 | H10: 45717 | I10: 意大利张总单导 | J10: 3720 | K10: 2/27 有效9 1080 2/28 有效31 3720 合计 4800 TLimy52jPz279TiS2LDfpCUYsim33dHTew，地址不变，2/27未结 | L10: 0.60694444 | S10: =SUMIF(M:M,"十月二不限——（泰华）",N:N) -> 1457 | T10: 十月二不限
C11: =C23 -> 1126835.1 | G11: 5 | H11: 45717 | I11: 巴西测试粉 | J11: 1657.06 | K11: 服务费15%，1440.92*1.15= 1657.06 | L11: 0.64722222 | S11: =SUMIF(M:M,"深圳芳林子@SHEN 户",N:N) -> 198077 | T11: 深圳芳林子@SHEN 户
C12: 结余 | G12: 6 | H12: 45717 | M12: 后勤支出 | N12: 50000 | O12: 分红B哥2月分红，220,136.40*0.45= 99061.38 | P12: 0.75 | S12: =SUMIF(M:M,"海总- BM户对接",N:N) -> 200 | T12: 海总- BM户对接
C13: =C9-C11 -> 323365.14 | G13: 7 | H13: 45717 | I13: 印度2期 | J13: 100000 | L13: 0.75902778 | S13: =SUMIF(M:M,"账单户充值",N:N) -> 1722.35 | T13: 账单户充值
G14: 8 | H14: 45717 | I14: 印度（10）金山 | J14: 100 | L14: 0.76527778 | S14: =SUMIF(M:M,"Y-5208 FB欧/美户",N:N) -> 10377.563 | T14: Y-5208 FB欧/美户
C15: 任意时段查询 | G15: 9 | H15: 45717 | I15: 印度（10）金山 | J15: 99900 | L15: 0.76597222 | M15: 印度003对接—胖鱼 | N15: 13800 | P15: 0.80208333 | S15: =SUMIF(M:M,"GTHY&papa 二不限 10+2+1",N:N) -> 10 | T15: GTHY&papa 二不限 10+2+1
C16: 起始日期： | G16: 10 | H16: 45717 | M16: 印度003对接—胖鱼 | N16: 9200 | P16: 0.91875 | S16: =SUMIF(M:M,"GT&SHEN 欧 2%+u1",N:N) -> 1635.86 | T16: GT&SHEN 欧 2%+u1
C17: 45292 | G17: 11 | H17: 45718 | M17: 印度003对接—胖鱼 | N17: 23000 | P17: 0.48680556 | S17: =SUMIF(M:M,"欧洲三不限-泰华3➕1（0.84）",N:N) -> 1329.9 | T17: 欧洲三不限-泰华3➕1（0.84）
C18: 结束日期： | G18: 12 | H18: 45718 | I18: 意大利张总单导 | J18: 4560 | K18: 2/27 9 3/1 29 未结算 38*120=4560 | L18: 0.56041667 | M18: 印度003对接—胖鱼 | N18: 35420 | P18: 0.64027778 | S18: =SUMIF(M:M,"哪吒-FB企业海外户",N:N) -> 1734 | T18: 哪吒-FB企业海外户
C19: 72805 | G19: 13 | H19: 45718 | M19: 意大利打群-fa | N19: 6380 | P19: 0.79583333 | S19: =SUMIF(M:M,"海总-全球户",N:N) -> 270 | T19: 海总-全球户
C20: 收入 | G20: 14 | H20: 45718 | M20: 后勤支出 | N20: 49061.38 | O20: 分红B哥2月分红，220,136.40*0.45= 99061.38 | P20: 0.85138889 | S20: =SUMIF(M:M,"Chris Ryan MYM美金户&麦芽-西柚",N:N) -> 100 | T20: Chris Ryan MYM美金户&麦芽-西柚
C21: =SUMIFS(J:J,H:H,">="&$C$17,H:H,"<="&$C$19) -> 1450200.2 | G21: 15 | H21: 45718 | M21: 启航广告费 | N21: 4767.68 | O21: 4000*1.18/0.99=4767.68 | P21: 0.89652778 | S21: =SUMIF(M:M,"海总-越南电信户",N:N) -> 200 | T21: 海总-越南电信户
C22: 支出 | G22: 16 | H22: 45719 | M22: 印度003对接—胖鱼 | N22: 63802 | P22: 0.53333333 | S22: =SUMIF(M:M,"济宁韦宁&香港有意思",N:N) -> 480 | T22: 济宁韦宁&香港有意思
C23: =SUMIFS(N:N,H:H,">="&$C$17,H:H,"<="&$C$19) -> 1126835.1 | G23: 17 | H23: 45719 | M23: 印度驻场-lala(郑总） | N23: 1978 | P23: 0.56875 | S23: =SUMIF(M:M,"凤凰渠道2-泰华",N:N) -> 680 | T23: 凤凰渠道2-泰华
C24: 结余 | G24: 18 | H24: 45719 | I24: 意大利第4梯队（蟑螂哥） | J24: 1680 | K24: 3月2日蟑螂哥 867群 有效3，3*120=360 397群 有效11，11*120=1320 合计 360+1320=1680 | L24: 0.60347222 | S24: =SUMIF(M:M,"海总-黑泽-欧洲户对接",N:N) -> 90 | T24: 海总-黑泽-欧洲户对接
C25: =C21-C23 -> 323365.14 | G25: 19 | H25: 45719 | I25: 印度FB天叶（2/24） | J25: 100 | L25: 0.60486111 | S25: =SUMIF(M:M,"技术学习费",N:N) -> 1288 | T25: 技术学习费
G26: 20 | H26: 45719 | I26: 印度FB天叶（2/24） | J26: 49900 | L26: 0.60902778 | S26: =SUMIF(M:M,"印度FB天叶（2/24）",N:N) -> 26976 | T26: 项目退款：印度FB天叶（2/24）
G27: 21 | H27: 45719 | I27: Y-5208 FB欧/美户 | J27: 485.33 | L27: 0.66736111 | M27: 印度003对接—胖鱼 | N27: 11500 | P27: 0.72986111 | S27: =SUMIF(M:M,"凯旋城7期退款",N:N) -> 15644 | T27: 项目退款：凯旋城7期退款
G28: 22 | H28: 45719 | M28: 启航广告费 | N28: 4116.16 | O28: 500*1.07/0.99+3000*1.18/0.99=4116.16 | P28: 0.73402778 | S28: =SUMIF(M:M,"渠道F 英文J",N:N) -> 2400 | T28: 项目退款：渠道F 英文J
G29: 23 | H29: 45719 | I29: 印度（10）金山 | J29: 100 | L29: 0.81458333 | S29: =SUMIF(M:M,"印度003对接—胖鱼",N:N) -> 346035 | T29: 印度003对接—胖鱼
G30: 24 | H30: 45719 | I30: 印度（10）金山 | J30: 99900 | L30: 0.81597222 | M30: 后勤支出 | N30: 99061.38 | O30: 分红张总2月分红，220,136.40*0.45= 99061.38 | P30: 0.94305556 | S30: =SUMIF(M:M,"印度驻场-lala(郑总）",N:N) -> 89240 | T30: 印度驻场-lala(郑总）
G31: 25 | H31: 45720 | M31: 广告配套 | N31: 900 | O31: 机器人防护 | P31: 0.50138889 | S31: =SUMIF(M:M,"印度FB——哈密瓜",N:N) -> 38295 | T31: 印度FB——哈密瓜
G32: 26 | H32: 45720 | M32: 后勤支出 | N32: 22013.64 | O32: 分红刘辉2月分红，220,136.40*10%=22013.64 | P32: 0.50625 | S32: =SUMIF(M:M,"马来打群-fa",N:N) -> 1390 | T32: 马来打群-fa
G33: 27 | H33: 45720 | I33: 意大利张总单导 | J33: 720 | L33: 0.52222222 | M33: 印度003对接—胖鱼 | N33: 37467 | P33: 0.55763889 | S33: =SUMIF(M:M,"德国打群-fa",N:N) -> 11080 | T33: 德国打群-fa
G34: 28 | H34: 45720 | M34: 海总-德国🇩🇪粉 | N34: 10 | P34: 0.67986111 | S34: =SUMIF(M:M,"海总-德国🇩🇪粉",N:N) -> 40300 | T34: 海总-德国🇩🇪粉
G35: 29 | H35: 45720 | M35: 海总-德国🇩🇪粉 | N35: =5000-N34 -> 4990 | P35: 0.68194444 | S35: =SUMIF(M:M,"意大利打群-fa",N:N) -> 6380 | T35: 意大利打群-fa
G36: 30 | H36: 45720 | M36: CH加白户14➕1 | N36: 550.45 | O36: 500*1.09*1.01=550.45 | P36: 0.83958333 | S36: =SUMIF(M:M,"浩天 意大利对接群",N:N) -> 11700 | T36: 浩天 意大利对接群
G37: 31 | H37: 45720 | M37: CH加白户14➕1 | N37: 550.45 | O37: 500*1.09*1.01=550.45 | P37: 0.94791667 | S37: 往上支出-------------------分割线-------------------往下收入
G38: 32 | H38: 45721 | M38: 印度003对接—胖鱼 | N38: 16836 | P38: 0.56527778 | S38: =SUM(S4:S36) -> 1126835.1
G39: 33 | H39: 45721 | M39: 后勤支出 | N39: 6058.85 | O39: 发工资 | P39: 0.66388889
G40: 34 | H40: 45721 | M40: 后勤支出 | N40: 3735.21 | O40: 发工资 | P40: 0.625 | S40: =SUMIF(I:I,"浩天 意大利对接群",J:J) -> 4900 | T40: 代投退款：浩天 意大利对接群
G41: 35 | H41: 45721 | M41: 后勤支出 | N41: 3885.73 | O41: 发工资 | P41: 0.62638889 | S41: =SUMIF(I:I,"印度006对接—henry",J:J) -> 4466 | T41: 代投退款：印度006对接—henry
G42: 36 | H42: 45721 | M42: 后勤支出 | N42: 864.89 | O42: 发工资 | P42: 0.62777778 | S42: =SUMIF(I:I,"海总-德国🇩🇪粉",J:J) -> 3400 | T42: 代投退款：海总-德国🇩🇪粉
G43: 37 | H43: 45721 | M43: 后勤支出 | N43: 3078.83 | O43: 发工资 | P43: 0.62847222 | S43: =SUMIF(I:I,"海总-越南电信户",J:J) -> 200 | T43: 代投退款：海总-越南电信户
G44: 38 | H44: 45721 | M44: 后勤支出 | N44: 560 | O44: 发工资 | P44: 0.63055556 | S44: =SUMIF(I:I,"十月二不限",J:J) -> 127 | T44: 户商退款：十月二不限
G45: 39 | H45: 45721 | M45: 后勤支出 | N45: 3331.29 | O45: 发工资 | P45: 0.63125 | S45: =SUMIF(I:I,"凤凰&洛阳",J:J) -> 31733.7 | T45: 户商退款：凤凰&洛阳
G46: 40 | H46: 45721 | M46: 后勤支出 | N46: 2834.91 | O46: 发工资 | P46: 0.63263889 | S46: =SUMIF(I:I,"海总-全球户",J:J) -> 341.74 | T46: 户商退款：海总-全球户
G47: 41 | H47: 45721 | M47: 后勤支出 | N47: 1735.28 | O47: 发工资 | P47: 0.63333333 | S47: =SUMIF(I:I,"印度企业户 欧洲美金户下户",J:J) -> 1527.85 | T47: 户商退款：印度企业户 欧洲美金户下户
G48: 42 | H48: 45721 | M48: 后勤支出 | N48: 500.69 | O48: 发工资 | P48: 0.63472222 | S48: =SUMIF(I:I,"CH加白户14➕1",J:J) -> 7757.94 | T48: 户商退款：CH加白户14➕1
G49: 43 | H49: 45721 | M49: 后勤支出 | N49: 5694.4444 | O49: 发工资 | P49: 0.63680556 | S49: =SUMIF(I:I,"Y-5208 FB欧/美户",J:J) -> 485.33 | T49: 户商退款：Y-5208 FB欧/美户
G50: 44 | H50: 45721 | M50: 印度企业户 欧洲美金户下户 | N50: 1130 | O50: 1000*1.13=1130U | P50: 0.63888889
G51: 45 | H51: 45721 | M51: 十月二不限——（泰华） | N51: 300 | P51: 0.65277778
G52: 46 | H52: 45722 | I52: 意大利张总单导 | J52: 1800 | K52: 3/4 有效17-4=13 13*120=1560 3/5 有效2 2*120=240 | L52: 0.4875 | S52: =SUMIF(I:I,"意大利张总单导",J:J) -> 10920 | T52: 意大利张总单导
G53: 47 | H53: 45722 | I53: 德国股票粉二组【张小强】 | J53: 9450 | K53: G3群有效33 33*135=4455 B4群有效37 37*135=4995 合计 4455+4995=9450 | L53: 0.59236111 | M53: 海总-德国🇩🇪粉 | N53: 10000 | P53: 0.60138889 | S53: =SUMIF(I:I,"巴西测试粉",J:J) -> 1657.06 | T53: 巴西测试粉
G54: 48 | H54: 45722 | M54: 广告配套 | N54: 270 | O54: 30个IP续费 | P54: 0.60347222 | S54: =SUMIF(I:I,"印度2期",J:J) -> 108640.8 | T54: 印度2期2/7开始
G55: 49 | H55: 45722 | I55: CH加白户14➕1 | J55: 992.31 | K55: 退款 | L55: 0.64444444 | S55: =SUMIF(I:I,"印度（10）金山",J:J) -> 225948 | T55: 印度（10）金山2/22
G56: 50 | H56: 45722 | I56: 印度企业户 欧洲美金户下户 | J56: 1130 | K56: 退款 | L56: 0.68680556 | S56: =SUMIF(I:I,"印度FB天叶（2/24）",J:J) -> 50000 | T56: 印度FB天叶（2/24） | U56: 其中已退款$26,976
G57: 51 | H57: 45722 | I57: 印度（10）金山 | J57: 48 | L57: 0.73819444 | M57: CH加白户14➕1 | N57: 1191 | O57: 80开户费 1000*1.1*1.01=1111➕80=1191 | P57: 0.74027778 | S57: =SUMIF(I:I,"意大利第4梯队（蟑螂哥）",J:J) -> 1680 | T57: 意大利第4梯队（蟑螂哥）
G58: 52 | H58: 45722 | I58: 印度（10）金山 | J58: 25900 | L58: 0.80347222 | M58: 启航广告费 | N58: 5626.26 | O58: 5000+626.26=5626.26 | P58: 0.89930556 | S58: =SUMIF(I:I,"德国股票粉二组【张小强】",J:J) -> 62775 | T58: 德国股票粉二组【张小强】
G59: 53 | H59: 45722 | M59: 印度驻场-lala(郑总） | N59: 2484 | P59: 0.92569444 | S59: =SUMIF(I:I,"印度3期",J:J) -> 50000 | T59: 印度3期
G60: 54 | H60: 45723 | M60: 印度003对接—胖鱼 | N60: 2185 | P60: 0.52013889 | S60: =SUMIF(I:I,"印度（10）金山3/17开始",J:J) -> 277200 | T60: 印度（10）金山3/17开始
G61: 55 | H61: 45723 | M61: 印度企业户 欧洲美金户下户 | N61: 11100 | O61: 10000*1.1*1.01=11100 | P61: 0.66041667 | S61: =SUMIF(I:I,"韩国刷单粉对接",J:J) -> 2138.39 | T61: 韩国刷单粉对接
G62: 56 | H62: 45723 | I62: 海总-全球户 | J62: 341.74 | L62: 0.79166667 | S62: =SUMIF(I:I,"渠道F 英文J",J:J) -> 7500 | T62: 渠道F 英文J | U62: 马来
G63: 57 | H63: 45723 | I63: 德国股票粉二组【张小强】 | J63: 11610 | K63: 3/6 F2 有效31 D2 有效19 3/7 Q1有效36 合计 31+19+36=86*135=11610 | L63: 0.80347222 | S63: =SUMIF(I:I,"（蟑螂哥）英国结算群",J:J) -> 415 | T63: （蟑螂哥）英国结算群
G64: 58 | H64: 45724 | I64: CH加白户14➕1 | J64: 1918.63 | K64: 退款 | L64: 0.068055556 | S64: =SUMIF(I:I,"印度L2期-强森",J:J) -> 100000 | T64: 印度L2期-强森
G65: 59 | H65: 45724 | I65: 德国股票粉二组【张小强】 | J65: 8100 | K65: 3/7 c2群 有效37 3/7 A5群 有效23 合计 （23+37）*135=8100 | L65: 0.51111111 | M65: 德国打群-fa | N65: 4080 | P65: 0.55902778 | S65: =SUMIF(I:I,"意大利二期",J:J) -> 50000 | T65: 意大利二期
G66: 60 | H66: 45724 | M66: 印度003对接—胖鱼 | N66: 2346 | P66: 0.575 | S66: =SUMIF(I:I,"印度14期-么么",J:J) -> 70000 | T66: 印度14期-么么
G67: 61 | H67: 45724 | M67: 深圳芳林子@SHEN 户 | N67: 3840.1 | O67: 4000-543.56=3456.44*1.1*1.01=3840.1 | P67: 0.59861111 | S67: =SUMIF(I:I,"印度4期-啊光",J:J) -> 150000 | T67: 印度4期-啊光 | U67: =S67+'2025年4月收支财务报表'!S49 -> 250000
G68: 62 | H68: 45724 | M68: 深圳芳林子@SHEN 户 | N68: 4444 | O68: 4000*1.1*1.01=4444 | P68: 0.625 | S68: =SUMIF(I:I,"渠道B 德国A",J:J) -> 6250 | T68: 渠道B 德国A
G69: 63 | H69: 45724 | M69: 印度企业户 欧洲美金户下户 | N69: 3330 | O69: 3000*1.11=3330U | P69: 0.62638889
G70: 64 | H70: 45724 | M70: 广告配套 | N70: 20 | O70: 5个BM | P70: 0.69722222 | S70: =J7 -> 220136.4 | T70: 2月结余
G71: 65 | H71: 45724 | M71: 印度企业户 欧洲美金户下户 | N71: 354 | O71: 100*3*1.08+30=354U | P71: 0.70902778 | S71: =SUM(S40:S70) -> 1450200.2
G72: 66 | H72: 45724 | M72: 广告配套 | N72: 207.35 | O72: ¥300*5=¥1500（207.35U实时汇率） | P72: 0.8375
G73: 67 | H73: 45724 | M73: 深圳芳林子@SHEN 户 | N73: 1161.5 | O73: 1000*1.15*1.01=1161.5 | P73: 0.73541667
G74: 68 | H74: 45725 | M74: 印度企业户 欧洲美金户下户 | N74: 100 | O74: 开户费 | P74: 0.78402778
G75: 69 | H75: 45725 | M75: 广告配套 | N75: 15 | O75: 主页3*15+百粉2*30=105 15U | P75: 0.87430556
G76: 70 | H76: 45725 | I76: 印度企业户 欧洲美金户下户 | J76: 100 | L76: 0.92777778
G77: 71 | H77: 45726 | M77: 印度FB——哈密瓜 | N77: 10 | P77: 0.47222222
G78: 72 | H78: 45726 | M78: 印度FB——哈密瓜 | N78: =3450-N77 -> 3440 | P78: 0.47291667
G79: 73 | H79: 45726 | M79: 深圳芳林子@SHEN 户 | N79: 4393.5 | O79: 5000*1.1*1.01=5555，5555-1161.5=4393.5 | P79: 0.57916667
G80: 74 | H80: 45726 | M80: 印度FB——哈密瓜 | N80: =3450 -> 3450 | P80: 0.62361111
G81: 75 | H81: 45726 | M81: 海总- BM户对接 | N81: 100 | O81: 开户费 | P81: 0.65902778
G82: 76 | H82: 45726 | M82: 广告配套 | N82: 5 | O82: 申诉个号1个 | P82: 0.69375
G83: 77 | H83: 45726 | M83: 海总-德国🇩🇪粉 | N83: 10600 | P83: 0.73888889
G84: 78 | H84: 45726 | M84: 印度FB天叶（2/24） | N84: 10 | O84: 退款 | P84: 0.76597222
G85: 79 | H85: 45726 | M85: 印度FB天叶（2/24） | N85: =26976-N84 -> 26966 | O85: 退款 | P85: 0.76736111
G86: 80 | H86: 45726 | M86: 印度企业户 欧洲美金户下户 | N86: 150 | O86: 开户费 | P86: 0.78333333
G87: 81 | H87: 45726 | M87: 广告配套 | N87: 265 | O87: 防护升级套餐 | P87: 0.94583333
G88: 82 | H88: 45726 | M88: 深圳芳林子@SHEN 户 | N88: 1742.25 | O88: 1500*1.15*1.01=1742.25 | P88: 0.98888889
G89: 83 | H89: 45726 | M89: 广告配套 | N89: 24 | O89: 主页1*15+百粉5*30=165 24U | P89: 0.99166667
G90: 84 | H90: 45727 | M90: 印度FB——哈密瓜 | N90: 3496 | P90: 0.50763889
G91: 85 | H91: 45727 | M91: 德国打群-fa | N91: 7000 | P91: 0.57222222
G92: 86 | H92: 45727 | I92: 德国股票粉二组【张小强】 | J92: 3780 | K92: 3月10-11日 德国股票粉二组【张小强】 3/10 D3 有效7 3/11 B6群 有效13 T2群 有效1 X3群 有效7 合计 （7+13+1+7）*135=3780 | L92: 0.61527778
G93: 87 | H93: 45727 | I93: 印度006对接—henry | J93: 6 | K93: 退款 | L93: 0.62083333
G94: 88 | H94: 45727 | I94: 印度006对接—henry | J94: 4460 | K94: 退款 | L94: 0.63055556 | M94: 印度企业户 欧洲美金户下户 | N94: 1220 | O94: 40*2+500*1.14*2=1220U | P94: 0.63472222
G95: 89 | H95: 45728 | I95: 德国股票粉二组【张小强】 | J95: 9045 | K95: 3月12日 德国股票粉二组【张小强】 D4 32 K1 14 Q2 21 合计（32+14+21） *135=9045 | L95: 0.62986111 | M95: 技术学习费 | N95: 10 | O95: 向南 | P95: 0.76736111
G96: 90 | H96: 45728 | M96: 技术学习费 | N96: =1188-N95 -> 1178 | O96: 向南 | P96: 0.76944444
G97: 91 | H97: 45728 | I97: 印度3期 | J97: 50000 | L97: 0.77708333
G98: 92 | H98: 45729 | M98: 账单户充值 | N98: 201.37 | P98: 0.045833333
G99: 93 | H99: 45729 | M99: 海总-德国🇩🇪粉 | N99: 1700 | P99: 0.52152778
G100: 94 | H100: 45729 | M100: 广告配套 | N100: 20 | O100: 5个BM | P100: 0.58055556
G101: 95 | H101: 45729 | M101: 广告配套 | N101: 76 | O101: 账单户*2 | P101: 0.65972222
G102: 96 | H102: 45729 | M102: Y-5208 FB欧/美户 | N102: 545 | O102: 500*1.09=545 | P102: 0.68125
...

Sheet 2025年2月收支财务报表
C1: 2025年2月收支财务报表
C4: 财务统计 STATISTICS | G4: 2025年2月收支明细 DETAIL | S4: =SUMIF(M:M,"广告配套",N:N) -> 4318.23 | T4: U支出的广告配套（不含RMB支出）
G5: 序号 | H5: 日期 | I5: 收入 | M5: 支出
C6: 月份查询 | I6: 项目 | J6: 金额 | K6: 备注 | L6: 时间 | M6: 项目 | N6: 金额 | O6: 备注 | P6: 时间 | S6: =SUMIF(M:M,"后勤支出",N:N) -> 389212.24 | T6: 后勤支出
C7: 2月 | D7: ▼ | G7: 1 | H7: 45689 | I7: 2025.1结余 | J7: ='2025年1月收支财务报表'!C13 -> 324824.07 | M7: 凤凰&洛阳&白户14 | N7: 4600 | O7: 4000*1.15=4600 | P7: 0.51944444 | S7: =SUMIF(M:M,"凤凰&洛阳&白户14",N:N) -> 128630.34 | T7: 凤凰&洛阳&白户14
C8: 收入 | G8: 2 | H8: 45689 | I8: 意大利蟑螂哥2月 | J8: 10200 | K8: 1/30 258群 有效34 1/31 638群 有效31 328群 有效20，85*120=10200 | L8: 0.675 | M8: 印度006对接—henry | N8: 8800 | O8: 400*22=8800 | P8: 0.69583333 | S8: =SUMIF(M:M,"深圳芳林子@SHEN 户",N:N) -> 133660.51 | T8: 深圳芳林子@SHEN 户
C9: =C21 -> 1368722.6 | G9: 3 | H9: 45689 | M9: 凤凰&洛阳&白户14 | N9: 17050 | O9: 10000*1.13+5000*1.15=17050 | P9: 0.74027778 | S9: =SUMIF(M:M,"CH加白户14➕1",N:N) -> 4741.041 | T9: CH加白户14➕1
C10: 支出 | G10: 4 | H10: 45689 | M10: 意大利-（岳总） | N10: 19800 | O10: 尾款18×100=1800，预付3个群180×100=18000，一共19800 | P10: 0.76736111 | S10: =SUMIF(M:M,"Fb 白户-长夏",N:N) -> 709.94 | T10: Fb 白户
C11: =C23 -> 1148586.2 | G11: 5 | H11: 45689 | M11: 后勤支出 | N11: 46170.832 | O11: 分红B哥1月分红 | P11: 0.81597222 | S11: =SUMIF(M:M,"Y-5208 FB欧/美户-Ivan（HX）",N:N) -> 560 | T11: Y-5208 FB欧/美户
C12: 结余 | G12: 6 | H12: 45689 | M12: 凤凰&洛阳&白户14 | N12: 9080 | O12: 6000*1.13+2000*1.15=9080 | P12: 0.93888889 | S12: =SUMIF(M:M,"印度企业户 欧洲美金户下户",N:N) -> 54490 | T12: 印度企业户 欧洲美金户下户
C13: =C9-C11 -> 220136.4 | G13: 7 | H13: 45689 | M13: 深圳芳林子@SHEN 户 | N13: 1111 | O13: 1000*1.1*1.01=1111 | P13: 0.98263889 | S13: =SUMIF(M:M,"桃子熊充值",N:N) -> 201.2 | T13: 桃子熊充值
G14: 8 | H14: 45690 | I14: Alex 法国TMI户&11+1 麦芽-西柚 | J14: 500 | K14: 退款 | L14: 0.22916667 | M14: 深圳芳林子@SHEN 户 | N14: 2222 | O14: 2000*1.10*1.01=2222 | P14: 0.54444444 | S14: =SUMIF(M:M,"海总-全球户-Milana",N:N) -> 565.6 | T14: 海总-全球户
C15: 任意时段查询 | G15: 9 | H15: 45690 | M15: 印度006对接—henry | N15: 13200 | O15: 600*22=13200 | P15: 0.61944444 | S15: =SUMIF(M:M,"启航广告费",N:N) -> 9807.13 | T15: 启航广告费
C16: 起始日期： | G16: 10 | H16: 45690 | M16: 印度驻场-lala(郑总） | N16: 60881 | O16: 2647*23=60881 | P16: 0.66597222 | S16: =SUMIF(M:M,"十月二不限——（泰华）",N:N) -> 21 | T16: 十月二不限——（泰华）
C17: 45292 | G17: 11 | H17: 45690 | I17: 印度25期 | J17: 100000 | L17: 0.74236111 | M17: 西班牙70A-xingxing | N17: 10 | P17: 0.75833333 | S17: =SUMIF(M:M,"海总- BM户对接",N:N) -> 50 | T17: 海总- BM户对接
C18: 结束日期： | G18: 12 | H18: 45690 | I18: 印度9期 | J18: 100000 | L18: 0.76597222 | M18: 意大利打群-fa | N18: 18000 | O18: 200*90=18000 | P18: 0.82777778
C19: 72805 | G19: 13 | H19: 45690 | M19: 西班牙70A-xingxing | N19: =2100-N17 -> 2090 | O19: 30*70=2100 | P19: 0.85277778
C20: 收入 | G20: 14 | H20: 45690 | M20: 意大利-（岳总） | N20: 26500 | O20: 预付剩余180-25-70-60=25个，预付4个群240×100=24000，一共26500，剩余290个预付 | P20: 0.86944444
C21: =SUMIFS(J:J,H:H,">="&$C$17,H:H,"<="&$C$19) -> 1368722.6 | G21: 15 | H21: 45691 | M21: 凤凰&洛阳&白户14 | N21: 10210 | O21: 7000*1.13+2000*1.15=10210 | P21: 0.95
C22: 支出 | G22: 16 | H22: 45691 | I22: 意大利蟑螂哥2月 | J22: 9120 | K22: 2/2 A96 有效55-同行5-350 351（3）-异国1=46*0.85=39，2/2 867群 有效37，39+37=76*120=9120 | L22: 0.48402778 | M22: CH加白户14➕1 | N22: 1151.4 | O22: 1000*1.14*1.01=1151.4 | P22: 0.48333333
C23: =SUMIFS(N:N,H:H,">="&$C$17,H:H,"<="&$C$19) -> 1148586.2 | G23: 17 | H23: 45691 | M23: 印度006对接—henry | N23: 10 | O23: 小额确认新地址 | P23: 0.60069444
C24: 结余 | G24: 18 | H24: 45691 | M24: 印度006对接—henry | N24: =8800-N23 -> 8790 | O24: 400*22=8800 | P24: 0.61180556 | S24: =SUMIF(M:M,"印度006对接—henry",N:N) -> 71192 | T24: 印度006对接—henry
C25: =C21-C23 -> 220136.4 | G25: 19 | H25: 45691 | M25: 深圳芳林子@SHEN 户 | N25: 3392.76 | O25: 3000*1.10*1.01=3333 3333+59.76=3392.76 | P25: 0.62222222 | S25: =SUMIF(M:M,"印度驻场-lala(郑总）",N:N) -> 206172 | T25: 印度驻场-lala(郑总）
G26: 20 | H26: 45691 | I26: 意大利（2000）阿光 | J26: 50000 | L26: 0.69861111 | M26: 后勤支出 | N26: 100000 | O26: 分红B哥1月分红 | P26: 0.70277778 | S26: =SUMIF(M:M,"印度003对接—胖鱼",N:N) -> 45655 | T26: 印度003对接—胖鱼
G27: 21 | H27: 45691 | M27: 印度驻场-lala(郑总） | N27: 19550 | O27: 850*23=19550 | P27: 0.7375
G28: 22 | H28: 45691 | M28: 凤凰&洛阳&白户14 | N28: 10170 | O28: 9000＊1.13=10170 | P28: 0.96527778
G29: 23 | H29: 45692 | M29: 印度驻场-lala(郑总） | N29: 16813 | O29: 731*23=16813 | P29: 0.50416667 | S29: =SUMIF(M:M,"浩天 意大利对接群",N:N) -> 5000 | T29: 浩天 意大利对接群
G30: 24 | H30: 45692 | I30: 意大利第三梯队608（蟑螂哥） | J30: 1080 | K30: 120*9=1080 | L30: 0.62013889 | M30: 凤凰&洛阳&白户14 | N30: 8475 | O30: 7500*1.13=8475 | P30: 0.66736111 | S30: =SUMIF(M:M,"意大利🇮🇹——海月",N:N) -> 6100 | T30: 意大利🇮🇹——海月
G31: 25 | H31: 45692 | M31: 广告配套 | N31: 2000 | O31: 换TRX | P31: 0.67083333 | S31: =SUMIF(M:M,"意大利-（岳总）",N:N) -> 56300 | T31: 意大利-（岳总）
G32: 26 | H32: 45692 | M32: Fb 白户-长夏 | N32: 709.94 | O32: 110000-100645.4*1.1= -709.94 | P32: 0.90902778 | S32: =SUMIF(M:M,"意大利打群-fa",N:N) -> 27000 | T32: 意大利打群-fa
G33: 27 | H33: 45692 | M33: 凤凰&洛阳&白户14 | N33: 10170 | O33: 9000*1.13=10170，500备用金已减 | P33: 0.96527778 | S33: =SUMIF(M:M,"西班牙70A-xingxing",N:N) -> 2100 | T33: 西班牙70A-xingxing
G34: 28 | H34: 45693 | I34: （蟑螂哥）西班牙 | J34: 400 | K34: 2/4 渠道： 日期：2/4 粉类别：FB 有效粉：5 单价：80 金额：400 | L34: 0.3875 | S34: =SUMIF(M:M,"西班牙/春兰/70A",N:N) -> 2100 | T34: 西班牙/春兰/70A
G35: 29 | H35: 45693 | I35: 意大利第三梯队608（蟑螂哥） | J35: 360 | K35: 2/4 有效粉3，3*120=360 | L35: 0.39027778 | S35: 往上支出-------------------分割线-------------------往下收入
G36: 30 | H36: 45693 | I36: 印度9期 | J36: 100000 | L36: 0.40972222 | M36: 印度驻场-lala(郑总） | N36: 22701 | O36: 987*23=22701 | P36: 0.50694444 | S36: =SUM(S4:S34) -> 1148586.2
G37: 31 | H37: 45693 | M37: 深圳芳林子@SHEN 户 | N37: 21109 | O37: 19000*1.10*1.01=21109 | P37: 0.58333333
G38: 32 | H38: 45693 | M38: 后勤支出 | N38: 7593.9835 | O38: 工资发放 | P38: 0.67291667 | S38: =SUMIF(I:I,"Alex 法国TMI户&11+1 麦芽-西柚",J:J) -> 500 | T38: 渠道商退款：Alex 法国TMI户&11+1 麦芽-西柚
G39: 33 | H39: 45693 | M39: 后勤支出 | N39: 6843.1366 | O39: 工资发放 | P39: 0.67291667 | S39: =SUMIF(I:I,"桃子熊退款",J:J) -> 4135.41 | T39: 渠道商退款：桃子熊退款
G40: 34 | H40: 45693 | M40: 后勤支出 | N40: 3102.1439 | O40: 工资发放 | P40: 0.67361111 | S40: =SUMIF(I:I,"GD&shen 欧洲美金户 10%u1",J:J) -> 1170 | T40: GD&shen 欧洲美金户 10%u1
G41: 35 | H41: 45693 | M41: 后勤支出 | N41: 702 | O41: 工资发放 | P41: 0.67430556 | S41: =SUMIF(I:I,"GT&Shen 欧洲美金低消户 12%u1",J:J) -> 10062 | T41: GT&Shen 欧洲美金低消户 12%u1
G42: 36 | H42: 45693 | M42: 后勤支出 | N42: 3832.64 | O42: 工资发放 | P42: 0.675 | S42: =SUMIF(I:I,"GF&SHEN美国户 开10u 10%+u1",J:J) -> 15631 | T42: GF&SHEN美国户 开10u 10%+u1
G43: 37 | H43: 45693 | M43: 后勤支出 | N43: 718.43333 | O43: 工资发放 | P43: 0.675 | S43: =SUMIF(I:I,"开户美国三不限户-Daisy",J:J) -> 4068.69 | T43: 开户美国三不限户-Daisy
G44: 38 | H44: 45693 | M44: 后勤支出 | N44: 2852.6315 | O44: 工资发放 | P44: 0.67569444 | S44: =SUMIF(I:I,"CH加白户14➕1",J:J) -> 3978 | T44: CH加白户14➕1
G45: 39 | H45: 45693 | M45: 后勤支出 | N45: 1920.4 | O45: 工资发放 | P45: 0.67638889 | S45: =SUMIF(I:I,"GT (井号户）",J:J) -> 16816.46 | T45: GT (井号户）
G46: 40 | H46: 45693 | M46: 后勤支出 | N46: 2186.8 | O46: 工资发放 | P46: 0.67708333
G47: 41 | H47: 45693 | M47: 后勤支出 | N47: 6000 | O47: 工资发放 | P47: 0.67777778 | S47: =SUMIF(I:I,"意大利-（岳总）",J:J) -> 400 | T47: 代投退款：意大利-（岳总）
G48: 42 | H48: 45694 | M48: 印度驻场-lala(郑总） | N48: 26082 | O48: 1134*23=26082 | P48: 0.47083333 | S48: =SUMIF(I:I,"西班牙/春兰/70A",J:J) -> 1190 | T48: 代投退款：西班牙/春兰/70A
G49: 43 | H49: 45694 | M49: CH加白户14➕1 | N49: 650.541 | O49: 1000-435=565*1.14*1.01=650.541 | P49: 0.55 | S49: =SUMIF(I:I,"西班牙70A-xingxing",J:J) -> 1610 | T49: 代投退款：西班牙70A-xingxing
G50: 44 | H50: 45694 | M50: 广告配套 | N50: 900 | O50: 机器人防护1个月 | P50: 0.64027778 | S50: =J7 -> 324824.07 | T50: 1月结余
G51: 45 | H51: 45694 | M51: 广告配套 | N51: 5 | O51: 五星主页1个 | P51: 0.64513889
G52: 46 | H52: 45694 | M52: 印度006对接—henry | N52: 8800 | O52: 400*22=8800 | P52: 0.65208333
G53: 47 | H53: 45694 | M53: 后勤支出 | N53: =32482.407 -> 32482.407 | O53: 分红刘辉1月分红，10U小额确认、杜总3000 | P53: 0.73541667 | S53: =SUMIF(I:I,"意大利蟑螂哥2月",J:J) -> 19320 | T53: 意大利蟑螂哥2月 | U53: 暂停
G54: 48 | H54: 45694 | M54: 凤凰&洛阳&白户14 | N54: 10000 | O54: （9000- 116）*1.13=10038.92，先转1W | P54: 0.75833333 | S54: =SUMIF(I:I,"意大利（2000）阿光",J:J) -> 50000 | T54: 意大利（2000）阿光 | U54: 暂停 | V54: =S54+'2025年1月收支财务报表'!S67 -> 150000
G55: 49 | H55: 45694 | M55: 凤凰&洛阳&白户14 | N55: 5689 | O55: （7000-2000）*1.13+38.92=5688.92，实际转出是5689 | P55: 0.99930556 | S55: =SUMIF(I:I,"意大利第三梯队608（蟑螂哥）",J:J) -> 27480 | T55: 意大利第三梯队608（蟑螂哥）
G56: 50 | H56: 45695 | M56: 凤凰&洛阳&白户14 | N56: 4520 | O56: 4000*1.13=4520 | P56: 0.54861111
G57: 51 | H57: 45695 | I57: 印度2期 | J57: 100000 | L57: 0.62222222 | S57: =SUMIF(I:I,"（蟑螂哥）西班牙",J:J) -> 1600 | T57: （蟑螂哥）西班牙 | U57: 暂停
G58: 52 | H58: 45695 | I58: 印度25期 | J58: 4276 | K58: 印度1期总打款300,000-总有效10867*28=-4,276 | L58: 0.69444444
G59: 53 | H59: 45695 | I59: 印度9期 | J59: 100000 | L59: 0.78680556 | M59: 印度003对接—胖鱼 | N59: 4255 | O59: 185*23=4255u | P59: 0.79722222
G60: 54 | H60: 45695 | M60: 后勤支出 | N60: 18076 | O60: 购车款 | P60: 0.85416667 | S60: =SUMIF(I:I,"印度25期",J:J) -> 104276 | T60: 印度25期（印度1期）2/7结束 | U60: 暂停 | V60: =S60+'2025年1月收支财务报表'!S59 -> 304276
G61: 55 | H61: 45695 | M61: 凤凰&洛阳&白户14 | N61: 5085 | O61: 4500*1.13=5085 | P61: 0.96597222 | S61: =SUMIF(I:I,"印度9期",J:J) -> 362840 | T61: 印度9期 | U61: 暂停 | V61: =S61+'2025年1月收支财务报表'!S58 -> 462840
G62: 56 | H62: 45696 | M62: 印度驻场-lala(郑总） | N62: 26634 | O62: 1158*23=26634 | P62: 0.50625 | S62: =SUMIF(I:I,"印度2期",J:J) -> 200000 | T62: 印度2期2/7开始
G63: 57 | H63: 45696 | M63: 广告配套 | N63: 255 | O63: VPN续费（一个季度） | P63: 0.51597222 | S63: =SUMIF(I:I,"印度（10）金山",J:J) -> 100000 | T63: 印度（10）金山2/22
G64: 58 | H64: 45696 | M64: 广告配套 | N64: 466 | O64: 2个计数号+50个IP | P64: 0.62847222 | S64: =SUMIF(I:I,"意大利张总单导",J:J) -> 8760 | T64: 意大利张总单导
G65: 59 | H65: 45696 | M65: 凤凰&洛阳&白户14 | N65: 6780 | O65: （7000-1000）*1.13=6780 | P65: 0.69861111 | S65: =SUMIF(I:I,"印度11期",J:J) -> 60004 | T65: 印度11期 | U65: 暂停
G66: 60 | H66: 45696 | M66: 深圳芳林子@SHEN 户 | N66: 3140.95 | O66: 2827.14*1.1*1.01=3140.95 | P66: 0.72708333 | S66: =SUMIF(I:I,"印度FB天叶（2/24）",J:J) -> 50000 | T66: 印度FB天叶（2/24）
G67: 61 | H67: 45696 | M67: Y-5208 FB欧/美户-Ivan（HX） | N67: 560 | O67: 500*1.12=560 | P67: 0.73611111 | S67: =SUMIF(I:I,"月度差值",J:J) -> 57 | T67: 月度差值
G68: 62 | H68: 45696 | M68: 印度003对接—胖鱼 | N68: 4094 | O68: 178*23=4094u | P68: 0.78819444
G69: 63 | H69: 45696 | M69: 凤凰&洛阳&白户14 | N69: 6780 | O69: 6000＊1.13=6780 | P69: 0.94444444
G70: 64 | H70: 45696 | I70: 西班牙70A-xingxing | J70: 1610 | K70: 30-7=23 23x70=1610 | L70: 0.96319444 | M70: 凤凰&洛阳&白户14 | N70: 5085 | O70: 4500*1.13=5085 | P70: 0.99930556
G71: 65 | H71: 45697 | M71: 西班牙/春兰/70A | N71: 10 | P71: 0.50347222
G72: 66 | H72: 45697 | M72: 西班牙/春兰/70A | N72: =2100-N71 -> 2090 | O72: 30*70=2100 | P72: 0.50486111 | S72: =SUM(S38:S71) -> 1368722.6
G73: 67 | H73: 45697 | M73: 印度003对接—胖鱼 | N73: 12926 | O73: 562*23=12926 | P73: 0.56527778
G74: 68 | H74: 45697 | M74: 深圳芳林子@SHEN 户 | N74: 1111 | O74: 1000*1.1*1.01=1111 | P74: 0.58472222
G75: 69 | H75: 45697 | M75: 凤凰&洛阳&白户14 | N75: 3955 | O75: 3500＊1.13=3955 | P75: 0.64305556
G76: 70 | H76: 45697 | M76: 印度驻场-lala(郑总） | N76: 25093 | O76: 1091*23=25093 | P76: 0.70833333
G77: 71 | H77: 45698 | M77: 印度006对接—henry | N77: 5192 | O77: 236*22=5192 | P77: 0.52361111
G78: 72 | H78: 45698 | M78: 广告配套 | N78: 5 | O78: 个号申诉（超30天） | P78: 0.54930556
G79: 73 | H79: 45698 | M79: 后勤支出 | N79: 560 | O79: NN工资发放 | P79: 0.60694444
G80: 74 | H80: 45699 | I80: 桃子熊退款 | J80: 4135.41 | K80: 退款 | L80: 0.042361111
G81: 75 | H81: 45699 | I81: （蟑螂哥）西班牙 | J81: 1120 | K81: 2/5 B55群 有效2未结算；2/9 未结算J09群 有效8，2/10 A55群 有效4未结算，2+8+4=14*80=1120 | L81: 0.64097222
G82: 76 | H82: 45699 | I82: 西班牙/春兰/70A | J82: 1190 | K82: (30-8-4-1)*70=1190 | L82: 0.81597222 | M82: 凤凰&洛阳&白户14 | N82: 10981.34 | O82: (10000-282)＊1.13=10981.34 | P82: 0.9125
G83: 77 | H83: 45699 | I83: 印度9期 | J83: 62840 | K83: 尾款 | L83: 0.93611111
G84: 78 | H84: 45700 | I84: （蟑螂哥）西班牙 | J84: 80 | K84: 2/11 €6 有效粉1 | L84: 0.15972222 | M84: 深圳芳林子@SHEN 户 | N84: 424.48 | O84: 2000-1617.93=382.07*1.10*1.01=424.48 | P84: 0.63055556
G85: 79 | H85: 45700 | M85: 深圳芳林子@SHEN 户 | N85: 1111 | O85: 1000*1.10*1.01=1111 | P85: 0.75833333
G86: 80 | H86: 45700 | M86: 深圳芳林子@SHEN 户 | N86: 2222 | O86: 2000*1.10*1.01=2222 | P86: 0.94791667
G87: 81 | H87: 45701 | M87: 深圳芳林子@SHEN 户 | N87: 3333 | O87: 3000*1.10*1.01=3333 | P87: 0.49166667
G88: 82 | H88: 45701 | M88: 广告配套 | N88: 205.23 | O88: 耐用号*5 | P88: 0.56180556
G89: 83 | H89: 45701 | M89: 深圳芳林子@SHEN 户 | N89: 3333 | O89: 3000*1.10*1.01=3333 | P89: 0.58402778
G90: 84 | H90: 45701 | M90: 深圳芳林子@SHEN 户 | N90: 3333 | O90: 3000*1.10*1.01=3333 | P90: 0.61388889
G91: 85 | H91: 45701 | M91: 深圳芳林子@SHEN 户 | N91: 3333 | O91: 3000*1.10*1.01=3333 | P91: 0.64305556
G92: 86 | H92: 45701 | M92: 印度企业户 欧洲美金户下户 | N92: 2320 | O92: （50+1000*1.11）*2=2320U | P92: 0.66527778
G93: 87 | H93: 45701 | M93: 海总-全球户-Milana | N93: 10 | P93: 0.73611111
G94: 88 | H94: 45701 | M94: 海总-全球户-Milana | N94: =565.6-N93 -> 555.6 | O94: 500×1.01×1.12=565.6 | P94: 0.74097222
G95: 89 | H95: 45701 | M95: 后勤支出 | N95: 10000 | O95: 换汇1W | P95: 0.79444444
G96: 90 | H96: 45701 | I96: CH加白户14➕1 | J96: 1386 | K96: CH户：450➕936=1386 | L96: 0.96319444
G97: 91 | H97: 45702 | M97: CH加白户14➕1 | N97: 2302.8 | O97: 2000*1.14*1.01=2302.8 | P97: 0.54375
G98: 92 | H98: 45702 | M98: 深圳芳林子@SHEN 户 | N98: 23331 | O98: 21000*1.1*1.01=23331 | P98: 0.59305556
G99: 93 | H99: 45702 | M99: 印度企业户 欧洲美金户下户 | N99: 2220 | O99: 2000×1.11=2220U | P99: 0.60069444
G100: 94 | H100: 45702 | M100: 后勤支出 | N100: 100000 | O100: 分红张总1月分红，46170.8315未出 | P100: 0.65486111
G101: 95 | H101: 45703 | M101: 印度企业户 欧洲美金户下户 | N101: 5550 | O101: 5000*1.11=5550U | P101: 0.54930556
G102: 96 | H102: 45703 | M102: 深圳芳林子@SHEN 户 | N102: 22220 | O102: 20,000*1.1*1.01=22,220 | P102: 0.59513889
...

Sheet 2025年1月收支财务报表
C1: 2025年1月收支财务报表
C4: 财务统计 STATISTICS | G4: 2025年1月月收支明细 DETAIL | S4: =SUMIF(M:M,"广告配套",N:N) -> 4127.07 | T4: U支出的广告配套（不含RMB支出）
G5: 序号 | H5: 日期 | I5: 收入 | M5: 支出
C6: 月份查询 | I6: 项目 | J6: 金额 | K6: 备注 | L6: 时间 | M6: 项目 | N6: 金额 | O6: 备注 | P6: 时间 | S6: =SUMIF(M:M,"后勤支出",N:N) -> 244956.44 | T6: 后勤支出
C7: 1月 | D7: ▼ | G7: 1 | H7: 45658 | I7: 2024.12结余 | J7: ='12月收支财务报表'!C13 -> 69219.832 | S7: =SUMIF(M:M,"Dong老虎",N:N) -> 6000 | T7: Dong老虎退款
C8: 收入 | G8: 2 | H8: 45658 | I8: Dong老虎 | J8: 6000 | L8: 0.93263889 | S8: =SUMIF(M:M,"深圳芳林子@SHEN 户",N:N) -> 335165.98 | T8: 深圳芳林子@SHEN 户
C9: =C21 -> 1854003.4 | G9: 3 | H9: 45659 | M9: 深圳芳林子@SHEN 户 | N9: 6666 | O9: 6000*1.10*1.01=6666 | P9: 0.55069444 | S9: =SUMIF(M:M,"GT&Shen (井号户）",N:N) -> 85880 | T9: GT&Shen (井号户）
C10: 支出 | G10: 4 | H10: 45659 | I10: 金融户印度-泰华 | J10: 187.2 | K10: 退款 | L10: 0.64930556 | M10: GT&Shen (井号户） | N10: 9040 | O10: 8000*1.13=9040 | P10: 0.72708333 | S10: =SUMIF(M:M,"凤凰&洛阳&白户14",N:N) -> 230196 | T10: 凤凰&洛阳&白户14
C11: =C23 -> 1529179.3 | G11: 5 | H11: 45659 | I11: 德国股粉对接群 | J11: 3915 | K11: 29*135=3915，12月的尾款 | M11: 深圳芳林子@SHEN 户 | N11: 1111 | O11: 1000*1.10*1.01=1111 | P11: 0.74027778 | S11: =SUMIF(M:M,"江小南＃字户10+1",N:N) -> 1110 | T11: 江小南＃字户10+1 | U11: 已退1000，手续费不退
C12: 结余 | G12: 6 | H12: 45659 | M12: 凤凰&洛阳&白户14 | N12: 9040 | O12: 8000*1.13=9040 | P12: 0.76041667 | S12: =SUMIF(M:M,"开户美国三不限户",N:N) -> 11550 | T12: 开户美国三不限户1月
C13: =C9-C11 -> 324824.07 | G13: 7 | H13: 45660 | M13: Dong老虎 | N13: 6000 | O13: 退款 | P13: 0.37083333 | S13: =SUMIF(M:M,"越南三不限-线条-泰华",N:N) -> 2180 | T13: 越南三不限-线条-泰华 | U13: 1/17已退1803
G14: 8 | H14: 45660 | M14: 深圳芳林子@SHEN 户 | N14: 14443 | O14: 13000*1.10*1.01=14443 | P14: 0.53958333 | S14: =SUMIF(M:M,"kk户（史塔克）913",N:N) -> 3510 | T14: kk户（史塔克）913
C15: 任意时段查询 | G15: 9 | H15: 45660 | I15: 印度23期 | J15: 100000 | L15: 0.66111111 | M15: GT&Shen (井号户） | N15: 11300 | O15: 10000×1.13=11300 | P15: 0.68125 | S15: =SUMIF(M:M,"🌹Y/量多多&YF FB合作群-（海登）",N:N) -> 1650 | T15: 🌹Y/量多多&YF FB合作群-（海登）
C16: 起始日期： | G16: 10 | H16: 45660 | M16: 江小南＃字户10+1 | N16: 10 | O16: 1000*1.11=1110 | P16: 0.74513889 | S16: =SUMIF(M:M,"Alex 法国TMI户&11+1 麦芽-西柚",N:N) -> 610.55 | T16: Alex 法国TMI户&11+1 麦芽-西柚
C17: 45292 | G17: 11 | H17: 45660 | M17: 江小南＃字户10+1 | N17: =1110-N16 -> 1100 | O17: 1000*1.11=1110 | P17: 0.75069444 | S17: =SUMIF(M:M,"印度企业户 欧洲美金户下户",N:N) -> 2320 | T17: 印度企业户 欧洲美金户下户
C18: 结束日期： | G18: 12 | H18: 45660 | I18: 十月二不限-泰华 | J18: 1460 | K18: 扣了2U的手续费 | L18: 0.75138889 | M18: 深圳芳林子@SHEN 户 | N18: 3333 | O18: 3000*1.1*1.01=3333 | P18: 0.82013889 | S18: =SUMIF(M:M,"CH加白户14➕1",N:N) -> 24418.293 | T18: CH加白户14➕1
C19: 72805 | G19: 13 | H19: 45661 | M19: GT&Shen (井号户） | N19: 20340 | O19: 18000×1.13=20340 | P19: 0.54652778 | S19: =SUMIF(M:M,"Fb 白户-长夏",N:N) -> 110000 | T19: Fb 白户-长夏
C20: 收入 | G20: 14 | H20: 45661 | I20: 江小南＃字户10+1 | J20: 1000 | L20: 0.68680556 | M20: 深圳芳林子@SHEN 户 | N20: 16665 | O20: 15000*1.10*1.01=16665 | P20: 0.54861111
C21: =SUMIFS(J:J,H:H,">="&$C$17,H:H,"<="&$C$19) -> 1854003.4 | G21: 15 | H21: 45662 | M21: 深圳芳林子@SHEN 户 | N21: 2777.5 | O21: 2500*1.111=2777.5 | P21: 0.45625
C22: 支出 | G22: 16 | H22: 45662 | M22: 深圳芳林子@SHEN 户 | N22: 11665.5 | O22: 10500*1.1*1.01=11665.5 | P22: 0.55833333
C23: =SUMIFS(N:N,H:H,">="&$C$17,H:H,"<="&$C$19) -> 1529179.3 | G23: 17 | H23: 45662 | M23: 深圳芳林子@SHEN 户 | N23: 11110 | O23: 10000*1.1*1.01=11110 | P23: 0.58680556
C24: 结余 | G24: 18 | H24: 45662 | I24: 印度22期 | J24: 100000 | L24: 0.69791667 | M24: 广告配套 | N24: 500 | O24: 矿工费 | P24: 0.7125
C25: =C21-C23 -> 324824.07 | G25: 19 | H25: 45662 | M25: 后勤支出 | N25: 6929.77 | O25: 工资发放 | P25: 0.70902778 | S25: =SUMIF(M:M,"印度006对接—henry",N:N) -> 101882 | T25: 印度006对接—henry | U25: 已结算1/10
G26: 20 | H26: 45662 | M26: 后勤支出 | N26: 2085.69 | O26: 工资发放 | P26: 0.71319444 | S26: =SUMIF(M:M,"印度003对接—胖鱼",N:N) -> 91448 | T26: 印度003对接—胖鱼 | U26: 已结算1/13
G27: 21 | H27: 45662 | M27: 后勤支出 | N27: 1415.19 | O27: 工资发放 | P27: 0.71458333 | S27: =SUMIF(M:M,"印度005对接_—李白",N:N) -> 4922 | T27: 印度005对接_—李白
G28: 22 | H28: 45662 | M28: 后勤支出 | N28: 2000 | O28: 工资发放 | P28: 0.71527778 | S28: =SUMIF(M:M,"意大利打群-fa",N:N) -> 93148 | T28: 意大利打群-fa | U28: 部分退款：84×90=7560 | V28: =S28-7560 -> 85588
G29: 23 | H29: 45662 | M29: 后勤支出 | N29: 4000 | O29: 工资发放 | P29: 0.71597222 | S29: =SUMIF(M:M,"印度打群-fa",N:N) -> 4400 | T29: 印度打群-fa
G30: 24 | H30: 45662 | M30: 后勤支出 | N30: 3575.71 | O30: 工资发放 | P30: 0.71666667 | S30: =SUMIF(M:M,"德国；意大利-（岳总）",N:N) -> 36780 | T30: 德国；意大利-（岳总）
G31: 25 | H31: 45662 | M31: 后勤支出 | N31: 1756.91 | O31: 工资发放 | P31: 0.71736111 | S31: =SUMIF(M:M,"德 LALA(郑总)",N:N) -> 3895 | T31: 德 LALA(郑总) | U31: 已结算1/14
G32: 26 | H32: 45662 | M32: 后勤支出 | N32: 3606.08 | O32: 工资发放 | P32: 0.71805556 | S32: =SUMIF(M:M,"印度驻场-lala(郑总）",N:N) -> 122590 | T32: 印度驻场-lala(郑总）
G33: 27 | H33: 45662 | M33: 后勤支出 | N33: 3249.4 | O33: 工资发放 | P33: 0.72013889 | S33: =SUMIF(M:M,"印度测试菜总",N:N) -> 1840 | T33: 印度测试菜总
G34: 28 | H34: 45662 | M34: 后勤支出 | N34: 1026.82 | O34: 工资发放 | P34: 0.72083333 | S34: =SUMIF(M:M,"印度002对接 - Yao",N:N) -> 4600 | T34: 印度002对接 - Yao
G35: 29 | H35: 45662 | M35: 广告配套 | N35: 900 | O35: 机器人斗篷防护 | P35: 0.80902778 | S35: 往上支出-------------------分割线-------------------往下收入
G36: 30 | H36: 45663 | M36: 后勤支出 | N36: 13621.53 | O36: 工资发放 | P36: 0.46527778
G37: 31 | H37: 45663 | M37: 广告配套 | N37: 2.16 | O37: 电报号1个 | P37: 0.52777778
G38: 32 | H38: 45663 | M38: 深圳芳林子@SHEN 户 | N38: 21109 | O38: 19000*1.10*1.01=21109 | P38: 0.54791667 | S38: =SUMIF(I:I,"印度002对接 - Yao",J:J) -> 4600 | T38: 代投退款：印度002对接 - Yao
G39: 33 | H39: 45663 | M39: GT&Shen (井号户） | N39: 22600 | O39: 20000*1.13=22600 | P39: 0.56666667 | S39: =SUMIF(I:I,"意大利打群-fa",J:J) -> 7560 | T39: 代投退款：意大利打群-fa | U39: 45672
G40: 34 | H40: 45663 | M40: 深圳芳林子@SHEN 户 | N40: 3333 | O40: 3000*1.10*1.01=3333 | P40: 0.56875 | S40: =SUMIF(I:I,"江小南＃字户10+1",J:J) -> 1000 | T40: 渠道商退款：江小南＃字户10+1
G41: 35 | H41: 45663 | M41: 广告配套 | N41: 19 | O41: 电报会员1个（6个月） | P41: 0.57013889 | S41: =SUMIF(I:I,"十月二不限-泰华",J:J) -> 1460 | T41: 十月二不限-泰华
G42: 36 | H42: 45663 | M42: 开户美国三不限户 | N42: 10 | O42: 小额确认 | P42: 0.78125 | S42: =SUMIF(I:I,"金融户印度-泰华",J:J) -> 234.01 | T42: 渠道商退款：金融户印度-泰华
G43: 37 | H43: 45663 | M43: 开户美国三不限户 | N43: =1575-N42 -> 1565 | O43: 500*3*1.05=1575 | P43: 0.78680556 | S43: =SUMIF(I:I,"越南三不限-线条-泰华",J:J) -> 1803 | T43: 渠道商退款：越南三不限-线条-泰华
G44: 38 | H44: 45663 | M44: 广告配套 | N44: 20 | O44: 五星主页4个 | P44: 0.94305556 | S44: =SUMIF(I:I,"kk户（史塔克）913",J:J) -> 2967 | T44: 渠道商退款：kk户（史塔克）913
G45: 39 | H45: 45664 | M45: 印度006对接—henry | N45: 10 | P45: 0.42638889 | S45: =SUMIF(I:I,"启航广告费",J:J) -> 25000 | T45: 渠道商退款：启航广告费
G46: 40 | H46: 45664 | M46: 印度006对接—henry | N46: =4400-N45 -> 4390 | O46: 200*22=4400 | P46: 0.42777778 | S46: =SUMIF(I:I,"🌹Y/量多多&YF FB合作群-（海登）",J:J) -> 1500 | T46: 渠道商退款：🌹Y/量多多&YF FB合作群-（海登）
G47: 41 | H47: 45664 | M47: 印度003对接—胖鱼 | N47: 10 | P47: 0.44513889 | S47: =SUMIF(I:I,"印度企业户 欧洲美金户下户",J:J) -> 1961 | T47: 渠道商退款：印度企业户 欧洲美金户下户
G48: 42 | H48: 45664 | M48: 印度003对接—胖鱼 | N48: =4600-N47 -> 4590 | O48: 200*23=4600u | P48: 0.44652778
G49: 43 | H49: 45664 | M49: 印度005对接_—李白 | N49: 10 | P49: 0.51597222
G50: 44 | H50: 45664 | M50: 印度005对接_—李白 | N50: =4600-N49 -> 4590 | O50: 200*23=4600 | P50: 0.52777778
G51: 45 | H51: 45664 | M51: 深圳芳林子@SHEN 户 | N51: 12785.54 | O51: （15000-3491.87）*1.111=12785.54 | P51: 0.54305556
G52: 46 | H52: 45664 | M52: 后勤支出 | N52: 10 | O52: 工资发放 | P52: 0.56666667
G53: 47 | H53: 45664 | M53: 后勤支出 | N53: =12285-N52 -> 12275 | O53: 工资发放 | P53: 0.57986111 | S53: =J7 -> 69219.832 | T53: 12月结余 | U53: 月底需要加上后勤的结余
G54: 48 | H54: 45664 | I54: 印度23期 | J54: 100000 | L54: 0.61736111 | M54: GT&Shen (井号户） | N54: 5650 | O54: 5000*1.13=5650 | P54: 0.63263889 | S54: =SUMIF(I:I,"12月后勤剩余",J:J) -> 2547.56 | T54: 12月后勤剩余
G55: 49 | H55: 45665 | M55: GT&Shen (井号户） | N55: 16950 | O55: 15000×1.13=16950 | P55: 0.4625 | S55: =SUMIF(I:I,"Dong老虎",J:J) -> 6000 | T55: Dong老虎 | U55: 已退6000
G56: 50 | H56: 45665 | M56: 深圳芳林子@SHEN 户 | N56: 21109 | O56: 19000*1.111=21109 | P56: 0.52569444 | S56: =SUMIF(I:I,"德国股粉对接群",J:J) -> 14715 | T56: 德国股粉对接群 | U56: 已结12/21的尾款$3,915
G57: 51 | H57: 45665 | M57: 深圳芳林子@SHEN 户 | N57: 4444 | O57: 4000*1.10*1.01=4444 | P57: 0.66180556
G58: 52 | H58: 45665 | M58: 深圳芳林子@SHEN 户 | N58: 4444 | O58: 4000*1.10*1.01=4444 | P58: 0.68194444 | S58: =SUMIF(I:I,"印度9期",J:J) -> 100000 | T58: 印度9期
G59: 53 | H59: 45665 | M59: 深圳芳林子@SHEN 户 | N59: 5555 | O59: 5000*1.10*1.01=5555 | P59: 0.75208333 | S59: =SUMIF(I:I,"印度25期",J:J) -> 200000 | T59: 印度25期（印度1期）
G60: 54 | H60: 45665 | M60: 广告配套 | N60: 84 | O60: 印度WS计数号1个，复接1次，2个菲律宾不留卡8U，5个美国IP（一个月） 合计：21+2+8U*2+5*9=84U | P60: 0.81180556 | S60: =SUMIF(I:I,"印度24期",J:J) -> 300000 | T60: 印度24期
G61: 55 | H61: 45665 | M61: 广告配套 | N61: 204.59 | O61: 5个不死号 | P61: 0.83958333 | S61: =SUMIF(I:I,"印度23期",J:J) -> 207756 | T61: 印度23期 | U61: 已结算1/10
G62: 56 | H62: 45666 | I62: 意大利蟑螂哥1月 | J62: 5520 | K62: 46*120=5520 | L62: 0.19513889 | M62: 深圳芳林子@SHEN 户 | N62: 22220 | O62: 20000*1.10*1.01=22220 | P62: 0.53125 | S62: =SUMIF(I:I,"印度23期补群",J:J) -> 116284 | T62: 印度23期补群1/16开始的
G63: 57 | H63: 45666 | M63: 意大利打群-fa | N63: =100*90 -> 9000 | P63: 0.64027778 | S63: =SUMIF(I:I,"印度22期",J:J) -> 100000 | T63: 印度22期 | U63: 已结算1/11
G64: 58 | H64: 45666 | M64: 印度003对接—胖鱼 | N64: 4600 | O64: 200*23=4600u | P64: 0.64930556 | S64: =SUMIF(I:I,"意大利蟑螂哥1月",J:J) -> 67800 | T64: 意大利蟑螂哥1月 | U64: =S64/120 -> 565
G65: 59 | H65: 45666 | M65: 印度005对接_—李白 | N65: 322 | O65: 14*23= 322 | P65: 0.74444444 | S65: =SUMIF(I:I,"印度期权 （粉）",J:J) -> 2000 | T65: 印度期权 （粉） | U65: 尾款已结算1/9
G66: 60 | H66: 45666 | M66: 广告配套 | N66: 165 | O66: 账单户*3 | P66: 0.81180556 | S66: =SUMIF(I:I,"L1印度",J:J) -> 150220 | T66: L1印度
G67: 61 | H67: 45666 | I67: 印度期权 （粉） | J67: 2000 | K67: 实付2000 | L67: 0.81319444 | M67: 深圳芳林子@SHEN 户 | N67: 3333 | O67: 3000*1.10*1.01=3333 | P67: 0.84444444 | S67: =SUMIF(I:I,"意大利（2000）阿光",J:J) -> 100000 | T67: 意大利（2000）阿光
G68: 62 | H68: 45666 | M68: 广告配套 | N68: 10 | O68: 个号短信验证 | P68: 0.93888889 | S68: =SUMIF(I:I,"K10期",J:J) -> 369376 | T68: K10期
G69: 63 | H69: 45667 | I69: 印度24期 | J69: 100000 | L69: 0.50208333 | M69: 印度006对接—henry | N69: 924 | O69: 42*22=924 | P69: 0.51597222 | S69: =SUM(S38:S68) -> 1854003.4
G70: 64 | H70: 45667 | M70: 深圳芳林子@SHEN 户 | N70: 13014.57 | O70: (3000+8000+6000+2000-7285.72)*1.10*1.01=13014.57 | P70: 0.54652778
G71: 65 | H71: 45667 | I71: 印度23期 | J71: 7756 | K71: 尾款 | L71: 0.65347222 | M71: 广告配套 | N71: 471 | O71: 印度WS计数号1个21U，50个美国IP（一个月） | P71: 0.76111111
G72: 66 | H72: 45667 | M72: 广告配套 | N72: 125 | O72: VPN续费（一个季度） | P72: 0.87152778
G73: 67 | H73: 45667 | M73: 广告配套 | N73: 20 | O73: 五星主页4个 | P73: 0.89375
G74: 68 | H74: 45667 | M74: 广告配套 | N74: 550 | O74: 账单户55U*10=550U | P74: 0.96111111
G75: 69 | H75: 45668 | M75: 开户美国三不限户 | N75: 2100 | O75: 2000*1.05=2100 | P75: 0.54236111
G76: 70 | H76: 45668 | M76: 深圳芳林子@SHEN 户 | N76: 12221 | O76: （6000+5000）*1.1*1.01=12221 | P76: 0.55625
G77: 71 | H77: 45668 | M77: 深圳芳林子@SHEN 户 | N77: 8888 | O77: （3000+5000）*1.1*1.01=8888 | P77: 0.67708333
G78: 72 | H78: 45668 | M78: 后勤支出 | N78: 16857 | O78: 分红LH，同一笔转款分2次转 | P78: 0.84444444
G79: 73 | H79: 45669 | M79: 深圳芳林子@SHEN 户 | N79: 21109 | O79: 19000*1.10*1.01=21109 | P79: 0.55694444
G80: 74 | H80: 45669 | M80: 深圳芳林子@SHEN 户 | N80: 4444 | O80: 4000*1.10*1.01=4444 | P80: 0.58402778
G81: 75 | H81: 45670 | I81: 印度24期 | J81: 100000 | L81: 0.45347222 | M81: 深圳芳林子@SHEN 户 | N81: 6666 | O81: 6000*1.1*1.01=6666 | P81: 0.52986111
G82: 76 | H82: 45670 | M82: 开户美国三不限户 | N82: 3150 | O82: 3000*1.05=3150 | P82: 0.56944444 | S82: 钱包手机改为+8区的时间
G83: 77 | H83: 45670 | M83: 开户美国三不限户 | N83: 1575 | O83: 500*3*1.05=1575 | P83: 0.63333333
G84: 78 | H84: 45670 | M84: 后勤支出 | N84: 20000 | O84: 分红B哥12月分红 | P84: 0.70486111
G85: 79 | H85: 45670 | M85: 印度003对接—胖鱼 | N85: 2806 | O85: 122*23=2806 | P85: 0.81666667
G86: 80 | H86: 45670 | M86: 越南三不限-线条-泰华 | N86: 10 | P86: 0.91736111
G87: 81 | H87: 45670 | M87: 越南三不限-线条-泰华 | N87: =2180-N86 -> 2170 | O87: 2000*1.09=2180 | P87: 0.92013889
G88: 82 | H88: 45671 | I88: 意大利蟑螂哥1月 | J88: 9360 | K88: 78*120=9360 | L88: 0.21736111 | M88: 意大利打群-fa | N88: 9000 | P88: 0.47083333
G89: 83 | H89: 45671 | M89: 深圳芳林子@SHEN 户 | N89: 7677.9 | O89: "12198.12/1.1=11089.2 还需要补款 18000-11089.2=6910.8 6910.8*1.1*1.01=7677.9" | P89: 0.575
G90: 84 | H90: 45671 | M90: 开户美国三不限户 | N90: 3150 | O90: 3000*1.05=3150 | P90: 0.60138889
G91: 85 | H91: 45671 | M91: kk户（史塔克）913 | N91: 10 | P91: 0.62361111
G92: 86 | H92: 45671 | I92: L1印度 | J92: 1000 | L92: 0.62291667
G93: 87 | H93: 45671 | I93: L1印度 | J93: 49000 | L93: 0.62638889 | M93: kk户（史塔克）913 | N93: =3510-N91 -> 3500 | O93: 500*1.07*6+50*6=3510 | P93: 0.63680556
G94: 88 | H94: 45671 | M94: 🌹Y/量多多&YF FB合作群-（海登） | N94: 10 | P94: 0.67638889
G95: 89 | H95: 45671 | M95: 🌹Y/量多多&YF FB合作群-（海登） | N95: =1650-N94 -> 1640 | O95: 500*3*1.10=1650 | P95: 0.68611111
G96: 90 | H96: 45671 | M96: 印度003对接—胖鱼 | N96: 4600 | O96: 200*23=4600u | P96: 0.74722222
G97: 91 | H97: 45671 | I97: 德国股粉对接群 | J97: 5940 | K97: 3+10+31=44 44*135=5940 | L97: 0.78055556 | M97: 德国；意大利-（岳总） | N97: 10 | P97: 0.79513889
G98: 92 | H98: 45671 | M98: 德国；意大利-（岳总） | N98: =4750-N97 -> 4740 | O98: 50*95= 4750 | P98: 0.79722222
G99: 93 | H99: 45671 | M99: Alex 法国TMI户&11+1 麦芽-西柚 | N99: 50 | O99: 开户费 | P99: 0.80972222
G100: 94 | H100: 45671 | M100: 德 LALA(郑总) | N100: 10 | P100: 0.84236111
G101: 95 | H101: 45671 | M101: 德 LALA(郑总) | N101: =3895-N100 -> 3885 | O101: 41*95=3,895 | P101: 0.84583333
G102: 96 | H102: 45671 | M102: 广告配套 | N102: 20 | O102: 5个BM | P102: 0.85694444
...

Sheet 12月收支财务报表
C1: 12月收支财务报表
C4: 财务统计 STATISTICS | G4: 12月收支明细 DETAIL | S4: =C13+2551.56 -> 71771.392
G5: 序号 | H5: 日期 | I5: 收入 | M5: 支出
C6: 月份查询 | I6: 项目 | J6: 金额 | K6: 备注 | L6: 时间 | M6: 项目 | N6: 金额 | O6: 备注 | P6: 时间
C7: 12月 | D7: ▼ | G7: 1 | H7: 45627 | I7: 11月剩余 | J7: ='11月收支财务报表'!C25 -> 287216.88 | M7: 账单户广告费 | N7: 3000.5 | P7: 0.72847222 | S7: =SUMIF(M:M,"广告配套",N:N) -> 2959 | T7: U支出的广告配套（不含RMB支出）
C8: 收入 | G8: 2 | H8: 45628 | I8: 土耳其张总股票粉 | J8: 19500 | K8: 阿金300*65=19500 | L8: 0.51875 | M8: 深圳芳林子@SHEN 户 | N8: 57772 | O8: (10000+15000+3000+5000+7000+3000+2000+7000)*1.10*1.01=57772 | P8: 0.53541667 | S8: =SUMIF(M:M,"印度测试",N:N) -> 23782 | T8: 印度测试
C9: =C21 -> 1475965.9 | G9: 3 | H9: 45628 | M9: 启航广告费 | N9: 15000 | P9: 0.53680556 | S9: =S7+S8 -> 26741
C10: 支出 | G10: 4 | H10: 45628 | M10: 深圳芳林子@SHEN 户 | N10: 856.29 | O10: 770.74*1.10*1.01=856.29，补1000的款Vys_FBCLN27 1047010629339687 | P10: 0.60347222
C11: =C23 -> 1406746.1 | G11: 5 | H11: 45628 | M11: GT欧洲 | N11: 11934.08 | O11: 12437-3863.36*0.7=€9,732.65/0.84*1.03=$11,934.08 | P11: 0.61388889
C12: 结余 | G12: 6 | H12: 45628 | M12: 土耳其介绍费 | N12: 6440 | P12: 0.67013889 | S12: =SUMIF(M:M,"土耳其介绍费",N:N) -> 6440 | T12: 土耳其介绍费
C13: =C9-C11 -> 69219.832 | G13: 7 | H13: 45629 | M13: 深圳芳林子@SHEN 户 | N13: 53328 | O13: 48000*1.10*1.01=53328 | P13: 0.55763889 | S13: =SUMIF(M:M,"退款土耳其张总股票粉",N:N) -> 5200 | T13: 退款土耳其张总股票粉12/8
G14: 8 | H14: 45629 | M14: 启航广告费 | N14: 15000 | P14: 0.63402778 | S14: =SUMIF(M:M,"张总垫付",N:N) -> 95000 | T14: 张总垫付
C15: 任意时段查询 | G15: 9 | H15: 45630 | I15: 土耳其张总股票粉 | J15: 19500 | K15: 阿金300*65=19500 | L15: 0.68402778 | M15: 启航广告费 | N15: 20000 | P15: 0.68680556 | S15: =SUMIF(M:M,"后勤转出",N:N) -> 271048.16 | T15: 后勤
C16: 起始日期： | G16: 10 | H16: 45631 | M16: 广告配套 | N16: 621 | P16: 0.40833333 | S16: =SUMIF(M:M,"账单户广告费",N:N) -> 8001.49 | T16: 账单户广告费
C17: 45292 | G17: 11 | H17: 45631 | M17: 后勤转出 | N17: 34100.71 | O17: 直接发到SZ财务的地址上 | P17: 0.51041667 | S17: =SUMIF(M:M,"深圳芳林子@SHEN 户",N:N) -> 263002.55 | T17: 深圳芳林子@SHEN 户
C18: 结束日期： | G18: 12 | H18: 45631 | M18: GT美国 | N18: 697.22 | O18: 628.13*1.11=697.22 | P18: 0.55555556 | S18: =SUMIF(M:M,"启航广告费",N:N) -> 257000 | T18: 启航广告费
C19: 72805 | G19: 13 | H19: 45631 | M19: GT美国 | N19: 5075.8 | O19: (1000+1000+500+1000+1000)*1.11+80*1.01=5075.8 | P19: 0.61180556 | S19: =SUMIF(M:M,"GT欧洲",N:N) -> 46570.71 | T19: GT欧洲
C20: 收入 | G20: 14 | H20: 45631 | I20: 印度20期 | J20: 21019 | L20: 14：44 | M20: 后勤转出 | N20: 80000 | P20: 0.61736111 | S20: =SUMIF(M:M,"GT美国",N:N) -> 104401.35 | T20: GT美国
C21: =SUMIFS(J:J,H:H,">="&$C$17,H:H,"<="&$C$19) -> 1475965.9 | G21: 15 | H21: 45631 | M21: GT美国 | N21: 1110 | O21: 1000*1.11=1110 | P21: 0.65069444 | S21: =SUMIF(M:M,"金融户印度-泰华",N:N) -> 3134.03 | T21: 金融户印度-泰华
C22: 支出 | G22: 16 | H22: 45631 | M22: 后勤转出 | N22: 13488.45 | P22: 0.72291667 | S22: =SUMIF(M:M,"GT&Shen (井号户）",N:N) -> 15920 | T22: GT&Shen (井号户）
C23: =SUMIFS(N:N,H:H,">="&$C$17,H:H,"<="&$C$19) -> 1406746.1 | G23: 17 | H23: 45631 | M23: GT美国 | N23: 1130 | O23: 1000*1.11=1110 1110+20=1130 | P23: 0.83541667 | S23: =SUMIF(M:M,"凤凰&洛阳&白户14",N:N) -> 302571.76 | T23: 凤凰&洛阳&白户14
C24: 结余 | G24: 18 | H24: 45631 | M24: 广告配套 | N24: 900 | O24: 斗篷防护 | P24: 0.55208333 | S24: =SUMIF(M:M,"FA-泰华印度1016（A-JIE）",N:N) -> 550 | T24: FA-泰华印度1016（A-JIE）
C25: =C21-C23 -> 69219.832 | G25: 19 | H25: 45632 | M25: GT美国 | N25: 1979.2 | O25: 4008-2547.24*0.7=1,783.06*1.11=1,979.2 | P25: 0.67916667 | S25: =SUMIF(M:M,"开户美国三不限户-Daisy",N:N) -> 1165 | T25: 开户美国三不限户-Daisy
G26: 20 | H26: 45632 | M26: 后勤转出 | N26: 8551 | P26: 19：02 | S26: =SUM(S12:S13) -> 11640
G27: 21 | H27: 45633 | M27: 账单户广告费 | N27: 2000.51 | P27: 0.60625 | S27: =SUM(S7:S25) -> 1433487.1
G28: 22 | H28: 45634 | I28: 印度22期 | J28: 100000 | L28: 0.64027778 | M28: 退款土耳其张总股票粉 | N28: 5200 | O28: 58500-820*65=5200 | P28: 0.80763889 | S28: =SUMIF(I:I,"开户美国三不限户",J:J) -> 998 | T28: 渠道商退款：开户美国三不限户
G29: 23 | H29: 45635 | I29: 天叶三期（张老板） | J29: 50000 | L29: 0.53680556 | M29: GT欧洲 | N29: 8371.63 | O29: 8000*1.03+107.35/0.84*1.03=8371.63 | P29: 0.5625 | S29: =SUMIF(I:I,"FA-泰华印度1016（A-JIE）",J:J) -> 550 | T29: 渠道商退款：FA-泰华印度1016（A-JIE）
G30: 24 | H30: 45635 | M30: GT美国 | N30: 1676.43 | O30: "5306.63*0.7-2224.94-3000=-1510.29 1510.29*1.11=1676.43" | P30: 0.62847222 | S30: =SUMIF(I:I,"土耳其张总股票粉",J:J)-S13 -> 33800 | T30: 土耳其张总股票粉（已减去退款的5200） | U30: =S30+'11月收支财务报表'!S37 -> 53300
G31: 25 | H31: 45635 | M31: GT美国 | N31: 17760.011 | O31: 待清5,306.63*0.7=3,714.64 ，19,714.65-3,714.64=16,000.01*1.11=17760.0111 | P31: 0.6375 | S31: =SUMIF(I:I,"印度20期",J:J) -> 21019 | T31: 印度20期11/16
G32: 26 | H32: 45635 | M32: 广告配套 | N32: 66 | O32: 5个WS计数号 | P32: 0.82222222 | S32: =SUMIF(I:I,"印度22期",J:J) -> 300000 | T32: 印度22期12/8
G33: 27 | H33: 45636 | M33: 账单户广告费 | N33: 3000.48 | P33: 0.51319444 | S33: =SUMIF(I:I,"天叶三期（张老板）",J:J) -> 200000 | T33: 天叶三期（张老板）12/9
G34: 28 | H34: 45636 | M34: GT欧洲 | N34: 5150 | O34: 5000*1.03=5150 | P34: 0.55694444 | S34: =SUMIF(I:I,"凯旋城印度8期",J:J) -> 17104 | T34: 凯旋城印度8期
G35: 29 | H35: 45636 | M35: 深圳芳林子@SHEN 户 | N35: 21124.23 | O35: Vys_FBCLN26系统备用金1986.29；总充值（10000+6000+5000-1986.29）*1.10*1.01=21124.23 | P35: 0.58125 | S35: =SUMIF(I:I,"德国股粉对接群",J:J) -> 8370 | T35: 德国股粉对接群 | U35: 1/2号结尾款
G36: 30 | H36: 45636 | M36: GT美国 | N36: 22783.57 | O36: "待清零是7412.72*0.7=5188.90 25714.64-5188.90=20525.74 需要打款20525.74*1.11=22783.57哈" | P36: 0.58541667 | S36: =SUMIF(I:I,"意大利蟑螂哥结算群",J:J) -> 1210 | T36: 意大利蟑螂哥结算群
G37: 31 | H37: 45636 | M37: 启航广告费 | N37: 15000 | P37: 0.59027778 | S37: =SUMIF(I:I,"印度10期孟德",J:J) -> 150498 | T37: 印度10期孟德 | U37: 5574*27=150498
G38: 32 | H38: 45636 | M38: GT欧洲 | N38: 1030 | O38: 1000*1.03=1030 | P38: 0.66666667 | S38: =SUMIF(I:I,"印度23期",J:J) -> 200000 | T38: 印度23期
G39: 33 | H39: 45636 | M39: GT美国 | N39: 5451.16 | O39: 待清零7771.66*0.7=5440.16 (7315.08+1500*2)-5440.16=4874.92 4874.92*1.11+40开户费=5451.1612 | P39: 0.67083333 | S39: =SUMIF(I:I,"老锅广告费垫付",J:J) -> 200000 | T39: 老锅广告费垫付
G40: 34 | H40: 45636 | M40: 广告配套 | N40: 200 | O40: 矿工费TRX | P40: 0.94236111 | S40: =SUMIF(I:I,"凯旋城7期",J:J) -> 50000 | T40: 凯旋城7期
G41: 35 | H41: 45637 | M41: 深圳芳林子@SHEN 户 | N41: 982.78 | O41: （2000-1115.41）*1.10*1.01=982.78 | P41: 0.54722222 | S41: =SUM(S28:S40) -> 1183549
G42: 36 | H42: 45637 | M42: 启航广告费 | N42: 15000 | P42: 0.51111111 | S42: =S41+J7+S13 -> 1475965.9 | T42: 包含退给土耳其张总股票粉的5200，还有11月的余款
G43: 37 | H43: 45637 | M43: GT欧洲 | N43: 1030 | O43: 1000*1.03=1030 | P43: 0.66180556
G44: 38 | H44: 45637 | M44: GT美国 | N44: 3330 | O44: 3000×1.11=3330 | P44: 0.675
G45: 39 | H45: 45637 | M45: 金融户印度-泰华 | N45: 974.03 | O45: 98.12-1000=-901.88 -901.88*1.08=-974.03 | P45: 0.76666667
G46: 40 | H46: 45637 | M46: 启航广告费 | N46: 15000 | P46: 0.81875
G47: 41 | H47: 45637 | I47: 凯旋城印度8期 | J47: 17104 | K47: 尾款 | L47: 0.96666667
G48: 42 | H48: 45638 | M48: GT欧洲 | N48: 3090 | O48: 3000*1.03=3090 | P48: 0.53402778
G49: 43 | H49: 45638 | M49: GT美国 | N49: 8615.53 | O49: 需要打款17633.59-14102.64*0.7=7761.74 7761.74*1.11=8615.53哈 | P49: 0.56458333
G50: 44 | H50: 45638 | M50: GT美国 | N50: 2220 | O50: 需要打款2000*1.11=2220哈 | P50: 0.62083333
G51: 45 | H51: 45638 | M51: GT美国 | N51: =7000*1.11 -> 7770 | O51: 需要打款7000*1.11=7770哈 | P51: 0.62916667
G52: 46 | H52: 45638 | I52: 天叶三期（张老板） | J52: 50000 | L52: 0.66666667 | M52: GT欧洲 | N52: 10300 | O52: 10000*1.03=10300 | P52: 0.69027778
G53: 47 | H53: 45638 | I53: 印度22期 | J53: 100000 | L53: 0.70208333 | M53: GT美国 | N53: 8880 | O53: 8000*1.11=8880 | P53: 0.69444444
G54: 48 | H54: 45638 | M54: GT欧洲 | N54: 1030 | O54: 1000*1.03=1030 | P54: 0.72291667
G55: 49 | H55: 45638 | M55: 启航广告费 | N55: 8000 | P55: 0.72708333
G56: 50 | H56: 45639 | M56: 金融户印度-泰华 | N56: 2160 | O56: -2000*1.08=-2160 | P56: 0.54444444
G57: 51 | H57: 45639 | M57: 启航广告费 | N57: 20000 | P57: 0.54722222
G58: 52 | H58: 45639 | M58: 深圳芳林子@SHEN 户 | N58: 8772.18 | O58: 10000-2104.25=7,895.75*1.1*1.01=8,772.18 | P58: 0.5625
G59: 53 | H59: 45639 | M59: GT欧洲 | N59: 1545 | O59: 1500*1.03=1545 | P59: 0.65833333
G60: 54 | H60: 45639 | M60: GT美国 | N60: 2047.43 | O60: "6208.15-6233.74*0.7=1844.53 1844.53*1.11=2047.43" | P60: 0.66180556
G61: 55 | H61: 45639 | I61: 德国股粉对接群 | J61: 2700 | K61: (3+3+2+12)*135=2700 | L61: 0.76597222
G62: 56 | H62: 45640 | M62: 启航广告费 | N62: 15000 | P62: 0.56944444
G63: 57 | H63: 45640 | I63: 天叶三期（张老板） | J63: 50000 | L63: 0.58125 | M63: 启航广告费 | N63: 20000 | P63: 0.78125
G64: 58 | H64: 45641 | M64: 启航广告费 | N64: 15000 | P64: 0.70972222
G65: 59 | H65: 45642 | M65: 启航广告费 | N65: 14000 | P65: 0.54652778
G66: 60 | H66: 45642 | I66: 天叶三期（张老板） | J66: 50000 | L66: 0.61875 | M66: 启航广告费 | N66: 20000 | P66: 0.62361111
G67: 61 | H67: 45642 | M67: GT美国 | N67: 2220 | O67: 2000*1.11=2220 | P67: 0.63194444
G68: 62 | H68: 45642 | I68: 印度22期 | J68: 100000 | L68: 0.64375
G69: 63 | H69: 45642 | I69: 德国股粉对接群 | J69: 5670 | K69: 截止12/15 未结算23+2+17=42 42*135=5670 | L69: 0.68888889 | M69: 后勤转出 | N69: 20000 | P69: 0.7875
G70: 64 | H70: 45643 | M70: 广告配套 | N70: 135 | O70: 账单户1套（售后一个户减¥120） | P70: 0.46180556
G71: 65 | H71: 45643 | M71: 启航广告费 | N71: 15000 | P71: 0.59305556
G72: 66 | H72: 45643 | M72: GT美国 | N72: 11655 | O72: （7000+3500）*1.11=11655 | P72: 0.59791667
G73: 67 | H73: 45644 | M73: 广告配套 | N73: 450 | O73: 50IP续费 | P73: 0.51666667
G74: 68 | H74: 45644 | M74: 启航广告费 | N74: 15000 | P74: 0.66805556
G75: 69 | H75: 45644 | M75: 深圳芳林子@SHEN 户 | N75: 3171.06 | O75: 2854.24*1.10*1.01=3171.06 | P75: 0.72986111
G76: 70 | H76: 45645 | I76: 意大利蟑螂哥结算群 | J76: 1210 | K76: 11*110=1210 | L76: 0.57291667 | M76: 印度测试 | N76: 10 | P76: 0.65208333
G77: 71 | H77: 45645 | M77: GT欧洲 | N77: 1030 | O77: 1000*1.03=1030 | P77: 0.65347222
G78: 72 | H78: 45645 | M78: 印度测试 | N78: 4590 | O78: 10+4590=4600 | P78: 0.65972222
G79: 73 | H79: 45645 | M79: 广告配套 | N79: 225 | O79: 圣盾防护续费（一个月） | P79: 0.56388889
G80: 74 | H80: 45646 | M80: GT欧洲 | N80: 2060 | O80: 2000*1.03=2060 | P80: 0.57638889
G81: 75 | H81: 45646 | M81: 深圳芳林子@SHEN 户 | N81: 12221 | O81: 11000*1.10*1.01=12221 | P81: 0.59236111
G82: 76 | H82: 45646 | M82: 启航广告费 | N82: 20000 | P82: 0.6
G83: 77 | H83: 45646 | M83: GT&Shen (井号户） | N83: 2240 | O83: 2000*1.14=2280，少转了40，下次补 | P83: 0.76666667
G84: 78 | H84: 45646 | M84: 后勤转出 | N84: 20000 | P84: 0.98125
G85: 79 | H85: 45647 | M85: 深圳芳林子@SHEN 户 | N85: 18884.11 | O85: 16997.4*1.1*1.01=18884.11 | P85: 0.54652778
G86: 80 | H86: 45647 | M86: 深圳芳林子@SHEN 户 | N86: 3333 | O86: 3000*1.1*1.01=3333 | P86: 0.63263889
G87: 81 | H87: 45648 | I87: 印度10期孟德 | J87: 498 | L87: 0.65208333
G88: 82 | H88: 45648 | I88: 印度10期孟德 | J88: 150000 | L88: 0.68055556
G89: 83 | H89: 45649 | M89: 张总垫付 | N89: 10 | P89: 0.45416667
G90: 84 | H90: 45649 | M90: 张总垫付 | N90: =95000-10 -> 94990 | P90: 0.45625
G91: 85 | H91: 45649 | M91: 深圳芳林子@SHEN 户 | N91: 24442 | O91: （8000+3000+3000+8000）*1.10*1.01=24442 | P91: 0.56458333
G92: 86 | H92: 45649 | I92: 印度23期 | J92: 100000 | L92: 0.58819444 | M92: 深圳芳林子@SHEN 户 | N92: 9275.19 | O92: 8348.51*1.1*1.01=9,275.19 | P92: 0.80555556
G93: 87 | H93: 45650 | M93: 印度测试 | N93: 4600 | O93: 200个 | P93: 0.44305556
G94: 88 | H94: 45650 | M94: 深圳芳林子@SHEN 户 | N94: 5555 | O94: 5000*1.10*1.01=5555 | P94: 0.57569444
G95: 89 | H95: 45650 | M95: 凤凰&洛阳&白户14 | N95: 2240 | O95: 2000*1.12=2240 | P95: 0.73125
G96: 90 | H96: 45650 | M96: FA-泰华印度1016（A-JIE） | N96: 550 | O96: 500*1.1=-550u | P96: 0.82777778
G97: 91 | H97: 45650 | M97: 凤凰&洛阳&白户14 | N97: 2811.76 | O97: (3000-489.5)*1.12=2811.76 | P97: 0.86527778
G98: 92 | H98: 45650 | M98: 凤凰&洛阳&白户14 | N98: 1680 | O98: 1500*1.12=1680 | P98: 0.88819444
G99: 93 | H99: 45650 | M99: 凤凰&洛阳&白户14 | N99: 2800 | O99: 500*5*1.12=2800 | P99: 0.92777778
G100: 94 | H100: 45651 | M100: 印度测试 | N100: 5543 | O100: 241*23=5543 | P100: 0.42083333
G101: 95 | H101: 45651 | M101: 深圳芳林子@SHEN 户 | N101: 8888 | O101: 8000*1.10*1.01=8888 | P101: 0.43333333
G102: 96 | H102: 45651 | M102: 凤凰&洛阳&白户14 | N102: 10080 | O102: 9000*1.12=10080 | P102: 0.47847222
...

Sheet 11月收支财务报表
C1: 11月收支财务报表
C4: 财务统计 STATISTICS | G4: 11月收支明细 DETAIL
G5: 序号 | H5: 日期 | I5: 收入 | M5: 支出
C6: 月份查询 | I6: 项目 | J6: 金额 | K6: 备注 | L6: 时间 | M6: 项目 | N6: 金额 | O6: 备注 | P6: 时间 | S6: =SUMIF(M:M,"广告配套",N:N) -> 3528.8858 | T6: 广告配套 | U6: 只有U的，需要加RMB的支出
C7: 11月 | D7: ▼ | G7: 1 | H7: 45597 | I7: 10月剩余 | J7: ='10月收支财务报表'!C13 -> 95595.759 | M7: 启航广告费 | N7: 20000 | P7: 0.41388889 | S7: =SUMIF(M:M,"Fb966半限户-啊噗",N:N) -> 1260 | T7: Fb966半限户-啊噗
C8: 收入 | G8: 2 | H8: 45597 | M8: Fb966半限户-啊噗 | N8: 210 | P8: 0.49305556 | S8: =SUMIF(M:M,"一拖九半限户",N:N) -> 1265 | T8: 一拖九半限户
C9: =C21 -> 1607693.1 | G9: 3 | H9: 45597 | M9: Fb966半限户-啊噗 | N9: 210 | P9: 0.54305556
C10: 支出 | G10: 4 | H10: 45597 | M10: 账单户广告费 | N10: 2000.62 | P10: 0.54305556
C11: =C23 -> 1320476.3 | G11: 5 | H11: 45597 | M11: 印度企业户100u➕14%扎克伯克 | N11: 1230 | O11: 1000×1.13+100=1230 | P11: 0.63125 | S11: =SUMIF(M:M,"印度手工粉测试LS",N:N) -> 8100 | T11: 印度手工粉测试LS | U11: 代投
C12: 结余 | G12: 6 | H12: 45597 | M12: 账单户广告费 | N12: 3000.01 | O12: 第1笔 | P12: 0.80138889 | S12: =SUMIF(M:M,"土耳其单导代投",N:N) -> 2756 | T12: 土耳其单导代投 | U12: 代投
C13: =C9-C11 -> 287216.88 | G13: 7 | H13: 45597 | M13: 账单户广告费 | N13: 3000.01 | O13: 第2笔 | P13: 0.80138889
G14: 8 | H14: 45597 | M14: 十月二不限-泰华 | N14: 3596 | P14: 0.92777778 | S14: =SUMIF(M:M,"账单户广告费",N:N) -> 40004.98 | T14: 账单户广告费
C15: 任意时段查询 | G15: 9 | H15: 45598 | M15: 启航广告费 | N15: 20000 | P15: 0.50416667 | S15: =SUMIF(M:M,"凤凰&洛阳11月",N:N) -> 340481.62 | T15: 凤凰&洛阳11月 | U15: =S15+41143.8 -> 381625.42
C16: 起始日期： | G16: 10 | H16: 45598 | M16: Fb966半限户-啊噗 | N16: 210 | P16: 0.59305556 | S16: =SUMIF(M:M,"启航广告费",N:N) -> 305000 | T16: 启航广告费
C17: 45292 | G17: 11 | H17: 45598 | I17: 土耳其/A李信 | J17: 32500 | K17: 500*65=32500 | L17: 0.6375 | M17: 十月二不限-泰华 | N17: 1700 | P17: 0.80069444 | S17: =SUMIF(M:M,"印度企业户100u➕14%扎克伯克",N:N) -> 2370 | T17: 印度企业户100u➕14%扎克伯克 | U17: =S17+'10月收支财务报表'!V63 -> 3626.986
C18: 结束日期： | G18: 12 | H18: 45598 | M18: 账单户广告费 | N18: 3000.83 | P18: 0.94375 | S18: =SUMIF(M:M,"十月二不限-泰华",N:N) -> 25592 | T18: 十月二不限-泰华
C19: 72805 | G19: 13 | H19: 45599 | M19: 启航广告费 | N19: 20000 | P19: 0.42777778 | S19: =SUMIF(M:M,"GT井号户",N:N) -> 22800 | T19: GT井号户
C20: 收入 | G20: 14 | H20: 45599 | M20: 十月二不限-泰华 | N20: 1730 | P20: 0.53472222 | S20: =SUMIF(M:M,"GT美国",N:N) -> 223906.94 | T20: GT美国
C21: =SUMIFS(J:J,H:H,">="&$C$17,H:H,"<="&$C$19) -> 1607693.1 | G21: 15 | H21: 45599 | M21: GT美国 | N21: 13334.43 | P21: 0.54861111 | S21: =SUMIF(M:M,"GT欧洲",N:N) -> 54636.06 | T21: GT欧洲
C22: 支出 | G22: 16 | H22: 45599 | M22: 账单户广告费 | N22: 3000.62 | P22: 0.57708333 | S22: =SUMIF(M:M,"GT台湾",N:N) -> 0 | T22: GT台湾
C23: =SUMIFS(N:N,H:H,">="&$C$17,H:H,"<="&$C$19) -> 1320476.3 | G23: 17 | H23: 45599 | M23: Fb966半限户-啊噗 | N23: 210 | P23: 0.57986111 | S23: =SUMIF(M:M,"金融户印度-泰华Jennie",N:N) -> 10875.27 | T23: 金融户印度-泰华Jennie
C24: 结余 | G24: 18 | H24: 45599 | M24: Fb966半限户-啊噗 | N24: 210 | P24: 0.71180556 | S24: =SUMIF(M:M,"深圳芳林子@SHEN 户",N:N) -> 147899.5 | T24: 深圳芳林子@SHEN 户
C25: =C21-C23 -> 287216.88 | G25: 19 | H25: 45599 | I25: 新印度5期 | J25: 100 | K25: 成成 | L25: 0.72013889
G26: 20 | H26: 45599 | I26: 新印度5期 | J26: 99900 | K26: 成成 | L26: 0.72569444 | M26: Fb966半限户-啊噗 | N26: 210 | P26: 0.74097222 | S26: =SUMIF(I:I,"济宁韦宁&香港有意思 二不限 3%",J:J) -> 3691.29 | T26: 退款（渠道商：济宁韦宁&香港有意思 二不限 3%
G27: 21 | H27: 45599 | M27: 后勤转入 | N27: 30000 | P27: 0.775 | S27: =SUMIF(I:I,"BH欧洲户-泰华-欧洲企业户-6+1",J:J) -> 995.35 | T27: 退款（渠道商：BH欧洲户-泰华-欧洲企业户-6+1
G28: 22 | H28: 45599 | M28: 账单户广告费 | N28: 5000.75 | P28: 0.77777778 | S28: =SUMIF(I:I,"欧洲三不限-泰华709-Sherry",J:J) -> 1266 | T28: 退款（渠道商：欧洲三不限-泰华709-Sherry
G29: 23 | H29: 45599 | I29: 调整金额 | J29: 6.9 | M29: GT美国 | N29: 2220 | O29: 2000*1.11=2220 | P29: 0.82152778 | S29: =SUMIF(I:I,"低消1万美金户",J:J) -> 3675 | T29: 退款（渠道商：低消1万美金户
G30: 24 | H30: 45599 | I30: 土耳其/A李信 | J30: 32500 | K30: 500*65=32500 | L30: 0.86319444 | M30: 账单户广告费 | N30: 5000.69 | P30: 0.87430556 | S30: =SUMIF(I:I,"印度企业户100u➕14%扎克伯克",J:J) -> 1831.59 | T30: 退款（渠道商：印度企业户100u➕14%扎克伯克
G31: 25 | H31: 45599 | M31: GT欧洲 | N31: 2100 | O31: 2000*1.05=2100 | P31: 0.89166667 | S31: =SUMIF(I:I,"Chris Ryan&二不限",J:J) -> 779.34 | T31: 退款（渠道商：Chris Ryan&二不限
G32: 26 | H32: 45599 | I32: 天叶印度2期 | J32: 100 | L32: 0.94375 | S32: =SUMIF(I:I,"FA-泰华印度1016（A-JIE）",J:J) -> 12189.85 | T32: 退款（渠道商：FA-泰华印度1016（A-JIE）
G33: 27 | H33: 45599 | I33: 天叶印度2期 | J33: 12900 | K33: 500*26=13000 | L33: 0.94722222 | S33: =SUMIF(I:I,"印度手工粉测试LS",J:J) -> 999 | T33: 退款（代投：印度手工粉测试LS
G34: 28 | H34: 45600 | M34: GT美国 | N34: 3330 | P34: 0.38888889
G35: 29 | H35: 45600 | M35: GT美国 | N35: 1110 | P35: 0.40208333 | S35: =SUMIF(I:I,"意大利蟑螂哥",J:J) -> 2300 | T35: 意大利蟑螂哥 | U35: =S35+'10月收支财务报表'!V27 -> 18944
G36: 30 | H36: 45600 | M36: 启航广告费 | N36: 20000 | P36: 0.44166667 | S36: =SUMIF(I:I,"土耳其/A李信",J:J) -> 205920 | T36: 土耳其/A李信
G37: 31 | H37: 45600 | M37: 十月二不限-泰华 | N37: 1240 | P37: 0.49791667 | S37: =SUMIF(I:I,"土耳其张总股票粉",J:J) -> 19500 | T37: 土耳其张总股票粉
G38: 32 | H38: 45600 | M38: 启航广告费 | N38: 30000 | P38: 0.51319444 | S38: =SUMIF(I:I,"新印度5期",J:J) -> 100000 | T38: 新印度5期
G39: 33 | H39: 45600 | M39: 账单户广告费 | N39: 5000.69 | P39: 0.51597222 | S39: =SUMIF(I:I,"天叶印度2期",J:J) -> 183000 | T39: 天叶印度2期
G40: 34 | H40: 45600 | I40: 印度19期 | J40: 100 | L40: 0.55486111 | S40: =SUMIF(I:I,"印度17期",J:J) -> 10422 | T40: 印度17期 | U40: 补群
G41: 35 | H41: 45600 | I41: 印度19期 | J41: 99900 | L41: 0.59097222 | M41: GT欧洲 | N41: 2625 | O41: 2500*1.05=2,625 | P41: 0.60972222 | S41: =SUMIF(I:I,"印度18期",J:J) -> 33121 | T41: 印度18期
G42: 36 | H42: 45600 | M42: 金融户印度-泰华Jennie | N42: 1070 | P42: 0.69861111 | S42: =SUMIF(I:I,"印度19期",J:J) -> 200000 | T42: 印度19期
G43: 37 | H43: 45600 | M43: 账单户广告费 | N43: 5000.35 | P43: 0.77083333 | S43: =SUMIF(I:I,"印度10期孟德",J:J) -> 241488 | T43: 印度10期孟德
G44: 38 | H44: 45600 | M44: 十月二不限-泰华 | N44: 2008 | P44: 0.93680556 | S44: =SUMIF(I:I,"印度6期11/13",J:J) -> 100000 | T44: 印度6期11/13
G45: 39 | H45: 45601 | M45: 启航广告费 | N45: 20000 | P45: 0.40069444 | S45: =SUMIF(I:I,"印度20期",J:J) -> 200000 | T45: 印度20期11/16
G46: 40 | H46: 45601 | M46: 十月二不限-泰华 | N46: 3333 | O46: 3300×1.01=3333 | P46: 0.40555556 | S46: =SUMIF(I:I,"印度21期",J:J) -> 100000 | T46: 印度21期11/27
G47: 41 | H47: 45601 | M47: GT美国 | N47: 3330 | O47: 3000×1.11=3330 | P47: 0.40833333 | S47: =SUMIF(I:I,"印度期权",J:J) -> 16912 | T47: 印度期权
G48: 42 | H48: 45601 | M48: 广告配套 | N48: 45 | O48: 美国IP*5 | P48: 0.44375 | S48: =SUMIF(I:I,"海哥印度粉11/26",J:J) -> 60000 | T48: 海哥印度粉11/26
G49: 43 | H49: 45601 | I49: 印度18期 | J49: 33121 | K49: 小柒 | L49: 0.56458333 | M49: GT欧洲 | N49: 2100 | P49: 0.525 | S49: =SUMIF(I:I,"自媒体矩阵F B广告",J:J) -> 14000 | T49: 日本自媒体矩阵F B广告
G50: 44 | H50: 45601 | M50: GT美国 | N50: 5000 | P50: 0.58680556
G51: 45 | H51: 45601 | M51: GT美国 | N51: 2220 | P51: 0.81041667
G52: 46 | H52: 45601 | M52: 广告配套 | N52: 45 | O52: 美国IP*5 | P52: 0.86944444
G53: 47 | H53: 45601 | M53: 一拖九半限户 | N53: 845 | O53: 账单户*4套 | P53: 0.87916667
G54: 48 | H54: 45601 | M54: GT美国 | N54: 2220 | O54: 2000*1.11=2220 | P54: 0.88125
G55: 49 | H55: 45601 | M55: 广告配套 | N55: 211.2 | O55: 个号*5 | P55: 0.90069444
G56: 50 | H56: 45601 | M56: 广告配套 | N56: 6.9058 | O56: SMS邮箱验证手机 | P56: 0.94236111
G57: 51 | H57: 45601 | M57: 广告配套 | N57: 200 | O57: 矿工费 | P57: 0.96041667
G58: 52 | H58: 45601 | M58: 账单户广告费 | N58: 3000.35 | P58: 0.96041667
G59: 53 | H59: 45602 | M59: GT美国 | N59: 4440 | O59: 4000×1.11=4440 | P59: 0.50763889
G60: 54 | H60: 45602 | M60: GT美国 | N60: 4440 | O60: 4000×1.11=4440 | P60: 0.54166667
G61: 55 | H61: 45602 | I61: 印度10期孟德 | J61: 100 | L61: 0.63680556
G62: 56 | H62: 45602 | I62: 印度10期孟德 | J62: 13400 | L62: 0.63819444 | M62: GT美国 | N62: 2220 | O62: 2000×1.11=2220 | P62: 0.64305556
G63: 57 | H63: 45602 | M63: 十月二不限-泰华 | N63: 887 | P63: 0.86388889
G64: 58 | H64: 45602 | M64: 凤凰&洛阳11月 | N64: 34437 | P64: 0.89027778
G65: 59 | H65: 45602 | M65: 启航广告费 | N65: 20000 | P65: 0.91597222
G66: 60 | H66: 45602 | I66: 济宁韦宁&香港有意思 二不限 3% | J66: 3691.29 | L66: 0.42361111
G67: 61 | H67: 45602 | I67: 意大利蟑螂哥 | J67: 2000 | K67: 尾款 | L67: 0.42361111
G68: 62 | H68: 45603 | M68: 印度手工粉测试LS | N68: 2700 | O68: 100*27=2700 | P68: 0.43055556
G69: 63 | H69: 45603 | M69: GT美国 | N69: 11100 | O69: 10000*1.11=11,100 | P69: 0.44305556
G70: 64 | H70: 45603 | M70: GT欧洲 | N70: 3150 | P70: 0.45763889
G71: 65 | H71: 45603 | I71: 天叶印度2期 | J71: 20000 | L71: 0.52152778 | M71: GT美国 | N71: 8325 | O71: 7500*1.11=8325 | P71: 0.55763889
G72: 66 | H72: 45603 | I72: 印度19期 | J72: 100000 | L72: 0.59444444 | M72: GT欧洲 | N72: 1415.05 | P72: 0.59791667
G73: 67 | H73: 45603 | M73: 广告配套 | N73: 209.38 | O73: 耐用号*5 | P73: 0.60277778
G74: 68 | H74: 45603 | M74: 广告配套 | N74: 45 | O74: 美国IP*5条 | P74: 0.66527778
G75: 69 | H75: 45603 | M75: 广告配套 | N75: 49 | O75: WS计数号1个土耳其、2个印度（一个月） | P75: 0.86805556
G76: 70 | H76: 45603 | M76: 一拖九半限户 | N76: 420 | O76: 2套账单户 | P76: 0.89513889
G77: 71 | H77: 45603 | M77: 账单户广告费 | N77: 3000.06 | P77: 0.90138889
G78: 72 | H78: 45604 | M78: 凤凰&洛阳11月 | N78: 10481 | O78: 3000*1.1+3000*1.19+3000*1.19+35*1.19 | P78: 0.99027778
G79: 73 | H79: 45604 | M79: 十月二不限-泰华 | N79: 1242 | P79: 0.015972222
G80: 74 | H80: 45604 | I80: 土耳其/A李信 | J80: 32500 | K80: 500*65=32500 | L80: 0.072916667 | M80: 印度手工粉测试LS | N80: =200*27 -> 5400 | O80: 200*27=5400 | P80: 0.40972222
G81: 75 | H81: 45604 | M81: 凤凰&洛阳11月 | N81: 11900 | O81: 10000*1.19=11900 | P81: 0.53125
G82: 76 | H82: 45604 | M82: GT美国 | N82: 10545 | O82: 9500*1.11=10545 | P82: 0.56111111
G83: 77 | H83: 45604 | M83: GT欧洲 | N83: 8925 | O83: 8500*1.05=8925 | P83: 0.56388889
G84: 78 | H84: 45604 | M84: 凤凰&洛阳11月 | N84: 11900 | O84: 10000*1.19=11900 | P84: 0.56527778
G85: 79 | H85: 45604 | M85: GT美国 | N85: 4440 | O85: 4000*1.11=4440 | P85: 0.60277778
G86: 80 | H86: 45604 | M86: GT美国 | N86: 4440 | O86: 4000*1.11=4440 | P86: 0.63055556
G87: 81 | H87: 45604 | I87: 印度10期孟德 | J87: 100 | L87: 0.64305556
G88: 82 | H88: 45604 | I88: 印度10期孟德 | J88: 26900 | K88: 1000*27=27000 | L88: 0.64513889 | M88: GT美国 | N88: 1110 | O88: 1000*1.11=1110 | P88: 0.66666667
G89: 83 | H89: 45604 | M89: 凤凰&洛阳11月 | N89: 23800 | O89: 20000*1.19=23800 | P89: 0.71319444
G90: 84 | H90: 45604 | M90: 广告配套 | N90: 125.71 | O90: 耐用号*3 | P90: 0.72777778
G91: 85 | H91: 45604 | I91: BH欧洲户-泰华-欧洲企业户-6+1 | J91: 995.35 | K91: 退款 | L91: 0.73472222 | M91: 十月二不限-泰华 | N91: 1866 | O91: 2000-152=1848×1.01=1866 | P91: 0.79236111
G92: 86 | H92: 45604 | M92: 凤凰&洛阳11月 | N92: 35700 | O92: 20000*1.19+11900=35700 | P92: 0.82361111
G93: 87 | H93: 45604 | M93: 广告配套 | N93: 45 | O93: 美国IP*5条 | P93: 0.90208333
G94: 88 | H94: 45604 | M94: 凤凰&洛阳11月 | N94: 51170 | O94: 43000*1.19=51170 | P94: 0.93680556
G95: 89 | H95: 45604 | I95: 土耳其/A李信 | J95: 32500 | K95: 500*65=32500 | L95: 0.99375
G96: 90 | H96: 45605 | M96: 十月二不限-泰华 | N96: 1212 | O96: 总充值1200×1.01=1212
G97: 91 | H97: 45605 | I97: 天叶印度2期 | J97: 50000 | L97: 0.50625 | M97: 广告配套 | N97: 45 | O97: 美国IP*5条 | P97: 0.55486111
G98: 92 | H98: 45605 | I98: 印度10期孟德 | J98: 100 | L98: 0.58055556
G99: 93 | H99: 45605 | I99: 印度10期孟德 | J99: 107900 | L99: 0.58333333 | M99: 凤凰&洛阳11月 | N99: 26220 | O99: 23000*1.14=26220 | P99: 0.69652778
G100: 94 | H100: 45605 | M100: 启航广告费 | N100: 15000 | P100: 0.69930556
G101: 95 | H101: 45605 | M101: 十月二不限-泰华 | N101: 3636 | P101: 0.72847222
G102: 96 | H102: 45605 | M102: 凤凰&洛阳11月 | N102: 28500 | P102: 0.67152778
...

Sheet 10月收支财务报表
C1: 10月收支财务报表
C4: 财务统计 STATISTICS | G4: 10月收支明细 DETAIL
G5: 序号 | H5: 日期 | I5: 收入 | M5: 支出
C6: 月份查询 | I6: 项目 | J6: 金额 | K6: 备注 | L6: 时间 | M6: 项目 | N6: 金额 | O6: 备注 | P6: 时间
C7: 10月 | D7: ▼ | G7: 1 | H7: 45566 | I7: 9月剩余 | J7: ='9月收支财务报表'!C25 -> 72340.422 | M7: 凤凰&洛阳&15+1（1200）&8+1（60） | N7: =37100-'9月收支财务报表'!N175 -> 35700 | O7: 其中1400在10/1的合并付款，结9月的尾款 | P7: 0.78680556 | V7: 45566 | W7: 凤凰&洛阳&15+1（1200）&8+1（60） | X7: 11900 | Y7: EGM | Z7: 已付
C8: 收入 | G8: 2 | H8: 45567 | I8: 凯旋城三期印度 | J8: 20000 | K8: 转汇旺了 | L8: 0.41944444 | M8: 后勤转入 | N8: 20000 | V8: 45566 | W8: 凤凰&洛阳&15+1（1200）&8+1（60） | X8: 11900 | Y8: SFA | Z8: 已付
C9: =C21 -> 1111450.1 | G9: 3 | H9: 45567 | I9: 凯旋城三期印度 | J9: 30000 | K9: 成成 | L9: 0.42083333 | M9: 凤凰&洛阳&15+1（1200）&8+1（60） | N9: 30744 | O9: 右边尾款+9/30 | P9: 0.44444444 | V9: 45566 | W9: 凤凰&洛阳&15+1（1200）&8+1（60） | X9: 11900 | Y9: EGM | Z9: 已付
C10: 支出 | G10: 4 | H10: 45567 | I10: 凯旋城三期印度 | J10: 50000 | K10: 成成 | L10: 0.55625 | V10: 45566 | W10: 凤凰&洛阳&15+1（1200）&8+1（60） | X10: 11900 | Y10: SFA | Z10: 已付
C11: =C23 -> 1015854.3 | G11: 5 | H11: 45567 | I11: 凯旋城三期印度 | J11: 38024 | K11: 成成 | L11: 0.70208333 | M11: 海哥-印度粉9/22 | N11: 38024 | O11: 退款泰总，张总直出 | P11: 0.70208333 | V11: 45567 | W11: 凤凰&洛阳&15+1（1200）&8+1（60） | X11: 2240 | Y11: KE 33 (PDT) - YSC-Leigee-28 | Z11: 已付
C12: 结余 | G12: 6 | H12: 45567 | I12: 印度一期9/19 | J12: 23298 | K12: 小柒 | L12: 0.72986111 | M12: 凤凰&洛阳&15+1（1200）&8+1（60） | N12: 40180 | O12: KE 33 (PDT) - YSC-Leigee-28（4480），SFA（23800），EGM （11900） | P12: 0.75833333 | V12: 45567 | W12: 凤凰&洛阳&15+1（1200）&8+1（60） | X12: 23800 | Y12: SFA | Z12: 已付
C13: =C9-C11 -> 95595.759 | G13: 7 | H13: 45567 | M13: GF&SHEN美国户 开10u 10%+u1 | N13: 40 | O13: 开户费 | P13: 0.79513889 | V13: 45567 | W13: 凤凰&洛阳&15+1（1200）&8+1（60） | X13: 11900 | Y13: EGM | Z13: 已付
G14: 8 | H14: 45568 | M14: GF&SHEN美国户 开10u 10%+u1 | N14: 2220 | O14: 4户*500+220手续费 | P14: 0.54583333 | AB14: =X8+X10+X12 -> 47600
C15: 任意时段查询 | G15: 9 | H15: 45568 | M15: 启航广告费 | N15: 7261.81 | O15: 启航 | P15: 0.97916667
C16: 起始日期： | G16: 10 | H16: 45569 | M16: BM户测试大白& | N16: 160 | O16: 4个开户费 | P16: 0.41041667 | V16: =SUM(V17:V23) -> 47236.64
C17: 45292 | G17: 11 | H17: 45569 | M17: BM户测试大白& | N17: 4560 | O17: 充值4K，手续费560 | P17: 0.46111111 | V17: =SUMIF(I:I,"斯特普思-泰华",J:J) -> 802 | W17: 退款（渠道商：斯特普思-泰华
C18: 结束日期： | G18: 12 | H18: 45569 | M18: 后勤转入 | N18: 54700 | P18: 0.70486111 | V18: =SUMIF(I:I,"邻点美国三不限户",J:J) -> 300 | W18: 退款（渠道商：邻点美国三不限户
C19: 72805 | G19: 13 | H19: 45570 | I19: 凯旋城三期印度 | J19: 30000 | K19: 成成 | L19: 0.37013889 | V19: =SUMIF(I:I,"FF139&星辰-欧元户5%",J:J) -> 1866 | W19: 退款（渠道商：FF139&星辰-欧元户5%
C20: 收入 | G20: 14 | H20: 45570 | I20: 印度 金融，测户Old K | J20: 1990.76 | K20: 退款 | L20: 0.58125 | V20: =SUMIF(I:I,"印度测户-黑泽明",J:J) -> 4988.35 | W20: 退款（渠道商：印度测户-黑泽明
C21: =SUMIFS(J:J,H:H,">="&$C$17,H:H,"<="&$C$19) -> 1111450.1 | G21: 15 | H21: 45570 | I21: 后勤转入 | J21: 20660 | L21: 0.58125 | M21: 后勤转入 | N21: 52715.34 | O21: 发fa工资 | V21: =SUMIF(I:I,"Shen wade&BM户35+2+1江小南",J:J) -> 3938.09 | W21: 退款（渠道商：Shen wade&BM户35+2+1江小南
C22: 支出 | G22: 16 | H22: 45572 | I22: 凯旋城三期印度 | J22: 11502 | K22: 成成 | L22: 0.75277778 | M22: 印度粉测试 | N22: 10290 | O22: ~K in | P22: 0.79722222 | V22: =SUMIF(I:I,"凤凰&洛阳&15+1（1200）&8+1（60）",J:J) -> 33351.44 | W22: 退款（渠道商：凤凰&洛阳&15+1（1200）&8+1（60）
C23: =SUMIFS(N:N,H:H,">="&$C$17,H:H,"<="&$C$19) -> 1015854.3 | G23: 17 | H23: 45573 | M23: bm5-mingzihaha | N23: 140 | O23: bm5户35*4=140 | P23: 0.48194444 | V23: =SUMIF(I:I,"印度 金融，测户Old K",J:J) -> 1990.76 | W23: 退款（渠道商：印度 金融，测户Old K）
C24: 结余 | G24: 18 | H24: 45573 | I24: 凤凰&洛阳&15+1（1200）&8+1（60） | J24: 30000 | K24: 退款 | L24: 0.75138889 | V24: =SUMIF(I:I,"凯旋城三期印度",J:J) -> 179526 | W24: 凯旋城三期印度 | X24: =V24+'9月收支财务报表'!S32 -> 329526
C25: =C21-C23 -> 95595.759 | G25: 19 | H25: 45574 | M25: bm5-mingzihaha | N25: 175 | O25: bm5户35*5=175 | P25: 0.54861111 | V25: =SUMIF(I:I,"印度一期9/19",J:J) -> 23298 | W25: 印度一期9/19
G26: 20 | H26: 45574 | M26: GF&SHEN美国户 开10u 10%+u1 | N26: 555 | O26: 55手续费 | P26: 0.57083333 | V26: =SUMIF(I:I,"鼎盛专用广告费",J:J) -> 150000 | W26: 鼎盛专用广告费
G27: 21 | H27: 45574 | M27: bm5-mingzihaha | N27: 175 | O27: bm5户35*5=175 | P27: 15.27 | V27: =SUMIF(I:I,"意大利蟑螂哥",J:J) -> 16644 | W27: 意大利蟑螂哥
G28: 22 | H28: 45574 | M28: 启航广告费 | N28: 8174.09 | O28: 启航 | P28: 0.76388889 | V28: =SUMIF(I:I,"德国股粉对接群",J:J) -> 9045 | W28: 德国股粉对接群
G29: 23 | H29: 45574 | M29: 账单户广告费 | N29: 2000.72 | O29: 账单户 | P29: 0.76736111 | V29: =SUMIF(I:I,"印度4期",J:J) -> 300000 | W29: 新印度4期
G30: 24 | H30: 45575 | M30: BM户测试大白& | N30: 160 | O30: 4个开户费 | P30: 0.34166667 | S30: 合并转款 | V30: =SUMIF(I:I,"土耳其/A李信",J:J) -> 26000 | W30: 土耳其/A李信
G31: 25 | H31: 45575 | M31: BM户测试大白& | N31: 1140 | O31: LT - 04469 - Gf-USD-22( 8) 332 | P31: 0.34166667 | S31: 合并转款 | V31: =SUMIF(I:I,"印度17期",J:J) -> 66700 | W31: 印度17期
G32: 26 | H32: 45575 | M32: BM户测试大白& | N32: 5700 | O32: LT - 04469 - Gf-USD-25(+8) 335 (1056817212636571)再充值3000 LT - 04469 - Gf-USD-22( 8) 332 (536985655554367)再充值2000 | P32: 0.42847222 | V32: =SUMIF(I:I,"印度18期",J:J) -> 200000 | W32: 印度18期 | X32: =V32+'11月收支财务报表'!S41 -> 233121
G33: 27 | H33: 45575 | M33: Shen wade&BM户35+2+1江小南 | N33: 1170 | O33: 35*4+1000*1.03=1170 | P33: 0.43472222 | V33: =SUM(V24:V32) -> 971213
G34: 28 | H34: 45575 | M34: 广告配套 | N34: 90 | O34: 欧洲IP：9*10=90 | P34: 0.44861111
G35: 29 | H35: 45575 | M35: Shen wade&BM户35+2+1江小南 | N35: 3300 | O35: 35*6+500*6*1.03=3300 | P35: 0.50833333 | S35: 开户费35*6=210
G36: 30 | H36: 45575 | M36: BM户测试大白& | N36: 2280 | O36: RF - 04469 Gf-USD-02(+8) 209 372505352366095 | P36: 0.51041667
G37: 31 | H37: 45575 | M37: 广告配套 | N37: 0.23 | O37: 谷歌邮箱 | P37: 0.57708333
G38: 32 | H38: 45575 | M38: 十月二不限-泰华 | N38: 909 | O38: Xingm-18 编号: 8869381796416185 充值：300 Xingm-19 编号: 459265433824967 充值：300 Xingm-20 编号: 2002146643576258 充值：300 | P38: 0.58541667 | V38: =SUMIF(M:M,"凤凰&洛阳&15+1（1200）&8+1（60）",N:N) -> 106624 | W38: 凤凰&洛阳&15+1（1200）&8+1（60） | X38: =V38+V39 -> 147767.8
G39: 33 | H39: 45575 | M39: GF&SHEN美国户 开10u 10%+u1 | N39: 1130 | O39: 1000*1.11=1110 1110+20=1130 | P39: 0.59861111 | V39: =SUMIF(M:M,"凤凰&洛阳&10月",N:N) -> 41143.8 | W39: 凤凰&洛阳&10月
G40: 34 | H40: 45575 | I40: 鼎盛专用广告费 | J40: 100000 | L40: 0.60902778 | M40: 十月二不限-泰华 | N40: 1527 | O40: Xingm-18 编号: 8869381796416185 充值500 Xingm-19 编号: 459265433824967 充值500 Xingm-20 编号: 2002146643576258 充值500 | P40: 0.70972222 | S40: 开户费12 | V40: =SUMIF(M:M,"GT2&SHEN 欧 4%+u1",N:N) -> 20111.537 | W40: GT2&SHEN 欧 4%+u1
G41: 35 | H41: 45576 | M41: GF&SHEN美国户 开10u 10%+u1 | N41: 1110 | O41: LT - 04469 - Gf-USD-26(+8) 336 1000*1.11=1110 | P41: 0.47986111 | V41: =SUMIF(M:M,"GF&SHEN美国户 开10u 10%+u1",N:N) -> 35254.09 | W41: GF&SHEN美国户 开10u 10%+u1
G42: 36 | H42: 45576 | M42: BM户测试大白& | N42: 5700 | O42: LT - 04469 - Gf-USD-24(+8) 334 1588711295191636 | P42: 0.48333333 | V42: =SUMIF(M:M,"GT&SHEN 台湾户 开 20 10%u1",N:N) -> 16992.9 | W42: GT&SHEN 台湾户 开 20 10%u1
G43: 37 | H43: 45576 | M43: BM户测试大白& | N43: 1140 | O43: RF - 04469 Gf-USD-04(+8) 207 373635832294866 | P43: 0.58611111 | V43: =SUMIF(M:M,"启航广告费",N:N) -> 286627.73 | W43: 启航广告费 | X43: 转款有一个点u损
G44: 38 | H44: 45576 | M44: 启航广告费 | N44: 10000 | O44: 启航 | P44: 0.63125 | V44: =SUMIF(M:M,"BM户测试大白&",N:N) -> 31344.74 | W44: BM户测试大白& | X44: =V44+'9月收支财务报表'!S19 -> 31794.74
G45: 39 | H45: 45576 | M45: GF&SHEN美国户 开10u 10%+u1 | N45: 20.2 | O45: 2个开户手续费 | P45: 0.75972222 | V45: =SUMIF(M:M,"印度粉测试",N:N) -> 10290 | W45: 印度粉测试代投 | X45: =V45+'9月收支财务报表'!S18 -> 15540
G46: 40 | H46: 45576 | M46: 十月二不限-泰华 | N46: 1419 | O46: 手续费 | P46: 0.77708333 | V46: =SUMIF(M:M,"bm5-mingzihaha",N:N) -> 490 | W46: bm5-mingzihaha
G47: 41 | H47: 45577 | I47: 意大利蟑螂哥 | J47: 4301 | L47: 03：41 | M47: 十月二不限-泰华 | N47: 1111 | P47: 0.45625 | V47: =SUMIF(M:M,"账单户广告费",N:N) -> 22006.16 | W47: 账单户广告费
G48: 42 | H48: 45577 | M48: 账单户广告费 | N48: 1000.37 | P48: 0.55833333 | V48: =SUMIF(M:M,"Shen wade&BM户35+2+1江小南",N:N) -> 4470 | W48: Shen wade&BM户35+2+1江小南
G49: 43 | H49: 45577 | M49: 三不限-泰华709-Sherry | N49: 120 | O49: 开户费 | P49: 0.69236111 | V49: =SUMIF(M:M,"广告配套",N:N) -> 2594.69 | W49: 广告配套
G50: 44 | H50: 45577 | M50: 十月二不限-泰华 | N50: 3168 | P50: 18：15 | V50: =SUMIF(M:M,"十月二不限-泰华",N:N) -> 88387.9 | W50: 十月二不限-泰华
G51: 45 | H51: 45578 | I51: 意大利蟑螂哥 | J51: 5598 | L51: 03：23 | M51: 账单户广告费 | N51: 1500.04 | P51: 0.5125 | V51: =SUMIF(M:M,"三不限-泰华709-Sherry",N:N) -> 1905 | W51: 三不限-泰华709-Sherry | X51: 欧洲三不限-泰华709
G52: 46 | H52: 45578 | M52: BM户测试大白& | N52: 2524.74 | O52: LT - 04469 - Gf-USD-25(+8) 335 (1056817212636571)充值3000 | P52: 0.93541667 | V52: =SUMIF(M:M,"狗头账单户",N:N) -> 254 | W52: 狗头账单户
G53: 47 | H53: 45578 | M53: 账单户广告费 | N53: 1000.95 | P53: 0.98402778 | V53: =SUMIF(M:M,"印度测户-黑泽明",N:N) -> 5492.25 | W53: 印度测户-黑泽明 | X53: 已退款
G54: 48 | H54: 45579 | M54: GF&SHEN美国户 开10u 10%+u1 | N54: 1681.07 | O54: RF - 04469 Gf-USD-07(+8) 204 (318533944174079) LT - 04469 Gf-USD-342 (-8) 0401 2134746810316208 | P54: 0.42430556 | V54: =SUMIF(M:M,"越南户测试-船奇",N:N) -> 25875 | W54: 越南户测试-船奇 | X54: 泡泡
G55: 49 | H55: 45579 | M55: GF&SHEN美国户 开10u 10%+u1 | N55: 1110 | O55: LT - 04469 Gf-USD-343 (-8) 0400 4054205168179144 | P55: 0.42777778 | V55: =SUMIF(M:M,"博程-欧洲美金户-泰华",N:N) -> 7150 | W55: 博程-欧洲美金户-泰华 | X55: 泡泡
G56: 50 | H56: 45579 | M56: BM户测试大白& | N56: 5700 | O56: LT - 04469 - Gf-USD-24(+8) 334 1588711295191636 | P56: 0.49513889 | V56: =SUMIF(M:M,"FA-泰华印度1016",N:N) -> 20260 | W56: FA-泰华印度1016（A-JIE）
G57: 51 | H57: 45579 | M57: GF&SHEN美国户 开10u 10%+u1 | N57: 3330 | O57: LT - 04469 Gf-USD-343 (-8) 0400 4054205168179144 充3000 | P57: 0.58541667 | V57: =SUMIF(M:M,"斯特普思-泰华",N:N) -> 4200 | W57: 斯特普思-泰华
G58: 52 | H58: 45579 | M58: BM户测试大白& | N58: 2280 | O58: LT - 04469 - Gf-USD-25(+8) 335 (1056817212636571)再充值2000 | P58: 0.59861111 | V58: =SUMIF(M:M,"深圳芳林子@SHEN 户",N:N) -> 110069.8 | W58: 深圳芳林子@SHEN 户
G59: 53 | H59: 45579 | M59: GF&SHEN美国户 开10u 10%+u1 | N59: 1111.23 | O59: RF - 04469 Gf-USD-07(+8) 204 (318533944174079)充值1000那就是目前的欠款 1.11+你充值的1000=1001.11*1.11=1111.23 打款这么多 | P59: 0.59444444 | V59: =SUMIF(M:M,"BH欧洲户-泰华-欧洲企业户-6+1",N:N) -> 1070.6 | W59: BH欧洲户-泰华-欧洲企业户-6+1 | X59: 11/5号退款
G60: 54 | H60: 45579 | M60: 广告配套 | N60: 90 | O60: 美国IP*10 | P60: 0.64444444 | V60: =SUMIF(M:M,"Fb966半限户-啊噗",N:N) -> 1051.26 | W60: Fb966半限户-啊噗
G61: 55 | H61: 45579 | M61: 广告配套 | N61: 423.77 | O61: 耐用号*10 | P61: 0.66041667 | V61: =SUMIF(M:M,"邻点美国三不限户",N:N) -> 3660 | W61: 邻点美国三不限户 | X61: 已退款300
G62: 56 | H62: 45579 | M62: 三不限-泰华709-Sherry | N62: 1785 | O62: 下户费：180+充值3x500+服务费105=1785 | P62: 0.66875 | V62: =SUMIF(M:M,"Chris Ryan&二不限 麦芽互动 下户-西柚",N:N) -> 1832.52 | W62: Chris Ryan&二不限
G63: 57 | H63: 45579 | I63: Shen wade&BM户35+2+1江小南 | J63: 3938.09 | K63: 退款 | L63: 16：43 | M63: 狗头账单户 | N63: 254 | O63: 5个半限 | P63: 0.71319444 | V63: =SUMIF(M:M,"印度企业户100u➕14%扎克伯克",N:N) -> 1256.986 | W63: 印度企业户100u➕14%扎克伯克
G64: 58 | H64: 45580 | I64: 意大利蟑螂哥 | J64: 3325 | L64: 0.11597222 | M64: 印度测户-黑泽明 | N64: 2701.75 | O64: 2500*1.07*1.01=2701.75 | P64: 0.59722222 | V64: =SUM(V38:V63) -> 850414.96
G65: 59 | H65: 45580 | M65: GF&SHEN美国户 开10u 10%+u1 | N65: 5550 | O65: LT - 04469 Gf-USD-342 (-8) 0401 2134746810316208 | P65: 0.64652778
G66: 60 | H66: 45580 | I66: 德国股粉对接群 | J66: 3375 | K66: 老九 | L66: 0.63611111 | M66: 账单户广告费 | N66: 2000.99 | P66: 0.69305556
G67: 61 | H67: 45580 | M67: 越南户测试-船奇 | N67: 2875 | O67: 2500*1.05=2625+50=2675+200定金=2875 | P67: 0.77916667
G68: 62 | H68: 45581 | M68: 广告配套 | N68: 762 | O68: 50.8*15=762u | P68: 0.47569444
G69: 63 | H69: 45581 | M69: 账单户广告费 | N69: 2000.02 | P69: 0.56388889
G70: 64 | H70: 45581 | M70: 广告配套 | N70: 210.69 | O70: 耐用号*5 | P70: 0.59097222
G71: 65 | H71: 45581 | M71: 广告配套 | N71: 45 | O71: 美国IP*5 | P71: 0.59236111
G72: 66 | H72: 45581 | M72: 广告配套 | N72: 90 | O72: 美国IP*10续费 | P72: 0.60277778
G73: 67 | H73: 45581 | I73: 印度测户-黑泽明 | J73: 2540.35 | K73: 540.35➕2000等于2540.35 | L73: 0.70972222
G74: 68 | H74: 45582 | M74: 博程-欧洲美金户-泰华 | N74: 10 | P74: 0.475
G75: 69 | H75: 45582 | M75: 博程-欧洲美金户-泰华 | N75: =6000-N74 -> 5990 | O75: 5000*1.15=5750+250=6000 | P75: 0.47847222
G76: 70 | H76: 45582 | M76: GF&SHEN美国户 开10u 10%+u1 | N76: 5650 | O76: 开户费10*10=100 5550+100=5650 | P76: 0.49791667
G77: 71 | H77: 45582 | M77: GT&SHEN 台湾户 开 20 10%u1 | N77: 1150 | O77: 1000×1.11=1110+40=1150 | P77: 0.55208333
G78: 72 | H78: 45582 | M78: 印度测户-黑泽明 | N78: 2790.5 | O78: 2000+500*1.07*1.01+250（开户费）=2790.5 | P78: 0.57708333
G79: 73 | H79: 45582 | M79: 十月二不限-泰华 | N79: 588 | P79: 0.59444444
G80: 74 | H80: 45582 | M80: 十月二不限-泰华 | N80: 1159 | P80: 0.77847222
G81: 75 | H81: 45582 | M81: FA-泰华印度1016 | N81: 2800 | O81: 500*5*1.12=2800 | P81: 0.80208333
G82: 76 | H82: 45582 | M82: 启航广告费 | N82: 10000 | O82: 启航 | P82: 0.95347222
G83: 77 | H83: 45583 | M83: GT&SHEN 台湾户 开 20 10%u1 | N83: 1100 | O83: 1000×1.10=1100 | P83: 0.60555556
G84: 78 | H84: 45583 | M84: 十月二不限-泰华 | N84: 1291 | P84: 17：36
G85: 79 | H85: 45583 | M85: 斯特普思-泰华 | N85: 420 | O85: 60*7=420 | P85: 19：19
G86: 80 | H86: 45583 | M86: 十月二不限-泰华 | N86: 614 | P86: 20：35
G87: 81 | H87: 45584 | M87: GT&SHEN 台湾户 开 20 10%u1 | N87: 987.9 | O87: 打款890*1.11=987.9 | P87: 0.55902778
G88: 82 | H88: 45584 | M88: 十月二不限-泰华 | N88: 1573 | P88: 15：26
G89: 83 | H89: 45584 | M89: 启航广告费 | N89: 10000 | O89: 启航 | P89: 0.96597222
G90: 84 | H90: 45585 | M90: 深圳芳林子@SHEN 户 | N90: 1111 | O90: 1000*1.1*1.01=1111 | P90: 0.37708333
G91: 85 | H91: 45585 | M91: GT&SHEN 台湾户 开 20 10%u1 | N91: 1111 | O91: 1000*1.1*1.01=1111 | P91: 0.40138889
G92: 86 | H92: 45585 | M92: 十月二不限-泰华 | N92: 1445 | P92: 0.52291667
G93: 87 | H93: 45585 | M93: Chris Ryan&二不限 麦芽互动 下户-西柚 | N93: 999 | O93: 900*1.01=909+45*2=999 | P93: 0.57777778
G94: 88 | H94: 45585 | M94: 广告配套 | N94: 228 | O94: 防护，圣盾 | P94: 0.64027778
G95: 89 | H95: 45585 | M95: 斯特普思-泰华 | N95: 2700 | O95: 2500*1.08=2700，64 (1438923226716919) | P95: 0.66805556
G96: 90 | H96: 45585 | M96: GT&SHEN 台湾户 开 20 10%u1 | N96: 1332 | O96: 1200*1.11=1332 | P96: 16：41
G97: 91 | H97: 45585 | I97: 鼎盛专用广告费 | J97: 50000 | L97: 0.85069444 | M97: GT&SHEN 台湾户 开 20 10%u1 | N97: 4440 | O97: YLG-GT-SHEN-1019-01(+8) (1754657002021877)充值4000 | P97: 0.91875
G98: 92 | H98: 45586 | M98: 十月二不限-泰华 | N98: 1133 | P98: 0.40416667
G99: 93 | H99: 45586 | M99: 博程-欧洲美金户-泰华 | N99: 1150 | O99: LT - 04469 - Gf-USD-12(+8) 423 1058145169313233充1000 | P99: 0.56597222
G100: 94 | H100: 45586 | M100: GF&SHEN美国户 开10u 10%+u1 | N100: 1650 | O100: 1500*1.1=1,650 | P100: 0.57708333
G101: 95 | H101: 45586 | M101: BH欧洲户-泰华-欧洲企业户-6+1 | N101: 1070.6 | O101: 1000*1.06*1.01=1070.6 | P101: 0.71805556
G102: 96 | H102: 45586 | M102: 斯特普思-泰华 | N102: 1080 | P102: 0.76180556
...

Sheet 10月支付宝备用金
C1: 10月收支财务报表
C4: 财务统计 STATISTICS | G4: 10月收支明细 DETAIL
G5: 序号 | H5: 日期 | I5: 收入 | M5: 支出
C6: 月份查询 | I6: 项目 | J6: 金额（¥） | K6: 备注 | L6: 时间 | M6: 项目 | N6: 金额（¥） | O6: 备注 | P6: 时间
C7: 10月 | D7: ▼ | G7: 1 | H7: 45566 | I7: 9月剩余 | J7: ='9月支付宝备用金'!C25 -> 7715.56
C8: 收入 | G8: 2 | H8: 45572 | M8: 广告配套 | N8: 100 | O8: BM*5 | P8: 0.68055556
C9: =C21 -> 7715.56 | G9: 3 | H9: 45573 | M9: 广告配套 | N9: 100 | O9: BM*5 | P9: 0.94097222
C10: 支出 | G10: 4 | H10: 45575 | M10: 广告配套 | N10: 350 | O10: 个号*10 | P10: 0.51597222
C11: =C23 -> 7715.56 | G11: 5 | H11: 45579 | M11: 转入总备用金 | N11: 7165.56
C12: 结余 | G12: 6
C13: =C9-C11 -> 0 | G13: 7
G14: 8
C15: 任意时段查询 | G15: 9
C16: 起始日期： | G16: 10
C17: 45292 | G17: 11
C18: 结束日期： | G18: 12
C19: 72805 | G19: 13
C20: 收入 | G20: 14
C21: =SUMIFS(J:J,H:H,">="&$C$17,H:H,"<="&$C$19) -> 7715.56 | G21: 15
C22: 支出 | G22: 16
C23: =SUMIFS(N:N,H:H,">="&$C$17,H:H,"<="&$C$19) -> 7715.56 | G23: 17
C24: 结余 | G24: 18
C25: =C21-C23 -> 0 | G25: 19
G26: 20
G27: 21
G28: 22
G29: 23
G30: 24
G31: 25
G32: 26
G33: 27
G34: 28
G35: 29
G36: 30
G37: 31
... G241: 235

Sheet 10月微信备用金
C1: 10月收支财务报表
C4: 财务统计 STATISTICS | G4: 10月收支明细 DETAIL
G5: 序号 | H5: 日期 | I5: 收入 | M5: 支出
C6: 月份查询 | I6: 项目 | J6: 金额（¥） | K6: 备注 | L6: 时间 | M6: 项目 | N6: 金额（¥） | O6: 备注 | P6: 时间
C7: 10月 | D7: ▼ | G7: 1 | H7: 45566 | I7: 9月剩余 | J7: ='9月微信备用金'!C25 -> 2086.86
C8: 收入 | G8: 2 | H8: 45575 | M8: 广告配套 | N8: 43.15 | O8: 100个浏览器环境（剩余6天） | P8: 0.47083333
C9: =C21 -> 2086.86 | G9: 3 | H9: 45579 | M9: 转入总备用金 | N9: =2043.71 -> 2043.71
C10: 支出 | G10: 4
C11: =C23 -> 2086.86 | G11: 5
C12: 结余 | G12: 6
C13: =C9-C11 -> 0 | G13: 7
G14: 8
C15: 任意时段查询 | G15: 9
C16: 起始日期： | G16: 10
C17: 45292 | G17: 11
C18: 结束日期： | G18: 12
C19: 72805 | G19: 13
C20: 收入 | G20: 14
C21: =SUMIFS(J:J,H:H,">="&$C$17,H:H,"<="&$C$19) -> 2086.86 | G21: 15
C22: 支出 | G22: 16
C23: =SUMIFS(N:N,H:H,">="&$C$17,H:H,"<="&$C$19) -> 2086.86 | G23: 17
C24: 结余 | G24: 18
C25: =C21-C23 -> 0 | G25: 19
G26: 20
G27: 21
G28: 22
G29: 23
G30: 24
G31: 25
G32: 26
G33: 27
G34: 28
G35: 29
G36: 30
G37: 31
... G241: 235

Sheet 9月收支财务报表
C1: 9月收支财务报表
S2: =SUM(S4:S19)-S4-S8 -> 2064249.4
C4: 财务统计 STATISTICS | G4: 9月收支明细 DETAIL | S4: =SUMIF(M:M,"后勤转入",N:N) -> 20000 | T4: 后勤发工资
G5: 序号 | H5: 日期 | I5: 收入 | M5: 支出 | S5: =SUMIF(M:M,"广告配套",N:N) -> 4760.6 | T5: 广告配套
C6: 月份查询 | I6: 项目 | J6: 金额 | K6: 备注 | L6: 时间 | M6: 项目 | N6: 金额 | O6: 备注 | P6: 时间 | S6: =SUMIF(M:M,"凤凰&洛阳&15+1（1200）&8+1（60）",N:N) -> 1882214.6 | T6: 凤凰&洛阳&15+1（1200）&8+1（60）
C7: 9月 | D7: ▼ | G7: 1 | H7: 45536 | I7: 8月结余 | J7: ='8月收支财务报表'!C25 -> 14888.892 | M7: 凤凰&洛阳&15+1（1200）&8+1（60） | N7: 11900 | O7: BBH ACC New 1 | P7: 0.49097222 | S7: =SUMIF(M:M,"账单户广告费",N:N) -> 41506.79 | T7: 账单户广告费
C8: 收入 | G8: 2 | H8: 45536 | I8: wade- 海外户对接nancy | J8: 8000 | L8: 0.030555556 | S8: =SUMIF(M:M,"深圳团队备用金",N:N) -> 20000 | T8: 深圳团队备用金 | U8: 算到后勤
C9: =C21 -> 2214195.8 | G9: 3 | H9: 45536 | I9: 印度14期 | J9: 100000 | K9: 小柒 | L9: 0.73263889 | M9: 凤凰&洛阳&15+1（1200）&8+1（60） | N9: 11900 | O9: BBH ACC New 1 | P9: 0.73402778 | S9: =SUMIF(M:M,"启航广告费",N:N) -> 104251.42 | T9: 启航广告费
C10: 支出 | G10: 4 | H10: 45536 | I10: 印度粉 FB 李修缘 | J10: 100 | K10: 咖啡 | L10: 0.76875 | S10: =SUMIF(M:M,"推特代投",N:N)-J71 -> 7480 | T10: 推特代投
C11: =C23 -> 2141855.4 | G11: 5 | H11: 45536 | I11: 印度粉 FB 李修缘 | J11: 49900 | K11: 咖啡 | L11: 0.77152778 | M11: 凤凰&洛阳&15+1（1200）&8+1（60） | N11: 23800 | O11: BBH ACC New 1 | P11: 0.77569444 | S11: =SUMIF(M:M,"户对接-Nancy",N:N) -> 1110 | T11: 户对接-Nancy
C12: 结余 | G12: 6 | H12: 45536 | M12: 凤凰&洛阳&15+1（1200）&8+1（60） | N12: 23800 | O12: BBH ACC New 1 | P12: 0.90347222 | S12: =SUMIF(M:M,"印度 金融，测户Old K",N:N) -> 2280 | T12: 印度 金融，测户Old K
C13: =C9-C11 -> 72340.422 | G13: 7 | H13: 45537 | M13: 账单户广告费 | N13: 5000.9 | O13: 桃子熊 | P13: 0.079166667 | S13: =SUMIF(M:M,"FF139-KE户-对接",N:N) -> 1100 | T13: FF139-KE户-对接
G14: 8 | H14: 45537 | M14: 账单户广告费 | N14: 5000.95 | O14: 桃子熊 | P14: 0.080555556 | S14: =SUMIF(M:M,"土耳其的代投",N:N) -> 2000 | T14: 土耳其的代投
